Workbook

Sheet Config
A1: Farmley Run Rate Dashboard
A3: Parameter | B3: Value | C3: Type
A4: Days in Month | B4: 30 | C4: EDITABLE ↕
A5: SO Date From | B5: 2026-05-01 | C5: Auto
A6: SO Date To | B6: 2026-05-19 | C6: Auto
A7: Days Elapsed (1st to max SO date) | B7: 19 | C7: Auto
A8: Projection File | B8: May 2026 Sales Projection (5).xlsx | C8: Info
A9: Sales Order File | B9: Custom Sales Order Report (40).xlsx | C9: Info
A10: Generated | B10: 2026-05-21 06:14 | C10: Info
A11: SO Rows Raw / Clean | B11: 23129 / 23042 | C11: Info
A12: Output Rows | B12: 2109 | C12: Info
A15: Color Legend
A16: >120% | B16: Urgent procurement
A17: 100-120% | B17: Plan procurement
A18: 80-100% | B18: On watch
A19: 50-80% | B19: Comfortable
A20: <50% | B20: No pressure
A21: 0% | B21: No orders
A23: Change B4 (Days in Month) → all formula cells recalculate automatically
A24: Expand/collapse grouped rows using [+]/[-] buttons on left margin

Sheet RunRate by Item Name
A1: Month | B1: Year | C1: Last Modified Date | D1: Last Modified Time | E1: Item Code | F1: BOM Item Type | G1: Item Group | H1: Item Name | I1: Item Parent | J1: Conversion Factor | K1: Projection Units | L1: Customer | M1: Total KGs | N1: Customer Group | O1: Origin | P1: Item Type | Q1: New MIS Item Group | R1: Daily Demand(Total KGs) | S1: Daily Demand(Projection Units) | T1: Projected KGs as of period | U1: Projected Units as of period | V1: Actual SO KGs | W1: Actual SO Units | X1: Achievement % KGs | Y1: Achievement % Units | Z1: Diff Proj-SO KGs | AA1: Diff Proj-SO Units | AB1: Run Rate Month-End KGs | AC1: Run Rate Month-End Units
A2: May | B2: 2026 | C2: 29-04-2026 | D2: 0.47064815 | E2: Makhana_7-30163 | F2: FG | G2: Roasted & Flavoured Makhana | H2: Roasted & Flavored Makhana - Tangy Tomato Farmley Composite Jar 83 g | I2: Prasadam Roasted Makhana | J2: 0.083 | K2: 5129 | L2: 3 Customers | M2: 425.71 | N2: Multiple | O2: Purnea | P2: Value Added | Q2: Roasted & Flavoured Makhana | R2: =IF(Config!$B$4>0,M2/Config!$B$4,0) | S2: =IF(Config!$B$4>0,K2/Config!$B$4,0) | T2: =R2*Config!$B$7 | U2: =S2*Config!$B$7 | V2: 35.86 | W2: 432 | X2: =IF(T2>0,V2/T2,0) | Y2: =IF(U2>0,W2/U2,0) | Z2: =T2-V2 | AA2: =U2-W2 | AB2: =IF(Config!$B$7>0,(V2/Config!$B$7)*Config!$B$4,0) | AC2: =IF(Config!$B$7>0,(W2/Config!$B$7)*Config!$B$4,0)
A3: May | B3: 2026 | C3: 29-04-2026 | D3: 0.47064815 | E3: Makhana_7-30163 | F3: FG | G3: Roasted & Flavoured Makhana | H3: Roasted & Flavored Makhana - Tangy Tomato Farmley Composite Jar 83 g | I3: Prasadam Roasted Makhana | J3: 0.083 | K3: 2904 | L3: Canteen Store Department (CSD) | M3: 241.03 | N3: CSD | O3: Purnea | P3: Value Added | Q3: Roasted & Flavoured Makhana | R3: =IF(Config!$B$4>0,M3/Config!$B$4,0) | S3: =IF(Config!$B$4>0,K3/Config!$B$4,0) | T3: =R3*Config!$B$7 | U3: =S3*Config!$B$7 | V3: 0 | W3: 0 | X3: =IF(T3>0,V3/T3,0) | Y3: =IF(U3>0,W3/U3,0) | Z3: =T3-V3 | AA3: =U3-W3 | AB3: =IF(Config!$B$7>0,(V3/Config!$B$7)*Config!$B$4,0) | AC3: =IF(Config!$B$7>0,(W3/Config!$B$7)*Config!$B$4,0)
A4: May | B4: 2026 | C4: 30-04-2026 | D4: 0.69038194 | E4: Makhana_7-30163 | F4: FG | G4: Roasted & Flavoured Makhana | H4: Roasted & Flavored Makhana - Tangy Tomato Farmley Composite Jar 83 g | I4: Prasadam Roasted Makhana | J4: 0.083 | K4: 1225 | L4: Amazon Retail India Private Limited | M4: 101.67 | N4: Amazon Retail India | O4: Purnea | P4: Value Added | Q4: Roasted & Flavoured Makhana | R4: =IF(Config!$B$4>0,M4/Config!$B$4,0) | S4: =IF(Config!$B$4>0,K4/Config!$B$4,0) | T4: =R4*Config!$B$7 | U4: =S4*Config!$B$7 | V4: 0 | W4: 0 | X4: =IF(T4>0,V4/T4,0) | Y4: =IF(U4>0,W4/U4,0) | Z4: =T4-V4 | AA4: =U4-W4 | AB4: =IF(Config!$B$7>0,(V4/Config!$B$7)*Config!$B$4,0) | AC4: =IF(Config!$B$7>0,(W4/Config!$B$7)*Config!$B$4,0)
A5: May | B5: 2026 | C5: 25-04-2026 | D5: 0.62569444 | E5: Makhana_7-30163 | F5: FG | G5: Roasted & Flavoured Makhana | H5: Roasted & Flavored Makhana - Tangy Tomato Farmley Composite Jar 83 g | I5: Prasadam Roasted Makhana | J5: 0.083 | K5: 1000 | L5: Avenue E-Commerce Ltd | M5: 83 | N5: E-Commerce | O5: Purnea | P5: Value Added | Q5: Roasted & Flavoured Makhana | R5: =IF(Config!$B$4>0,M5/Config!$B$4,0) | S5: =IF(Config!$B$4>0,K5/Config!$B$4,0) | T5: =R5*Config!$B$7 | U5: =S5*Config!$B$7 | V5: 35.86 | W5: 432 | X5: =IF(T5>0,V5/T5,0) | Y5: =IF(U5>0,W5/U5,0) | Z5: =T5-V5 | AA5: =U5-W5 | AB5: =IF(Config!$B$7>0,(V5/Config!$B$7)*Config!$B$4,0) | AC5: =IF(Config!$B$7>0,(W5/Config!$B$7)*Config!$B$4,0)
A6: May | B6: 2026 | C6: 29-04-2026 | D6: 0.47065972 | E6: Makhana_7-30166 | F6: FG | G6: Roasted & Flavoured Makhana | H6: Roasted & Flavored Makhana - Mint Farmley Composite Jar 83 g | I6: Prasadam Roasted Makhana | J6: 0.083 | K6: 5329 | L6: 4 Customers | M6: 442.31 | N6: Multiple | O6: Purnea | P6: Value Added | Q6: Roasted & Flavoured Makhana | R6: =IF(Config!$B$4>0,M6/Config!$B$4,0) | S6: =IF(Config!$B$4>0,K6/Config!$B$4,0) | T6: =R6*Config!$B$7 | U6: =S6*Config!$B$7 | V6: 39.84 | W6: 480 | X6: =IF(T6>0,V6/T6,0) | Y6: =IF(U6>0,W6/U6,0) | Z6: =T6-V6 | AA6: =U6-W6 | AB6: =IF(Config!$B$7>0,(V6/Config!$B$7)*Config!$B$4,0) | AC6: =IF(Config!$B$7>0,(W6/Config!$B$7)*Config!$B$4,0)
A7: May | B7: 2026 | C7: 29-04-2026 | D7: 0.47065972 | E7: Makhana_7-30166 | F7: FG | G7: Roasted & Flavoured Makhana | H7: Roasted & Flavored Makhana - Mint Farmley Composite Jar 83 g | I7: Prasadam Roasted Makhana | J7: 0.083 | K7: 2736 | L7: Canteen Store Department (CSD) | M7: 227.09 | N7: CSD | O7: Purnea | P7: Value Added | Q7: Roasted & Flavoured Makhana | R7: =IF(Config!$B$4>0,M7/Config!$B$4,0) | S7: =IF(Config!$B$4>0,K7/Config!$B$4,0) | T7: =R7*Config!$B$7 | U7: =S7*Config!$B$7 | V7: 0 | W7: 0 | X7: =IF(T7>0,V7/T7,0) | Y7: =IF(U7>0,W7/U7,0) | Z7: =T7-V7 | AA7: =U7-W7 | AB7: =IF(Config!$B$7>0,(V7/Config!$B$7)*Config!$B$4,0) | AC7: =IF(Config!$B$7>0,(W7/Config!$B$7)*Config!$B$4,0)
A8: May | B8: 2026 | C8: 30-04-2026 | D8: 0.69038194 | E8: Makhana_7-30166 | F8: FG | G8: Roasted & Flavoured Makhana | H8: Roasted & Flavored Makhana - Mint Farmley Composite Jar 83 g | I8: Prasadam Roasted Makhana | J8: 0.083 | K8: 1281 | L8: Amazon Retail India Private Limited | M8: 106.32 | N8: Amazon Retail India | O8: Purnea | P8: Value Added | Q8: Roasted & Flavoured Makhana | R8: =IF(Config!$B$4>0,M8/Config!$B$4,0) | S8: =IF(Config!$B$4>0,K8/Config!$B$4,0) | T8: =R8*Config!$B$7 | U8: =S8*Config!$B$7 | V8: 0 | W8: 0 | X8: =IF(T8>0,V8/T8,0) | Y8: =IF(U8>0,W8/U8,0) | Z8: =T8-V8 | AA8: =U8-W8 | AB8: =IF(Config!$B$7>0,(V8/Config!$B$7)*Config!$B$4,0) | AC8: =IF(Config!$B$7>0,(W8/Config!$B$7)*Config!$B$4,0)
A9: May | B9: 2026 | C9: 25-04-2026 | D9: 0.62569444 | E9: Makhana_7-30166 | F9: FG | G9: Roasted & Flavoured Makhana | H9: Roasted & Flavored Makhana - Mint Farmley Composite Jar 83 g | I9: Prasadam Roasted Makhana | J9: 0.083 | K9: 1000 | L9: Avenue E-Commerce Ltd | M9: 83 | N9: E-Commerce | O9: Purnea | P9: Value Added | Q9: Roasted & Flavoured Makhana | R9: =IF(Config!$B$4>0,M9/Config!$B$4,0) | S9: =IF(Config!$B$4>0,K9/Config!$B$4,0) | T9: =R9*Config!$B$7 | U9: =S9*Config!$B$7 | V9: 35.86 | W9: 432 | X9: =IF(T9>0,V9/T9,0) | Y9: =IF(U9>0,W9/U9,0) | Z9: =T9-V9 | AA9: =U9-W9 | AB9: =IF(Config!$B$7>0,(V9/Config!$B$7)*Config!$B$4,0) | AC9: =IF(Config!$B$7>0,(W9/Config!$B$7)*Config!$B$4,0)
A10: May | B10: 2026 | C10: 25-04-2026 | D10: 0.72665509 | E10: Makhana_7-30166 | F10: FG | G10: Roasted & Flavoured Makhana | H10: Roasted & Flavored Makhana - Mint Farmley Composite Jar 83 g | I10: Prasadam Roasted Makhana | J10: 0.083 | K10: 312 | L10: Avenue Supermarts Ltd | M10: 25.9 | N10: Modern Trade | O10: Purnea | P10: Value Added | Q10: Roasted & Flavoured Makhana | R10: =IF(Config!$B$4>0,M10/Config!$B$4,0) | S10: =IF(Config!$B$4>0,K10/Config!$B$4,0) | T10: =R10*Config!$B$7 | U10: =S10*Config!$B$7 | V10: 3.98 | W10: 48 | X10: =IF(T10>0,V10/T10,0) | Y10: =IF(U10>0,W10/U10,0) | Z10: =T10-V10 | AA10: =U10-W10 | AB10: =IF(Config!$B$7>0,(V10/Config!$B$7)*Config!$B$4,0) | AC10: =IF(Config!$B$7>0,(W10/Config!$B$7)*Config!$B$4,0)
A11: May | B11: 2026 | C11: 29-04-2026 | D11: 0.47065972 | E11: Makhana_7-30167 | F11: FG | G11: Roasted & Flavoured Makhana | H11: Roasted & Salted Makhana Farmley Composite Jar 83 g | I11: Prasadam Roasted Makhana | J11: 0.083 | K11: 9105 | L11: 4 Customers | M11: 755.72 | N11: Multiple | O11: Purnea | P11: Value Added | Q11: Roasted & Flavoured Makhana | R11: =IF(Config!$B$4>0,M11/Config!$B$4,0) | S11: =IF(Config!$B$4>0,K11/Config!$B$4,0) | T11: =R11*Config!$B$7 | U11: =S11*Config!$B$7 | V11: 93.62 | W11: 1128 | X11: =IF(T11>0,V11/T11,0) | Y11: =IF(U11>0,W11/U11,0) | Z11: =T11-V11 | AA11: =U11-W11 | AB11: =IF(Config!$B$7>0,(V11/Config!$B$7)*Config!$B$4,0) | AC11: =IF(Config!$B$7>0,(W11/Config!$B$7)*Config!$B$4,0)
A12: May | B12: 2026 | C12: 29-04-2026 | D12: 0.47065972 | E12: Makhana_7-30167 | F12: FG | G12: Roasted & Flavoured Makhana | H12: Roasted & Salted Makhana Farmley Composite Jar 83 g | I12: Prasadam Roasted Makhana | J12: 0.083 | K12: 2448 | L12: Canteen Store Department (CSD) | M12: 203.18 | N12: CSD | O12: Purnea | P12: Value Added | Q12: Roasted & Flavoured Makhana | R12: =IF(Config!$B$4>0,M12/Config!$B$4,0) | S12: =IF(Config!$B$4>0,K12/Config!$B$4,0) | T12: =R12*Config!$B$7 | U12: =S12*Config!$B$7 | V12: 0 | W12: 0 | X12: =IF(T12>0,V12/T12,0) | Y12: =IF(U12>0,W12/U12,0) | Z12: =T12-V12 | AA12: =U12-W12 | AB12: =IF(Config!$B$7>0,(V12/Config!$B$7)*Config!$B$4,0) | AC12: =IF(Config!$B$7>0,(W12/Config!$B$7)*Config!$B$4,0)
A13: May | B13: 2026 | C13: 30-04-2026 | D13: 0.69040509 | E13: Makhana_7-30167 | F13: FG | G13: Roasted & Flavoured Makhana | H13: Roasted & Salted Makhana Farmley Composite Jar 83 g | I13: Prasadam Roasted Makhana | J13: 0.083 | K13: 4545 | L13: Amazon Retail India Private Limited | M13: 377.24 | N13: Amazon Retail India | O13: Purnea | P13: Value Added | Q13: Roasted & Flavoured Makhana | R13: =IF(Config!$B$4>0,M13/Config!$B$4,0) | S13: =IF(Config!$B$4>0,K13/Config!$B$4,0) | T13: =R13*Config!$B$7 | U13: =S13*Config!$B$7 | V13: 0 | W13: 0 | X13: =IF(T13>0,V13/T13,0) | Y13: =IF(U13>0,W13/U13,0) | Z13: =T13-V13 | AA13: =U13-W13 | AB13: =IF(Config!$B$7>0,(V13/Config!$B$7)*Config!$B$4,0) | AC13: =IF(Config!$B$7>0,(W13/Config!$B$7)*Config!$B$4,0)
... A30: May | B30: 2026 | C30: 25-04-2026 | D30: 0.7266088 | E30: Cashewnut_3-1987 | F30: FG | G30: Cashew | H30: Premium W320 Cashew Farmley Standee Pouch 500 g | I30: Premium W320 Cashew | J30: 0.5 | K30: 100 | L30: Wal-Mart India Private Limited | M30: 50 | N30: Modern Trade | O30: Udupi | P30: KVI | Q30: Cashew | R30: =IF(Config!$B$4>0,M30/Config!$B$4,0) | S30: =IF(Config!$B$4>0,K30/Config!$B$4,0) | T30: =R30*Config!$B$7 | U30: =S30*Config!$B$7 | V30: 100 | W30: 200 | X30: =IF(T30>0,V30/T30,0) | Y30: =IF(U30>0,W30/U30,0) | Z30: =T30-V30 | AA30: =U30-W30 | AB30: =IF(Config!$B$7>0,(V30/Config!$B$7)*Config!$B$4,0) | AC30: =IF(Config!$B$7>0,(W30/Config!$B$7)*Config!$B$4,0)
E31: Cashewnut_3-1987 | G31: Cashewnut | H31: Premium W320 Cashew Farmley Standee Pouch 500 g | J31: 0 | K31: 0 | L31: CPC - C P C Master Canteen -Khargone -Madhya Pradesh -451115 | M31: 0 | N31: CPC KPKB | O31: Udupi | Q31: Cashew | R31: =IF(Config!$B$4>0,M31/Config!$B$4,0) | S31: =IF(Config!$B$4>0,K31/Config!$B$4,0) | T31: =R31*Config!$B$7 | U31: =S31*Config!$B$7 | V31: 30 | W31: 60 | X31: =IF(T31>0,V31/T31,0) | Y31: =IF(U31>0,W31/U31,0) | Z31: =T31-V31 | AA31: =U31-W31 | AB31: =IF(Config!$B$7>0,(V31/Config!$B$7)*Config!$B$4,0) | AC31: =IF(Config!$B$7>0,(W31/Config!$B$7)*Config!$B$4,0)
E32: Cashewnut_3-1987 | G32: Cashewnut | H32: Premium W320 Cashew Farmley Standee Pouch 500 g | J32: 0 | K32: 0 | L32: CPC - Canteen Officer Master Canteen Frontier HQR SSB Lucknow | M32: 0 | N32: CPC KPKB | O32: Udupi | Q32: Cashew | R32: =IF(Config!$B$4>0,M32/Config!$B$4,0) | S32: =IF(Config!$B$4>0,K32/Config!$B$4,0) | T32: =R32*Config!$B$7 | U32: =S32*Config!$B$7 | V32: 32 | W32: 64 | X32: =IF(T32>0,V32/T32,0) | Y32: =IF(U32>0,W32/U32,0) | Z32: =T32-V32 | AA32: =U32-W32 | AB32: =IF(Config!$B$7>0,(V32/Config!$B$7)*Config!$B$4,0) | AC32: =IF(Config!$B$7>0,(W32/Config!$B$7)*Config!$B$4,0)
E33: Cashewnut_3-1987 | G33: Cashewnut | H33: Premium W320 Cashew Farmley Standee Pouch 500 g | J33: 0 | K33: 0 | L33: CPC - Central Police Canteen Cisf Unit Kopt Kolkata | M33: 0 | N33: CPC KPKB | O33: Udupi | Q33: Cashew | R33: =IF(Config!$B$4>0,M33/Config!$B$4,0) | S33: =IF(Config!$B$4>0,K33/Config!$B$4,0) | T33: =R33*Config!$B$7 | U33: =S33*Config!$B$7 | V33: 190 | W33: 380 | X33: =IF(T33>0,V33/T33,0) | Y33: =IF(U33>0,W33/U33,0) | Z33: =T33-V33 | AA33: =U33-W33 | AB33: =IF(Config!$B$7>0,(V33/Config!$B$7)*Config!$B$4,0) | AC33: =IF(Config!$B$7>0,(W33/Config!$B$7)*Config!$B$4,0)
E34: Cashewnut_3-1987 | G34: Cashewnut | H34: Premium W320 Cashew Farmley Standee Pouch 500 g | J34: 0 | K34: 0 | L34: CPC - Commandant 57th Bn SSB | M34: 0 | N34: CPC KPKB | O34: Udupi | Q34: Cashew | R34: =IF(Config!$B$4>0,M34/Config!$B$4,0) | S34: =IF(Config!$B$4>0,K34/Config!$B$4,0) | T34: =R34*Config!$B$7 | U34: =S34*Config!$B$7 | V34: 200 | W34: 400 | X34: =IF(T34>0,V34/T34,0) | Y34: =IF(U34>0,W34/U34,0) | Z34: =T34-V34 | AA34: =U34-W34 | AB34: =IF(Config!$B$7>0,(V34/Config!$B$7)*Config!$B$4,0) | AC34: =IF(Config!$B$7>0,(W34/Config!$B$7)*Config!$B$4,0)
E35: Cashewnut_3-1987 | G35: Cashewnut | H35: Premium W320 Cashew Farmley Standee Pouch 500 g | J35: 0 | K35: 0 | L35: CPC - KPKB Master Canteen Dhanbad | M35: 0 | N35: CPC KPKB | O35: Udupi | Q35: Cashew | R35: =IF(Config!$B$4>0,M35/Config!$B$4,0) | S35: =IF(Config!$B$4>0,K35/Config!$B$4,0) | T35: =R35*Config!$B$7 | U35: =S35*Config!$B$7 | V35: 200 | W35: 400 | X35: =IF(T35>0,V35/T35,0) | Y35: =IF(U35>0,W35/U35,0) | Z35: =T35-V35 | AA35: =U35-W35 | AB35: =IF(Config!$B$7>0,(V35/Config!$B$7)*Config!$B$4,0) | AC35: =IF(Config!$B$7>0,(W35/Config!$B$7)*Config!$B$4,0)
E36: Cashewnut_3-1987 | G36: Cashewnut | H36: Premium W320 Cashew Farmley Standee Pouch 500 g | J36: 0 | K36: 0 | L36: CPC - Kendriya Police Kalyan Bhandar - HP | M36: 0 | N36: CPC KPKB | O36: Udupi | Q36: Cashew | R36: =IF(Config!$B$4>0,M36/Config!$B$4,0) | S36: =IF(Config!$B$4>0,K36/Config!$B$4,0) | T36: =R36*Config!$B$7 | U36: =S36*Config!$B$7 | V36: 100 | W36: 200 | X36: =IF(T36>0,V36/T36,0) | Y36: =IF(U36>0,W36/U36,0) | Z36: =T36-V36 | AA36: =U36-W36 | AB36: =IF(Config!$B$7>0,(V36/Config!$B$7)*Config!$B$4,0) | AC36: =IF(Config!$B$7>0,(W36/Config!$B$7)*Config!$B$4,0)
E37: Cashewnut_3-1987 | G37: Cashewnut | H37: Premium W320 Cashew Farmley Standee Pouch 500 g | J37: 0 | K37: 0 | L37: CPC - Kendriya Police Kalyan Master Bhandar | M37: 0 | N37: CPC KPKB | O37: Udupi | Q37: Cashew | R37: =IF(Config!$B$4>0,M37/Config!$B$4,0) | S37: =IF(Config!$B$4>0,K37/Config!$B$4,0) | T37: =R37*Config!$B$7 | U37: =S37*Config!$B$7 | V37: 30 | W37: 60 | X37: =IF(T37>0,V37/T37,0) | Y37: =IF(U37>0,W37/U37,0) | Z37: =T37-V37 | AA37: =U37-W37 | AB37: =IF(Config!$B$7>0,(V37/Config!$B$7)*Config!$B$4,0) | AC37: =IF(Config!$B$7>0,(W37/Config!$B$7)*Config!$B$4,0)
E38: Cashewnut_3-1987 | G38: Cashewnut | H38: Premium W320 Cashew Farmley Standee Pouch 500 g | J38: 0 | K38: 0 | L38: CPC - Master Bhandar | M38: 0 | N38: CPC KPKB | O38: Udupi | Q38: Cashew | R38: =IF(Config!$B$4>0,M38/Config!$B$4,0) | S38: =IF(Config!$B$4>0,K38/Config!$B$4,0) | T38: =R38*Config!$B$7 | U38: =S38*Config!$B$7 | V38: 60 | W38: 120 | X38: =IF(T38>0,V38/T38,0) | Y38: =IF(U38>0,W38/U38,0) | Z38: =T38-V38 | AA38: =U38-W38 | AB38: =IF(Config!$B$7>0,(V38/Config!$B$7)*Config!$B$4,0) | AC38: =IF(Config!$B$7>0,(W38/Config!$B$7)*Config!$B$4,0)
E39: Cashewnut_3-1987 | G39: Cashewnut | H39: Premium W320 Cashew Farmley Standee Pouch 500 g | J39: 0 | K39: 0 | L39: CPC - Master Bhandar - Haryana | M39: 0 | N39: CPC KPKB | O39: Udupi | Q39: Cashew | R39: =IF(Config!$B$4>0,M39/Config!$B$4,0) | S39: =IF(Config!$B$4>0,K39/Config!$B$4,0) | T39: =R39*Config!$B$7 | U39: =S39*Config!$B$7 | V39: 30 | W39: 60 | X39: =IF(T39>0,V39/T39,0) | Y39: =IF(U39>0,W39/U39,0) | Z39: =T39-V39 | AA39: =U39-W39 | AB39: =IF(Config!$B$7>0,(V39/Config!$B$7)*Config!$B$4,0) | AC39: =IF(Config!$B$7>0,(W39/Config!$B$7)*Config!$B$4,0)
E40: Cashewnut_3-1987 | G40: Cashewnut | H40: Premium W320 Cashew Farmley Standee Pouch 500 g | J40: 0 | K40: 0 | L40: CPC - Master Bhandar CRPF HQ CGO | M40: 0 | N40: CPC KPKB | O40: Udupi | Q40: Cashew | R40: =IF(Config!$B$4>0,M40/Config!$B$4,0) | S40: =IF(Config!$B$4>0,K40/Config!$B$4,0) | T40: =R40*Config!$B$7 | U40: =S40*Config!$B$7 | V40: 130 | W40: 260 | X40: =IF(T40>0,V40/T40,0) | Y40: =IF(U40>0,W40/U40,0) | Z40: =T40-V40 | AA40: =U40-W40 | AB40: =IF(Config!$B$7>0,(V40/Config!$B$7)*Config!$B$4,0) | AC40: =IF(Config!$B$7>0,(W40/Config!$B$7)*Config!$B$4,0)
E41: Cashewnut_3-1987 | G41: Cashewnut | H41: Premium W320 Cashew Farmley Standee Pouch 500 g | J41: 0 | K41: 0 | L41: CPC - Master Bhandar Kendriya Police Kalyan Bhandar | M41: 0 | N41: CPC KPKB | O41: Udupi | Q41: Cashew | R41: =IF(Config!$B$4>0,M41/Config!$B$4,0) | S41: =IF(Config!$B$4>0,K41/Config!$B$4,0) | T41: =R41*Config!$B$7 | U41: =S41*Config!$B$7 | V41: 20 | W41: 40 | X41: =IF(T41>0,V41/T41,0) | Y41: =IF(U41>0,W41/U41,0) | Z41: =T41-V41 | AA41: =U41-W41 | AB41: =IF(Config!$B$7>0,(V41/Config!$B$7)*Config!$B$4,0) | AC41: =IF(Config!$B$7>0,(W41/Config!$B$7)*Config!$B$4,0)
E42: Cashewnut_3-1987 | G42: Cashewnut | H42: Premium W320 Cashew Farmley Standee Pouch 500 g | J42: 0 | K42: 0 | L42: CPC - Master Bhander Gc-1 CRPF Ajmer | M42: 0 | N42: CPC KPKB | O42: Udupi | Q42: Cashew | R42: =IF(Config!$B$4>0,M42/Config!$B$4,0) | S42: =IF(Config!$B$4>0,K42/Config!$B$4,0) | T42: =R42*Config!$B$7 | U42: =S42*Config!$B$7 | V42: 150 | W42: 300 | X42: =IF(T42>0,V42/T42,0) | Y42: =IF(U42>0,W42/U42,0) | Z42: =T42-V42 | AA42: =U42-W42 | AB42: =IF(Config!$B$7>0,(V42/Config!$B$7)*Config!$B$4,0) | AC42: =IF(Config!$B$7>0,(W42/Config!$B$7)*Config!$B$4,0)
... E72: Cashewnut_3-1987 | G72: Cashewnut | H72: Premium W320 Cashew Farmley Standee Pouch 500 g | J72: 0 | K72: 0 | L72: PJTJ Technologies Private Limited | M72: 0 | N72: Quick Commerce | O72: Udupi | Q72: Cashew | R72: =IF(Config!$B$4>0,M72/Config!$B$4,0) | S72: =IF(Config!$B$4>0,K72/Config!$B$4,0) | T72: =R72*Config!$B$7 | U72: =S72*Config!$B$7 | V72: 30 | W72: 60 | X72: =IF(T72>0,V72/T72,0) | Y72: =IF(U72>0,W72/U72,0) | Z72: =T72-V72 | AA72: =U72-W72 | AB72: =IF(Config!$B$7>0,(V72/Config!$B$7)*Config!$B$4,0) | AC72: =IF(Config!$B$7>0,(W72/Config!$B$7)*Config!$B$4,0)
A73: May | B73: 2026 | C73: 29-04-2026 | D73: 0.47065972 | E73: Seeds_11-2541 | F73: FG | G73: Chia Seeds | H73: Premium Chia Seeds Farmley Standee Pouch 200 g | I73: Premium Chia Seeds | J73: 0.2 | K73: 182029.61 | L73: 47 Customers | M73: 36405.92 | N73: Multiple | O73: Indore | P73: KVI | Q73: Chia Seeds | R73: =IF(Config!$B$4>0,M73/Config!$B$4,0) | S73: =IF(Config!$B$4>0,K73/Config!$B$4,0) | T73: =R73*Config!$B$7 | U73: =S73*Config!$B$7 | V73: 21282 | W73: 106410 | X73: =IF(T73>0,V73/T73,0) | Y73: =IF(U73>0,W73/U73,0) | Z73: =T73-V73 | AA73: =U73-W73 | AB73: =IF(Config!$B$7>0,(V73/Config!$B$7)*Config!$B$4,0) | AC73: =IF(Config!$B$7>0,(W73/Config!$B$7)*Config!$B$4,0)
A74: May | B74: 2026 | C74: 29-04-2026 | D74: 0.47065972 | E74: Seeds_11-2541 | F74: FG | G74: Chia Seeds | H74: Premium Chia Seeds Farmley Standee Pouch 200 g | I74: Premium Chia Seeds | J74: 0.2 | K74: 1740 | L74: Canteen Store Department (CSD) | M74: 348 | N74: CSD | O74: Indore | P74: KVI | Q74: Chia Seeds | R74: =IF(Config!$B$4>0,M74/Config!$B$4,0) | S74: =IF(Config!$B$4>0,K74/Config!$B$4,0) | T74: =R74*Config!$B$7 | U74: =S74*Config!$B$7 | V74: 0 | W74: 0 | X74: =IF(T74>0,V74/T74,0) | Y74: =IF(U74>0,W74/U74,0) | Z74: =T74-V74 | AA74: =U74-W74 | AB74: =IF(Config!$B$7>0,(V74/Config!$B$7)*Config!$B$4,0) | AC74: =IF(Config!$B$7>0,(W74/Config!$B$7)*Config!$B$4,0)
A75: May | B75: 2026 | C75: 29-04-2026 | D75: 0.4706713 | E75: Seeds_11-2541 | F75: FG | G75: Chia Seeds | H75: Premium Chia Seeds Farmley Standee Pouch 200 g | I75: Premium Chia Seeds | J75: 0.2 | K75: 3000 | L75: CPC KPKB | M75: 600 | N75: CPC | O75: Indore | P75: KVI | Q75: Chia Seeds | R75: =IF(Config!$B$4>0,M75/Config!$B$4,0) | S75: =IF(Config!$B$4>0,K75/Config!$B$4,0) | T75: =R75*Config!$B$7 | U75: =S75*Config!$B$7 | V75: 0 | W75: 0 | X75: =IF(T75>0,V75/T75,0) | Y75: =IF(U75>0,W75/U75,0) | Z75: =T75-V75 | AA75: =U75-W75 | AB75: =IF(Config!$B$7>0,(V75/Config!$B$7)*Config!$B$4,0) | AC75: =IF(Config!$B$7>0,(W75/Config!$B$7)*Config!$B$4,0)
A76: May | B76: 2026 | C76: 29-04-2026 | D76: 0.53008102 | E76: Seeds_11-2541 | F76: FG | G76: Chia Seeds | H76: Premium Chia Seeds Farmley Standee Pouch 200 g | I76: Premium Chia Seeds | J76: 0.2 | K76: 4000 | L76: Metro Cash & Carry India Private Limited | M76: 800 | N76: Modern Trade | O76: Indore | P76: KVI | Q76: Chia Seeds | R76: =IF(Config!$B$4>0,M76/Config!$B$4,0) | S76: =IF(Config!$B$4>0,K76/Config!$B$4,0) | T76: =R76*Config!$B$7 | U76: =S76*Config!$B$7 | V76: 390 | W76: 1950 | X76: =IF(T76>0,V76/T76,0) | Y76: =IF(U76>0,W76/U76,0) | Z76: =T76-V76 | AA76: =U76-W76 | AB76: =IF(Config!$B$7>0,(V76/Config!$B$7)*Config!$B$4,0) | AC76: =IF(Config!$B$7>0,(W76/Config!$B$7)*Config!$B$4,0)
A77: May | B77: 2026 | C77: 29-04-2026 | D77: 0.62038194 | E77: Seeds_11-2541 | F77: FG | G77: Chia Seeds | H77: Premium Chia Seeds Farmley Standee Pouch 200 g | I77: Premium Chia Seeds | J77: 0.2 | K77: 16330 | L77: Amazon Retail India Private Limited | M77: 3266 | N77: Amazon Retail India | O77: Indore | P77: KVI | Q77: Chia Seeds | R77: =IF(Config!$B$4>0,M77/Config!$B$4,0) | S77: =IF(Config!$B$4>0,K77/Config!$B$4,0) | T77: =R77*Config!$B$7 | U77: =S77*Config!$B$7 | V77: 2370 | W77: 11850 | X77: =IF(T77>0,V77/T77,0) | Y77: =IF(U77>0,W77/U77,0) | Z77: =T77-V77 | AA77: =U77-W77 | AB77: =IF(Config!$B$7>0,(V77/Config!$B$7)*Config!$B$4,0) | AC77: =IF(Config!$B$7>0,(W77/Config!$B$7)*Config!$B$4,0)
A78: May | B78: 2026 | C78: 29-04-2026 | D78: 0.68864583 | E78: Seeds_11-2541 | F78: FG | G78: Chia Seeds | H78: Premium Chia Seeds Farmley Standee Pouch 200 g | I78: Premium Chia Seeds | J78: 0.2 | K78: 574.61 | L78: Farmley Website B2C | M78: 114.92 | N78: Own Website | O78: Indore | P78: KVI | Q78: Chia Seeds | R78: =IF(Config!$B$4>0,M78/Config!$B$4,0) | S78: =IF(Config!$B$4>0,K78/Config!$B$4,0) | T78: =R78*Config!$B$7 | U78: =S78*Config!$B$7 | V78: 0 | W78: 0 | X78: =IF(T78>0,V78/T78,0) | Y78: =IF(U78>0,W78/U78,0) | Z78: =T78-V78 | AA78: =U78-W78 | AB78: =IF(Config!$B$7>0,(V78/Config!$B$7)*Config!$B$4,0) | AC78: =IF(Config!$B$7>0,(W78/Config!$B$7)*Config!$B$4,0)
A79: May | B79: 2026 | C79: 27-04-2026 | D79: 0.83001157 | E79: Seeds_11-2541 | F79: FG | G79: Chia Seeds | H79: Premium Chia Seeds Farmley Standee Pouch 200 g | I79: Premium Chia Seeds | J79: 0.2 | K79: 7000 | L79: GT Retail | M79: 1400 | N79: Category A | O79: Indore | P79: KVI | Q79: Chia Seeds | R79: =IF(Config!$B$4>0,M79/Config!$B$4,0) | S79: =IF(Config!$B$4>0,K79/Config!$B$4,0) | T79: =R79*Config!$B$7 | U79: =S79*Config!$B$7 | V79: 780 | W79: 3900 | X79: =IF(T79>0,V79/T79,0) | Y79: =IF(U79>0,W79/U79,0) | Z79: =T79-V79 | AA79: =U79-W79 | AB79: =IF(Config!$B$7>0,(V79/Config!$B$7)*Config!$B$4,0) | AC79: =IF(Config!$B$7>0,(W79/Config!$B$7)*Config!$B$4,0)
A80: May | B80: 2026 | C80: 25-04-2026 | D80: 0.59434028 | E80: Seeds_11-2541 | F80: FG | G80: Chia Seeds | H80: Premium Chia Seeds Farmley Standee Pouch 200 g | I80: Premium Chia Seeds | J80: 0.2 | K80: 19000 | L80: Flipkart India Private Limited | M80: 3800 | N80: E-Commerce | O80: Indore | P80: KVI | Q80: Chia Seeds | R80: =IF(Config!$B$4>0,M80/Config!$B$4,0) | S80: =IF(Config!$B$4>0,K80/Config!$B$4,0) | T80: =R80*Config!$B$7 | U80: =S80*Config!$B$7 | V80: 4068 | W80: 20340 | X80: =IF(T80>0,V80/T80,0) | Y80: =IF(U80>0,W80/U80,0) | Z80: =T80-V80 | AA80: =U80-W80 | AB80: =IF(Config!$B$7>0,(V80/Config!$B$7)*Config!$B$4,0) | AC80: =IF(Config!$B$7>0,(W80/Config!$B$7)*Config!$B$4,0)
A81: May | B81: 2026 | C81: 25-04-2026 | D81: 0.62571759 | E81: Seeds_11-2541 | F81: FG | G81: Chia Seeds | H81: Premium Chia Seeds Farmley Standee Pouch 200 g | I81: Premium Chia Seeds | J81: 0.2 | K81: 2500 | L81: Avenue E-Commerce Ltd | M81: 500 | N81: E-Commerce | O81: Indore | P81: KVI | Q81: Chia Seeds | R81: =IF(Config!$B$4>0,M81/Config!$B$4,0) | S81: =IF(Config!$B$4>0,K81/Config!$B$4,0) | T81: =R81*Config!$B$7 | U81: =S81*Config!$B$7 | V81: 108 | W81: 540 | X81: =IF(T81>0,V81/T81,0) | Y81: =IF(U81>0,W81/U81,0) | Z81: =T81-V81 | AA81: =U81-W81 | AB81: =IF(Config!$B$7>0,(V81/Config!$B$7)*Config!$B$4,0) | AC81: =IF(Config!$B$7>0,(W81/Config!$B$7)*Config!$B$4,0)
A82: May | B82: 2026 | C82: 25-04-2026 | D82: 0.63921296 | E82: Seeds_11-2541 | F82: FG | G82: Chia Seeds | H82: Premium Chia Seeds Farmley Standee Pouch 200 g | I82: Premium Chia Seeds | J82: 0.2 | K82: 8200 | L82: Flipkart B2C | M82: 1640 | N82: E-Commerce Dropship | O82: Indore | P82: KVI | Q82: Chia Seeds | R82: =IF(Config!$B$4>0,M82/Config!$B$4,0) | S82: =IF(Config!$B$4>0,K82/Config!$B$4,0) | T82: =R82*Config!$B$7 | U82: =S82*Config!$B$7 | V82: 0 | W82: 0 | X82: =IF(T82>0,V82/T82,0) | Y82: =IF(U82>0,W82/U82,0) | Z82: =T82-V82 | AA82: =U82-W82 | AB82: =IF(Config!$B$7>0,(V82/Config!$B$7)*Config!$B$4,0) | AC82: =IF(Config!$B$7>0,(W82/Config!$B$7)*Config!$B$4,0)
A83: May | B83: 2026 | C83: 25-04-2026 | D83: 0.6449537 | E83: Seeds_11-2541 | F83: FG | G83: Chia Seeds | H83: Premium Chia Seeds Farmley Standee Pouch 200 g | I83: Premium Chia Seeds | J83: 0.2 | K83: 2500 | L83: INNOVATIVE RETAIL CONCEPTS PRIVATE LIMITED | M83: 500 | N83: Quick Commerce | O83: Indore | P83: KVI | Q83: Chia Seeds | R83: =IF(Config!$B$4>0,M83/Config!$B$4,0) | S83: =IF(Config!$B$4>0,K83/Config!$B$4,0) | T83: =R83*Config!$B$7 | U83: =S83*Config!$B$7 | V83: 480 | W83: 2400 | X83: =IF(T83>0,V83/T83,0) | Y83: =IF(U83>0,W83/U83,0) | Z83: =T83-V83 | AA83: =U83-W83 | AB83: =IF(Config!$B$7>0,(V83/Config!$B$7)*Config!$B$4,0) | AC83: =IF(Config!$B$7>0,(W83/Config!$B$7)*Config!$B$4,0)
A84: May | B84: 2026 | C84: 25-04-2026 | D84: 0.65229167 | E84: Seeds_11-2541 | F84: FG | G84: Chia Seeds | H84: Premium Chia Seeds Farmley Standee Pouch 200 g | I84: Premium Chia Seeds | J84: 0.2 | K84: 1600 | L84: Reliance Retail Limited _Milk Basket | M84: 320 | N84: Quick Commerce | O84: Indore | P84: KVI | Q84: Chia Seeds | R84: =IF(Config!$B$4>0,M84/Config!$B$4,0) | S84: =IF(Config!$B$4>0,K84/Config!$B$4,0) | T84: =R84*Config!$B$7 | U84: =S84*Config!$B$7 | V84: 114 | W84: 570 | X84: =IF(T84>0,V84/T84,0) | Y84: =IF(U84>0,W84/U84,0) | Z84: =T84-V84 | AA84: =U84-W84 | AB84: =IF(Config!$B$7>0,(V84/Config!$B$7)*Config!$B$4,0) | AC84: =IF(Config!$B$7>0,(W84/Config!$B$7)*Config!$B$4,0)
... A93: May | B93: 2026 | C93: 25-04-2026 | D93: 0.72672454 | E93: Seeds_11-2541 | F93: FG | G93: Chia Seeds | H93: Premium Chia Seeds Farmley Standee Pouch 200 g | I93: Premium Chia Seeds | J93: 0.2 | K93: 180 | L93: Natures Basket Limited | M93: 36 | N93: Modern Trade | O93: Indore | P93: KVI | Q93: Chia Seeds | R93: =IF(Config!$B$4>0,M93/Config!$B$4,0) | S93: =IF(Config!$B$4>0,K93/Config!$B$4,0) | T93: =R93*Config!$B$7 | U93: =S93*Config!$B$7 | V93: 0 | W93: 0 | X93: =IF(T93>0,V93/T93,0) | Y93: =IF(U93>0,W93/U93,0) | Z93: =T93-V93 | AA93: =U93-W93 | AB93: =IF(Config!$B$7>0,(V93/Config!$B$7)*Config!$B$4,0) | AC93: =IF(Config!$B$7>0,(W93/Config!$B$7)*Config!$B$4,0)
E94: Seeds_11-2541 | G94: Seeds | H94: Premium Chia Seeds Farmley Standee Pouch 200 g | J94: 0 | K94: 0 | L94: CPC - Canteen Officer Master Canteen Frontier HQR SSB Lucknow | M94: 0 | N94: CPC KPKB | O94: Indore | Q94: Chia Seeds | R94: =IF(Config!$B$4>0,M94/Config!$B$4,0) | S94: =IF(Config!$B$4>0,K94/Config!$B$4,0) | T94: =R94*Config!$B$7 | U94: =S94*Config!$B$7 | V94: 6 | W94: 30 | X94: =IF(T94>0,V94/T94,0) | Y94: =IF(U94>0,W94/U94,0) | Z94: =T94-V94 | AA94: =U94-W94 | AB94: =IF(Config!$B$7>0,(V94/Config!$B$7)*Config!$B$4,0) | AC94: =IF(Config!$B$7>0,(W94/Config!$B$7)*Config!$B$4,0)
E95: Seeds_11-2541 | G95: Seeds | H95: Premium Chia Seeds Farmley Standee Pouch 200 g | J95: 0 | K95: 0 | L95: CPC - Central Police Canteen Cisf Unit Kopt Kolkata | M95: 0 | N95: CPC KPKB | O95: Indore | Q95: Chia Seeds | R95: =IF(Config!$B$4>0,M95/Config!$B$4,0) | S95: =IF(Config!$B$4>0,K95/Config!$B$4,0) | T95: =R95*Config!$B$7 | U95: =S95*Config!$B$7 | V95: 36 | W95: 180 | X95: =IF(T95>0,V95/T95,0) | Y95: =IF(U95>0,W95/U95,0) | Z95: =T95-V95 | AA95: =U95-W95 | AB95: =IF(Config!$B$7>0,(V95/Config!$B$7)*Config!$B$4,0) | AC95: =IF(Config!$B$7>0,(W95/Config!$B$7)*Config!$B$4,0)
E96: Seeds_11-2541 | G96: Seeds | H96: Premium Chia Seeds Farmley Standee Pouch 200 g | J96: 0 | K96: 0 | L96: CPC - Commandant 57th Bn SSB | M96: 0 | N96: CPC KPKB | O96: Indore | Q96: Chia Seeds | R96: =IF(Config!$B$4>0,M96/Config!$B$4,0) | S96: =IF(Config!$B$4>0,K96/Config!$B$4,0) | T96: =R96*Config!$B$7 | U96: =S96*Config!$B$7 | V96: 12 | W96: 60 | X96: =IF(T96>0,V96/T96,0) | Y96: =IF(U96>0,W96/U96,0) | Z96: =T96-V96 | AA96: =U96-W96 | AB96: =IF(Config!$B$7>0,(V96/Config!$B$7)*Config!$B$4,0) | AC96: =IF(Config!$B$7>0,(W96/Config!$B$7)*Config!$B$4,0)
E97: Seeds_11-2541 | G97: Seeds | H97: Premium Chia Seeds Farmley Standee Pouch 200 g | J97: 0 | K97: 0 | L97: CPC - KPKB Master Canteen Dhanbad | M97: 0 | N97: CPC KPKB | O97: Indore | Q97: Chia Seeds | R97: =IF(Config!$B$4>0,M97/Config!$B$4,0) | S97: =IF(Config!$B$4>0,K97/Config!$B$4,0) | T97: =R97*Config!$B$7 | U97: =S97*Config!$B$7 | V97: 36 | W97: 180 | X97: =IF(T97>0,V97/T97,0) | Y97: =IF(U97>0,W97/U97,0) | Z97: =T97-V97 | AA97: =U97-W97 | AB97: =IF(Config!$B$7>0,(V97/Config!$B$7)*Config!$B$4,0) | AC97: =IF(Config!$B$7>0,(W97/Config!$B$7)*Config!$B$4,0)
E98: Seeds_11-2541 | G98: Seeds | H98: Premium Chia Seeds Farmley Standee Pouch 200 g | J98: 0 | K98: 0 | L98: CPC - Master Bhandar | M98: 0 | N98: CPC KPKB | O98: Indore | Q98: Chia Seeds | R98: =IF(Config!$B$4>0,M98/Config!$B$4,0) | S98: =IF(Config!$B$4>0,K98/Config!$B$4,0) | T98: =R98*Config!$B$7 | U98: =S98*Config!$B$7 | V98: 6 | W98: 30 | X98: =IF(T98>0,V98/T98,0) | Y98: =IF(U98>0,W98/U98,0) | Z98: =T98-V98 | AA98: =U98-W98 | AB98: =IF(Config!$B$7>0,(V98/Config!$B$7)*Config!$B$4,0) | AC98: =IF(Config!$B$7>0,(W98/Config!$B$7)*Config!$B$4,0)
E99: Seeds_11-2541 | G99: Seeds | H99: Premium Chia Seeds Farmley Standee Pouch 200 g | J99: 0 | K99: 0 | L99: CPC - Master Bhandar CRPF HQ CGO | M99: 0 | N99: CPC KPKB | O99: Indore | Q99: Chia Seeds | R99: =IF(Config!$B$4>0,M99/Config!$B$4,0) | S99: =IF(Config!$B$4>0,K99/Config!$B$4,0) | T99: =R99*Config!$B$7 | U99: =S99*Config!$B$7 | V99: 42 | W99: 210 | X99: =IF(T99>0,V99/T99,0) | Y99: =IF(U99>0,W99/U99,0) | Z99: =T99-V99 | AA99: =U99-W99 | AB99: =IF(Config!$B$7>0,(V99/Config!$B$7)*Config!$B$4,0) | AC99: =IF(Config!$B$7>0,(W99/Config!$B$7)*Config!$B$4,0)
E100: Seeds_11-2541 | G100: Seeds | H100: Premium Chia Seeds Farmley Standee Pouch 200 g | J100: 0 | K100: 0 | L100: CPC - Master Bhandar Kendriya Police Kalyan Bhandar | M100: 0 | N100: CPC KPKB | O100: Indore | Q100: Chia Seeds | R100: =IF(Config!$B$4>0,M100/Config!$B$4,0) | S100: =IF(Config!$B$4>0,K100/Config!$B$4,0) | T100: =R100*Config!$B$7 | U100: =S100*Config!$B$7 | V100: 12 | W100: 60 | X100: =IF(T100>0,V100/T100,0) | Y100: =IF(U100>0,W100/U100,0) | Z100: =T100-V100 | AA100: =U100-W100 | AB100: =IF(Config!$B$7>0,(V100/Config!$B$7)*Config!$B$4,0) | AC100: =IF(Config!$B$7>0,(W100/Config!$B$7)*Config!$B$4,0)
E101: Seeds_11-2541 | G101: Seeds | H101: Premium Chia Seeds Farmley Standee Pouch 200 g | J101: 0 | K101: 0 | L101: CPC - Master Bhander Gc-1 CRPF Ajmer | M101: 0 | N101: CPC KPKB | O101: Indore | Q101: Chia Seeds | R101: =IF(Config!$B$4>0,M101/Config!$B$4,0) | S101: =IF(Config!$B$4>0,K101/Config!$B$4,0) | T101: =R101*Config!$B$7 | U101: =S101*Config!$B$7 | V101: 12 | W101: 60 | X101: =IF(T101>0,V101/T101,0) | Y101: =IF(U101>0,W101/U101,0) | Z101: =T101-V101 | AA101: =U101-W101 | AB101: =IF(Config!$B$7>0,(V101/Config!$B$7)*Config!$B$4,0) | AC101: =IF(Config!$B$7>0,(W101/Config!$B$7)*Config!$B$4,0)
E102: Seeds_11-2541 | G102: Seeds | H102: Premium Chia Seeds Farmley Standee Pouch 200 g | J102: 0 | K102: 0 | L102: CPC - Master Canteen Central Police Canteen | M102: 0 | N102: CPC KPKB | O102: Indore | Q102: Chia Seeds | R102: =IF(Config!$B$4>0,M102/Config!$B$4,0) | S102: =IF(Config!$B$4>0,K102/Config!$B$4,0) | T102: =R102*Config!$B$7 | U102: =S102*Config!$B$7 | V102: 120 | W102: 600 | X102: =IF(T102>0,V102/T102,0) | Y102: =IF(U102>0,W102/U102,0) | Z102: =T102-V102 | AA102: =U102-W102 | AB102: =IF(Config!$B$7>0,(V102/Config!$B$7)*Config!$B$4,0) | AC102: =IF(Config!$B$7>0,(W102/Config!$B$7)*Config!$B$4,0)
E103: Seeds_11-2541 | G103: Seeds | H103: Premium Chia Seeds Farmley Standee Pouch 200 g | J103: 0 | K103: 0 | L103: CPC - Principal RTC CRPF Peringome | M103: 0 | N103: CPC KPKB | O103: Indore | Q103: Chia Seeds | R103: =IF(Config!$B$4>0,M103/Config!$B$4,0) | S103: =IF(Config!$B$4>0,K103/Config!$B$4,0) | T103: =R103*Config!$B$7 | U103: =S103*Config!$B$7 | V103: 6 | W103: 30 | X103: =IF(T103>0,V103/T103,0) | Y103: =IF(U103>0,W103/U103,0) | Z103: =T103-V103 | AA103: =U103-W103 | AB103: =IF(Config!$B$7>0,(V103/Config!$B$7)*Config!$B$4,0) | AC103: =IF(Config!$B$7>0,(W103/Config!$B$7)*Config!$B$4,0)
E104: Seeds_11-2541 | G104: Seeds | H104: Premium Chia Seeds Farmley Standee Pouch 200 g | J104: 0 | K104: 0 | L104: CPC -KPKB Master Bhandar Cisf Unit RSP Rourkela | M104: 0 | N104: CPC KPKB | O104: Indore | Q104: Chia Seeds | R104: =IF(Config!$B$4>0,M104/Config!$B$4,0) | S104: =IF(Config!$B$4>0,K104/Config!$B$4,0) | T104: =R104*Config!$B$7 | U104: =S104*Config!$B$7 | V104: 12 | W104: 60 | X104: =IF(T104>0,V104/T104,0) | Y104: =IF(U104>0,W104/U104,0) | Z104: =T104-V104 | AA104: =U104-W104 | AB104: =IF(Config!$B$7>0,(V104/Config!$B$7)*Config!$B$4,0) | AC104: =IF(Config!$B$7>0,(W104/Config!$B$7)*Config!$B$4,0)
E105: Seeds_11-2541 | G105: Seeds | H105: Premium Chia Seeds Farmley Standee Pouch 200 g | J105: 0 | K105: 0 | L105: CPC -Master Bhandar | M105: 0 | N105: CPC KPKB | O105: Indore | Q105: Chia Seeds | R105: =IF(Config!$B$4>0,M105/Config!$B$4,0) | S105: =IF(Config!$B$4>0,K105/Config!$B$4,0) | T105: =R105*Config!$B$7 | U105: =S105*Config!$B$7 | V105: 12 | W105: 60 | X105: =IF(T105>0,V105/T105,0) | Y105: =IF(U105>0,W105/U105,0) | Z105: =T105-V105 | AA105: =U105-W105 | AB105: =IF(Config!$B$7>0,(V105/Config!$B$7)*Config!$B$4,0) | AC105: =IF(Config!$B$7>0,(W105/Config!$B$7)*Config!$B$4,0)
... E120: Seeds_11-2541 | G120: Seeds | H120: Premium Chia Seeds Farmley Standee Pouch 200 g | J120: 0 | K120: 0 | L120: PJTJ Technologies Private Limited | M120: 0 | N120: Quick Commerce | O120: Indore | Q120: Chia Seeds | R120: =IF(Config!$B$4>0,M120/Config!$B$4,0) | S120: =IF(Config!$B$4>0,K120/Config!$B$4,0) | T120: =R120*Config!$B$7 | U120: =S120*Config!$B$7 | V120: 1098 | W120: 5490 | X120: =IF(T120>0,V120/T120,0) | Y120: =IF(U120>0,W120/U120,0) | Z120: =T120-V120 | AA120: =U120-W120 | AB120: =IF(Config!$B$7>0,(V120/Config!$B$7)*Config!$B$4,0) | AC120: =IF(Config!$B$7>0,(W120/Config!$B$7)*Config!$B$4,0)
A121: May | B121: 2026 | C121: 29-04-2026 | D121: 0.47065972 | E121: Almonds_1-1748 | F121: FG | G121: Almonds | H121: Premium California Almonds Farmley Standee Pouch 500 g | I121: Premium California Almonds | J121: 0.5 | K121: 9840 | L121: 43 Customers | M121: 4920 | N121: Multiple | O121: Indore | P121: KVI | Q121: Almonds | R121: =IF(Config!$B$4>0,M121/Config!$B$4,0) | S121: =IF(Config!$B$4>0,K121/Config!$B$4,0) | T121: =R121*Config!$B$7 | U121: =S121*Config!$B$7 | V121: 6108 | W121: 12216 | X121: =IF(T121>0,V121/T121,0) | Y121: =IF(U121>0,W121/U121,0) | Z121: =T121-V121 | AA121: =U121-W121 | AB121: =IF(Config!$B$7>0,(V121/Config!$B$7)*Config!$B$4,0) | AC121: =IF(Config!$B$7>0,(W121/Config!$B$7)*Config!$B$4,0)
A122: May | B122: 2026 | C122: 29-04-2026 | D122: 0.47065972 | E122: Almonds_1-1748 | F122: FG | G122: Almonds | H122: Premium California Almonds Farmley Standee Pouch 500 g | I122: Premium California Almonds | J122: 0.5 | K122: 9840 | L122: CPC KPKB | M122: 4920 | N122: CPC | O122: Indore | P122: KVI | Q122: Almonds | R122: =IF(Config!$B$4>0,M122/Config!$B$4,0) | S122: =IF(Config!$B$4>0,K122/Config!$B$4,0) | T122: =R122*Config!$B$7 | U122: =S122*Config!$B$7 | V122: 0 | W122: 0 | X122: =IF(T122>0,V122/T122,0) | Y122: =IF(U122>0,W122/U122,0) | Z122: =T122-V122 | AA122: =U122-W122 | AB122: =IF(Config!$B$7>0,(V122/Config!$B$7)*Config!$B$4,0) | AC122: =IF(Config!$B$7>0,(W122/Config!$B$7)*Config!$B$4,0)
E123: Almonds_1-1748 | G123: Almonds | H123: Premium California Almonds Farmley Standee Pouch 500 g | J123: 0 | K123: 0 | L123: CPC - C P C Master Canteen -Khargone -Madhya Pradesh -451115 | M123: 0 | N123: CPC KPKB | O123: Indore | Q123: Almonds | R123: =IF(Config!$B$4>0,M123/Config!$B$4,0) | S123: =IF(Config!$B$4>0,K123/Config!$B$4,0) | T123: =R123*Config!$B$7 | U123: =S123*Config!$B$7 | V123: 36 | W123: 72 | X123: =IF(T123>0,V123/T123,0) | Y123: =IF(U123>0,W123/U123,0) | Z123: =T123-V123 | AA123: =U123-W123 | AB123: =IF(Config!$B$7>0,(V123/Config!$B$7)*Config!$B$4,0) | AC123: =IF(Config!$B$7>0,(W123/Config!$B$7)*Config!$B$4,0)
E124: Almonds_1-1748 | G124: Almonds | H124: Premium California Almonds Farmley Standee Pouch 500 g | J124: 0 | K124: 0 | L124: CPC - Canteen Officer Master Canteen Frontier HQR SSB Lucknow | M124: 0 | N124: CPC KPKB | O124: Indore | Q124: Almonds | R124: =IF(Config!$B$4>0,M124/Config!$B$4,0) | S124: =IF(Config!$B$4>0,K124/Config!$B$4,0) | T124: =R124*Config!$B$7 | U124: =S124*Config!$B$7 | V124: 24 | W124: 48 | X124: =IF(T124>0,V124/T124,0) | Y124: =IF(U124>0,W124/U124,0) | Z124: =T124-V124 | AA124: =U124-W124 | AB124: =IF(Config!$B$7>0,(V124/Config!$B$7)*Config!$B$4,0) | AC124: =IF(Config!$B$7>0,(W124/Config!$B$7)*Config!$B$4,0)
E125: Almonds_1-1748 | G125: Almonds | H125: Premium California Almonds Farmley Standee Pouch 500 g | J125: 0 | K125: 0 | L125: CPC - Central Police Canteen Cisf Unit Kopt Kolkata | M125: 0 | N125: CPC KPKB | O125: Indore | Q125: Almonds | R125: =IF(Config!$B$4>0,M125/Config!$B$4,0) | S125: =IF(Config!$B$4>0,K125/Config!$B$4,0) | T125: =R125*Config!$B$7 | U125: =S125*Config!$B$7 | V125: 192 | W125: 384 | X125: =IF(T125>0,V125/T125,0) | Y125: =IF(U125>0,W125/U125,0) | Z125: =T125-V125 | AA125: =U125-W125 | AB125: =IF(Config!$B$7>0,(V125/Config!$B$7)*Config!$B$4,0) | AC125: =IF(Config!$B$7>0,(W125/Config!$B$7)*Config!$B$4,0)
E126: Almonds_1-1748 | G126: Almonds | H126: Premium California Almonds Farmley Standee Pouch 500 g | J126: 0 | K126: 0 | L126: CPC - Commandant 57th Bn SSB | M126: 0 | N126: CPC KPKB | O126: Indore | Q126: Almonds | R126: =IF(Config!$B$4>0,M126/Config!$B$4,0) | S126: =IF(Config!$B$4>0,K126/Config!$B$4,0) | T126: =R126*Config!$B$7 | U126: =S126*Config!$B$7 | V126: 240 | W126: 480 | X126: =IF(T126>0,V126/T126,0) | Y126: =IF(U126>0,W126/U126,0) | Z126: =T126-V126 | AA126: =U126-W126 | AB126: =IF(Config!$B$7>0,(V126/Config!$B$7)*Config!$B$4,0) | AC126: =IF(Config!$B$7>0,(W126/Config!$B$7)*Config!$B$4,0)
E127: Almonds_1-1748 | G127: Almonds | H127: Premium California Almonds Farmley Standee Pouch 500 g | J127: 0 | K127: 0 | L127: CPC - KPKB Master Canteen Dhanbad | M127: 0 | N127: CPC KPKB | O127: Indore | Q127: Almonds | R127: =IF(Config!$B$4>0,M127/Config!$B$4,0) | S127: =IF(Config!$B$4>0,K127/Config!$B$4,0) | T127: =R127*Config!$B$7 | U127: =S127*Config!$B$7 | V127: 240 | W127: 480 | X127: =IF(T127>0,V127/T127,0) | Y127: =IF(U127>0,W127/U127,0) | Z127: =T127-V127 | AA127: =U127-W127 | AB127: =IF(Config!$B$7>0,(V127/Config!$B$7)*Config!$B$4,0) | AC127: =IF(Config!$B$7>0,(W127/Config!$B$7)*Config!$B$4,0)
E128: Almonds_1-1748 | G128: Almonds | H128: Premium California Almonds Farmley Standee Pouch 500 g | J128: 0 | K128: 0 | L128: CPC - Kendriya Police Kalyan Bhandar - HP | M128: 0 | N128: CPC KPKB | O128: Indore | Q128: Almonds | R128: =IF(Config!$B$4>0,M128/Config!$B$4,0) | S128: =IF(Config!$B$4>0,K128/Config!$B$4,0) | T128: =R128*Config!$B$7 | U128: =S128*Config!$B$7 | V128: 120 | W128: 240 | X128: =IF(T128>0,V128/T128,0) | Y128: =IF(U128>0,W128/U128,0) | Z128: =T128-V128 | AA128: =U128-W128 | AB128: =IF(Config!$B$7>0,(V128/Config!$B$7)*Config!$B$4,0) | AC128: =IF(Config!$B$7>0,(W128/Config!$B$7)*Config!$B$4,0)
E129: Almonds_1-1748 | G129: Almonds | H129: Premium California Almonds Farmley Standee Pouch 500 g | J129: 0 | K129: 0 | L129: CPC - Kendriya Police Kalyan Master Bhandar | M129: 0 | N129: CPC KPKB | O129: Indore | Q129: Almonds | R129: =IF(Config!$B$4>0,M129/Config!$B$4,0) | S129: =IF(Config!$B$4>0,K129/Config!$B$4,0) | T129: =R129*Config!$B$7 | U129: =S129*Config!$B$7 | V129: 36 | W129: 72 | X129: =IF(T129>0,V129/T129,0) | Y129: =IF(U129>0,W129/U129,0) | Z129: =T129-V129 | AA129: =U129-W129 | AB129: =IF(Config!$B$7>0,(V129/Config!$B$7)*Config!$B$4,0) | AC129: =IF(Config!$B$7>0,(W129/Config!$B$7)*Config!$B$4,0)
E130: Almonds_1-1748 | G130: Almonds | H130: Premium California Almonds Farmley Standee Pouch 500 g | J130: 0 | K130: 0 | L130: CPC - Master Bhandar | M130: 0 | N130: CPC KPKB | O130: Indore | Q130: Almonds | R130: =IF(Config!$B$4>0,M130/Config!$B$4,0) | S130: =IF(Config!$B$4>0,K130/Config!$B$4,0) | T130: =R130*Config!$B$7 | U130: =S130*Config!$B$7 | V130: 72 | W130: 144 | X130: =IF(T130>0,V130/T130,0) | Y130: =IF(U130>0,W130/U130,0) | Z130: =T130-V130 | AA130: =U130-W130 | AB130: =IF(Config!$B$7>0,(V130/Config!$B$7)*Config!$B$4,0) | AC130: =IF(Config!$B$7>0,(W130/Config!$B$7)*Config!$B$4,0)
E131: Almonds_1-1748 | G131: Almonds | H131: Premium California Almonds Farmley Standee Pouch 500 g | J131: 0 | K131: 0 | L131: CPC - Master Bhandar - Haryana | M131: 0 | N131: CPC KPKB | O131: Indore | Q131: Almonds | R131: =IF(Config!$B$4>0,M131/Config!$B$4,0) | S131: =IF(Config!$B$4>0,K131/Config!$B$4,0) | T131: =R131*Config!$B$7 | U131: =S131*Config!$B$7 | V131: 48 | W131: 96 | X131: =IF(T131>0,V131/T131,0) | Y131: =IF(U131>0,W131/U131,0) | Z131: =T131-V131 | AA131: =U131-W131 | AB131: =IF(Config!$B$7>0,(V131/Config!$B$7)*Config!$B$4,0) | AC131: =IF(Config!$B$7>0,(W131/Config!$B$7)*Config!$B$4,0)
E132: Almonds_1-1748 | G132: Almonds | H132: Premium California Almonds Farmley Standee Pouch 500 g | J132: 0 | K132: 0 | L132: CPC - Master Bhandar CRPF HQ CGO | M132: 0 | N132: CPC KPKB | O132: Indore | Q132: Almonds | R132: =IF(Config!$B$4>0,M132/Config!$B$4,0) | S132: =IF(Config!$B$4>0,K132/Config!$B$4,0) | T132: =R132*Config!$B$7 | U132: =S132*Config!$B$7 | V132: 204 | W132: 408 | X132: =IF(T132>0,V132/T132,0) | Y132: =IF(U132>0,W132/U132,0) | Z132: =T132-V132 | AA132: =U132-W132 | AB132: =IF(Config!$B$7>0,(V132/Config!$B$7)*Config!$B$4,0) | AC132: =IF(Config!$B$7>0,(W132/Config!$B$7)*Config!$B$4,0)
E133: Almonds_1-1748 | G133: Almonds | H133: Premium California Almonds Farmley Standee Pouch 500 g | J133: 0 | K133: 0 | L133: CPC - Master Bhandar Kendriya Police Kalyan Bhandar | M133: 0 | N133: CPC KPKB | O133: Indore | Q133: Almonds | R133: =IF(Config!$B$4>0,M133/Config!$B$4,0) | S133: =IF(Config!$B$4>0,K133/Config!$B$4,0) | T133: =R133*Config!$B$7 | U133: =S133*Config!$B$7 | V133: 72 | W133: 144 | X133: =IF(T133>0,V133/T133,0) | Y133: =IF(U133>0,W133/U133,0) | Z133: =T133-V133 | AA133: =U133-W133 | AB133: =IF(Config!$B$7>0,(V133/Config!$B$7)*Config!$B$4,0) | AC133: =IF(Config!$B$7>0,(W133/Config!$B$7)*Config!$B$4,0)
E134: Almonds_1-1748 | G134: Almonds | H134: Premium California Almonds Farmley Standee Pouch 500 g | J134: 0 | K134: 0 | L134: CPC - Master Bhander Gc-1 CRPF Ajmer | M134: 0 | N134: CPC KPKB | O134: Indore | Q134: Almonds | R134: =IF(Config!$B$4>0,M134/Config!$B$4,0) | S134: =IF(Config!$B$4>0,K134/Config!$B$4,0) | T134: =R134*Config!$B$7 | U134: =S134*Config!$B$7 | V134: 240 | W134: 480 | X134: =IF(T134>0,V134/T134,0) | Y134: =IF(U134>0,W134/U134,0) | Z134: =T134-V134 | AA134: =U134-W134 | AB134: =IF(Config!$B$7>0,(V134/Config!$B$7)*Config!$B$4,0) | AC134: =IF(Config!$B$7>0,(W134/Config!$B$7)*Config!$B$4,0)
... E164: Almonds_1-1748 | G164: Almonds | H164: Premium California Almonds Farmley Standee Pouch 500 g | J164: 0 | K164: 0 | L164: Moksh Enterprises Private Limited | M164: 0 | N164: Quick Commerce | O164: Indore | Q164: Almonds | R164: =IF(Config!$B$4>0,M164/Config!$B$4,0) | S164: =IF(Config!$B$4>0,K164/Config!$B$4,0) | T164: =R164*Config!$B$7 | U164: =S164*Config!$B$7 | V164: 12 | W164: 24 | X164: =IF(T164>0,V164/T164,0) | Y164: =IF(U164>0,W164/U164,0) | Z164: =T164-V164 | AA164: =U164-W164 | AB164: =IF(Config!$B$7>0,(V164/Config!$B$7)*Config!$B$4,0) | AC164: =IF(Config!$B$7>0,(W164/Config!$B$7)*Config!$B$4,0)
A165: May | B165: 2026 | C165: 29-04-2026 | D165: 0.47065972 | E165: Dry Fruit Mix_15-2402 | F165: FG | G165: Trail Mixes | H165: Trail Mix Farmley Standee Pouch 200 g | I165: Trail Mix | J165: 0.2 | K165: 52754.25 | L165: 51 Customers | M165: 10550.85 | N165: Multiple | O165: Indore | P165: Value Added | Q165: Trail Mixes | R165: =IF(Config!$B$4>0,M165/Config!$B$4,0) | S165: =IF(Config!$B$4>0,K165/Config!$B$4,0) | T165: =R165*Config!$B$7 | U165: =S165*Config!$B$7 | V165: 4380 | W165: 21900 | X165: =IF(T165>0,V165/T165,0) | Y165: =IF(U165>0,W165/U165,0) | Z165: =T165-V165 | AA165: =U165-W165 | AB165: =IF(Config!$B$7>0,(V165/Config!$B$7)*Config!$B$4,0) | AC165: =IF(Config!$B$7>0,(W165/Config!$B$7)*Config!$B$4,0)
A166: May | B166: 2026 | C166: 29-04-2026 | D166: 0.47065972 | E166: Dry Fruit Mix_15-2402 | F166: FG | G166: Trail Mixes | H166: Trail Mix Farmley Standee Pouch 200 g | I166: Trail Mix | J166: 0.2 | K166: 3600 | L166: CPC KPKB | M166: 720 | N166: CPC | O166: Indore | P166: Value Added | Q166: Trail Mixes | R166: =IF(Config!$B$4>0,M166/Config!$B$4,0) | S166: =IF(Config!$B$4>0,K166/Config!$B$4,0) | T166: =R166*Config!$B$7 | U166: =S166*Config!$B$7 | V166: 0 | W166: 0 | X166: =IF(T166>0,V166/T166,0) | Y166: =IF(U166>0,W166/U166,0) | Z166: =T166-V166 | AA166: =U166-W166 | AB166: =IF(Config!$B$7>0,(V166/Config!$B$7)*Config!$B$4,0) | AC166: =IF(Config!$B$7>0,(W166/Config!$B$7)*Config!$B$4,0)
A167: May | B167: 2026 | C167: 29-04-2026 | D167: 0.53009259 | E167: Dry Fruit Mix_15-2402 | F167: FG | G167: Trail Mixes | H167: Trail Mix Farmley Standee Pouch 200 g | I167: Trail Mix | J167: 0.2 | K167: 800 | L167: Metro Cash & Carry India Private Limited | M167: 160 | N167: Modern Trade | O167: Indore | P167: Value Added | Q167: Trail Mixes | R167: =IF(Config!$B$4>0,M167/Config!$B$4,0) | S167: =IF(Config!$B$4>0,K167/Config!$B$4,0) | T167: =R167*Config!$B$7 | U167: =S167*Config!$B$7 | V167: 132 | W167: 660 | X167: =IF(T167>0,V167/T167,0) | Y167: =IF(U167>0,W167/U167,0) | Z167: =T167-V167 | AA167: =U167-W167 | AB167: =IF(Config!$B$7>0,(V167/Config!$B$7)*Config!$B$4,0) | AC167: =IF(Config!$B$7>0,(W167/Config!$B$7)*Config!$B$4,0)
A168: May | B168: 2026 | C168: 29-04-2026 | D168: 0.68866898 | E168: Dry Fruit Mix_15-2402 | F168: FG | G168: Trail Mixes | H168: Trail Mix Farmley Standee Pouch 200 g | I168: Trail Mix | J168: 0.2 | K168: 85.25 | L168: Farmley Website B2C | M168: 17.05 | N168: Own Website | O168: Indore | P168: Value Added | Q168: Trail Mixes | R168: =IF(Config!$B$4>0,M168/Config!$B$4,0) | S168: =IF(Config!$B$4>0,K168/Config!$B$4,0) | T168: =R168*Config!$B$7 | U168: =S168*Config!$B$7 | V168: 0 | W168: 0 | X168: =IF(T168>0,V168/T168,0) | Y168: =IF(U168>0,W168/U168,0) | Z168: =T168-V168 | AA168: =U168-W168 | AB168: =IF(Config!$B$7>0,(V168/Config!$B$7)*Config!$B$4,0) | AC168: =IF(Config!$B$7>0,(W168/Config!$B$7)*Config!$B$4,0)
A169: May | B169: 2026 | C169: 27-04-2026 | D169: 0.72568287 | E169: Dry Fruit Mix_15-2402 | F169: FG | G169: Trail Mixes | H169: Trail Mix Farmley Standee Pouch 200 g | I169: Trail Mix | J169: 0.2 | K169: 1200 | L169: April Moon Retail Limited | M169: 240 | N169: Other Institutions | O169: Indore | P169: Value Added | Q169: Trail Mixes | R169: =IF(Config!$B$4>0,M169/Config!$B$4,0) | S169: =IF(Config!$B$4>0,K169/Config!$B$4,0) | T169: =R169*Config!$B$7 | U169: =S169*Config!$B$7 | V169: 60 | W169: 300 | X169: =IF(T169>0,V169/T169,0) | Y169: =IF(U169>0,W169/U169,0) | Z169: =T169-V169 | AA169: =U169-W169 | AB169: =IF(Config!$B$7>0,(V169/Config!$B$7)*Config!$B$4,0) | AC169: =IF(Config!$B$7>0,(W169/Config!$B$7)*Config!$B$4,0)
A170: May | B170: 2026 | C170: 27-04-2026 | D170: 0.83003472 | E170: Dry Fruit Mix_15-2402 | F170: FG | G170: Trail Mixes | H170: Trail Mix Farmley Standee Pouch 200 g | I170: Trail Mix | J170: 0.2 | K170: 2600 | L170: GT Retail | M170: 520 | N170: Category A | O170: Indore | P170: Value Added | Q170: Trail Mixes | R170: =IF(Config!$B$4>0,M170/Config!$B$4,0) | S170: =IF(Config!$B$4>0,K170/Config!$B$4,0) | T170: =R170*Config!$B$7 | U170: =S170*Config!$B$7 | V170: 120 | W170: 600 | X170: =IF(T170>0,V170/T170,0) | Y170: =IF(U170>0,W170/U170,0) | Z170: =T170-V170 | AA170: =U170-W170 | AB170: =IF(Config!$B$7>0,(V170/Config!$B$7)*Config!$B$4,0) | AC170: =IF(Config!$B$7>0,(W170/Config!$B$7)*Config!$B$4,0)
A171: May | B171: 2026 | C171: 25-04-2026 | D171: 0.594375 | E171: Dry Fruit Mix_15-2402 | F171: FG | G171: Trail Mixes | H171: Trail Mix Farmley Standee Pouch 200 g | I171: Trail Mix | J171: 0.2 | K171: 2350 | L171: Flipkart India Private Limited | M171: 470 | N171: E-Commerce | O171: Indore | P171: Value Added | Q171: Trail Mixes | R171: =IF(Config!$B$4>0,M171/Config!$B$4,0) | S171: =IF(Config!$B$4>0,K171/Config!$B$4,0) | T171: =R171*Config!$B$7 | U171: =S171*Config!$B$7 | V171: 450 | W171: 2250 | X171: =IF(T171>0,V171/T171,0) | Y171: =IF(U171>0,W171/U171,0) | Z171: =T171-V171 | AA171: =U171-W171 | AB171: =IF(Config!$B$7>0,(V171/Config!$B$7)*Config!$B$4,0) | AC171: =IF(Config!$B$7>0,(W171/Config!$B$7)*Config!$B$4,0)
A172: May | B172: 2026 | C172: 25-04-2026 | D172: 0.62568287 | E172: Dry Fruit Mix_15-2402 | F172: FG | G172: Trail Mixes | H172: Trail Mix Farmley Standee Pouch 200 g | I172: Trail Mix | J172: 0.2 | K172: 1200 | L172: Avenue E-Commerce Ltd | M172: 240 | N172: E-Commerce | O172: Indore | P172: Value Added | Q172: Trail Mixes | R172: =IF(Config!$B$4>0,M172/Config!$B$4,0) | S172: =IF(Config!$B$4>0,K172/Config!$B$4,0) | T172: =R172*Config!$B$7 | U172: =S172*Config!$B$7 | V172: 66 | W172: 330 | X172: =IF(T172>0,V172/T172,0) | Y172: =IF(U172>0,W172/U172,0) | Z172: =T172-V172 | AA172: =U172-W172 | AB172: =IF(Config!$B$7>0,(V172/Config!$B$7)*Config!$B$4,0) | AC172: =IF(Config!$B$7>0,(W172/Config!$B$7)*Config!$B$4,0)
A173: May | B173: 2026 | C173: 25-04-2026 | D173: 0.63921296 | E173: Dry Fruit Mix_15-2402 | F173: FG | G173: Trail Mixes | H173: Trail Mix Farmley Standee Pouch 200 g | I173: Trail Mix | J173: 0.2 | K173: 700 | L173: Flipkart B2C | M173: 140 | N173: E-Commerce Dropship | O173: Indore | P173: Value Added | Q173: Trail Mixes | R173: =IF(Config!$B$4>0,M173/Config!$B$4,0) | S173: =IF(Config!$B$4>0,K173/Config!$B$4,0) | T173: =R173*Config!$B$7 | U173: =S173*Config!$B$7 | V173: 0 | W173: 0 | X173: =IF(T173>0,V173/T173,0) | Y173: =IF(U173>0,W173/U173,0) | Z173: =T173-V173 | AA173: =U173-W173 | AB173: =IF(Config!$B$7>0,(V173/Config!$B$7)*Config!$B$4,0) | AC173: =IF(Config!$B$7>0,(W173/Config!$B$7)*Config!$B$4,0)
A174: May | B174: 2026 | C174: 25-04-2026 | D174: 0.64491898 | E174: Dry Fruit Mix_15-2402 | F174: FG | G174: Trail Mixes | H174: Trail Mix Farmley Standee Pouch 200 g | I174: Trail Mix | J174: 0.2 | K174: 900 | L174: INNOVATIVE RETAIL CONCEPTS PRIVATE LIMITED | M174: 180 | N174: Quick Commerce | O174: Indore | P174: Value Added | Q174: Trail Mixes | R174: =IF(Config!$B$4>0,M174/Config!$B$4,0) | S174: =IF(Config!$B$4>0,K174/Config!$B$4,0) | T174: =R174*Config!$B$7 | U174: =S174*Config!$B$7 | V174: 66 | W174: 330 | X174: =IF(T174>0,V174/T174,0) | Y174: =IF(U174>0,W174/U174,0) | Z174: =T174-V174 | AA174: =U174-W174 | AB174: =IF(Config!$B$7>0,(V174/Config!$B$7)*Config!$B$4,0) | AC174: =IF(Config!$B$7>0,(W174/Config!$B$7)*Config!$B$4,0)
A175: May | B175: 2026 | C175: 25-04-2026 | D175: 0.65229167 | E175: Dry Fruit Mix_15-2402 | F175: FG | G175: Trail Mixes | H175: Trail Mix Farmley Standee Pouch 200 g | I175: Trail Mix | J175: 0.2 | K175: 250 | L175: Reliance Retail Limited _Milk Basket | M175: 50 | N175: Quick Commerce | O175: Indore | P175: Value Added | Q175: Trail Mixes | R175: =IF(Config!$B$4>0,M175/Config!$B$4,0) | S175: =IF(Config!$B$4>0,K175/Config!$B$4,0) | T175: =R175*Config!$B$7 | U175: =S175*Config!$B$7 | V175: 6 | W175: 30 | X175: =IF(T175>0,V175/T175,0) | Y175: =IF(U175>0,W175/U175,0) | Z175: =T175-V175 | AA175: =U175-W175 | AB175: =IF(Config!$B$7>0,(V175/Config!$B$7)*Config!$B$4,0) | AC175: =IF(Config!$B$7>0,(W175/Config!$B$7)*Config!$B$4,0)
A176: May | B176: 2026 | C176: 25-04-2026 | D176: 0.65841435 | E176: Dry Fruit Mix_15-2402 | F176: FG | G176: Trail Mixes | H176: Trail Mix Farmley Standee Pouch 200 g | I176: Trail Mix | J176: 0.2 | K176: 100 | L176: Meesho B2C | M176: 20 | N176: E-Commerce Dropship | O176: Indore | P176: Value Added | Q176: Trail Mixes | R176: =IF(Config!$B$4>0,M176/Config!$B$4,0) | S176: =IF(Config!$B$4>0,K176/Config!$B$4,0) | T176: =R176*Config!$B$7 | U176: =S176*Config!$B$7 | V176: 0 | W176: 0 | X176: =IF(T176>0,V176/T176,0) | Y176: =IF(U176>0,W176/U176,0) | Z176: =T176-V176 | AA176: =U176-W176 | AB176: =IF(Config!$B$7>0,(V176/Config!$B$7)*Config!$B$4,0) | AC176: =IF(Config!$B$7>0,(W176/Config!$B$7)*Config!$B$4,0)
... A189: May | B189: 2026 | C189: 25-04-2026 | D189: 0.72672454 | E189: Dry Fruit Mix_15-2402 | F189: FG | G189: Trail Mixes | H189: Trail Mix Farmley Standee Pouch 200 g | I189: Trail Mix | J189: 0.2 | K189: 180 | L189: Natures Basket Limited | M189: 36 | N189: Modern Trade | O189: Indore | P189: Value Added | Q189: Trail Mixes | R189: =IF(Config!$B$4>0,M189/Config!$B$4,0) | S189: =IF(Config!$B$4>0,K189/Config!$B$4,0) | T189: =R189*Config!$B$7 | U189: =S189*Config!$B$7 | V189: 0 | W189: 0 | X189: =IF(T189>0,V189/T189,0) | Y189: =IF(U189>0,W189/U189,0) | Z189: =T189-V189 | AA189: =U189-W189 | AB189: =IF(Config!$B$7>0,(V189/Config!$B$7)*Config!$B$4,0) | AC189: =IF(Config!$B$7>0,(W189/Config!$B$7)*Config!$B$4,0)
E190: Dry Fruit Mix_15-2402 | G190: Dry Fruit Mix | H190: Trail Mix Farmley Standee Pouch 200 g | J190: 0 | K190: 0 | L190: CPC - Central Police Canteen Cisf Unit Kopt Kolkata | M190: 0 | N190: CPC KPKB | O190: Indore | Q190: Trail Mixes | R190: =IF(Config!$B$4>0,M190/Config!$B$4,0) | S190: =IF(Config!$B$4>0,K190/Config!$B$4,0) | T190: =R190*Config!$B$7 | U190: =S190*Config!$B$7 | V190: 18 | W190: 90 | X190: =IF(T190>0,V190/T190,0) | Y190: =IF(U190>0,W190/U190,0) | Z190: =T190-V190 | AA190: =U190-W190 | AB190: =IF(Config!$B$7>0,(V190/Config!$B$7)*Config!$B$4,0) | AC190: =IF(Config!$B$7>0,(W190/Config!$B$7)*Config!$B$4,0)
E191: Dry Fruit Mix_15-2402 | G191: Dry Fruit Mix | H191: Trail Mix Farmley Standee Pouch 200 g | J191: 0 | K191: 0 | L191: CPC - Commandant 57th Bn SSB | M191: 0 | N191: CPC KPKB | O191: Indore | Q191: Trail Mixes | R191: =IF(Config!$B$4>0,M191/Config!$B$4,0) | S191: =IF(Config!$B$4>0,K191/Config!$B$4,0) | T191: =R191*Config!$B$7 | U191: =S191*Config!$B$7 | V191: 42 | W191: 210 | X191: =IF(T191>0,V191/T191,0) | Y191: =IF(U191>0,W191/U191,0) | Z191: =T191-V191 | AA191: =U191-W191 | AB191: =IF(Config!$B$7>0,(V191/Config!$B$7)*Config!$B$4,0) | AC191: =IF(Config!$B$7>0,(W191/Config!$B$7)*Config!$B$4,0)
E192: Dry Fruit Mix_15-2402 | G192: Dry Fruit Mix | H192: Trail Mix Farmley Standee Pouch 200 g | J192: 0 | K192: 0 | L192: CPC - KPKB Master Canteen Dhanbad | M192: 0 | N192: CPC KPKB | O192: Indore | Q192: Trail Mixes | R192: =IF(Config!$B$4>0,M192/Config!$B$4,0) | S192: =IF(Config!$B$4>0,K192/Config!$B$4,0) | T192: =R192*Config!$B$7 | U192: =S192*Config!$B$7 | V192: 30 | W192: 150 | X192: =IF(T192>0,V192/T192,0) | Y192: =IF(U192>0,W192/U192,0) | Z192: =T192-V192 | AA192: =U192-W192 | AB192: =IF(Config!$B$7>0,(V192/Config!$B$7)*Config!$B$4,0) | AC192: =IF(Config!$B$7>0,(W192/Config!$B$7)*Config!$B$4,0)
E193: Dry Fruit Mix_15-2402 | G193: Dry Fruit Mix | H193: Trail Mix Farmley Standee Pouch 200 g | J193: 0 | K193: 0 | L193: CPC - Master Bhandar | M193: 0 | N193: CPC KPKB | O193: Indore | Q193: Trail Mixes | R193: =IF(Config!$B$4>0,M193/Config!$B$4,0) | S193: =IF(Config!$B$4>0,K193/Config!$B$4,0) | T193: =R193*Config!$B$7 | U193: =S193*Config!$B$7 | V193: 12 | W193: 60 | X193: =IF(T193>0,V193/T193,0) | Y193: =IF(U193>0,W193/U193,0) | Z193: =T193-V193 | AA193: =U193-W193 | AB193: =IF(Config!$B$7>0,(V193/Config!$B$7)*Config!$B$4,0) | AC193: =IF(Config!$B$7>0,(W193/Config!$B$7)*Config!$B$4,0)
E194: Dry Fruit Mix_15-2402 | G194: Dry Fruit Mix | H194: Trail Mix Farmley Standee Pouch 200 g | J194: 0 | K194: 0 | L194: CPC - Master Bhandar CRPF HQ CGO | M194: 0 | N194: CPC KPKB | O194: Indore | Q194: Trail Mixes | R194: =IF(Config!$B$4>0,M194/Config!$B$4,0) | S194: =IF(Config!$B$4>0,K194/Config!$B$4,0) | T194: =R194*Config!$B$7 | U194: =S194*Config!$B$7 | V194: 18 | W194: 90 | X194: =IF(T194>0,V194/T194,0) | Y194: =IF(U194>0,W194/U194,0) | Z194: =T194-V194 | AA194: =U194-W194 | AB194: =IF(Config!$B$7>0,(V194/Config!$B$7)*Config!$B$4,0) | AC194: =IF(Config!$B$7>0,(W194/Config!$B$7)*Config!$B$4,0)
E195: Dry Fruit Mix_15-2402 | G195: Dry Fruit Mix | H195: Trail Mix Farmley Standee Pouch 200 g | J195: 0 | K195: 0 | L195: CPC -Chairman Master Bhandar -Pithoragarh-Uttarakhand-262501 | M195: 0 | N195: CPC KPKB | O195: Indore | Q195: Trail Mixes | R195: =IF(Config!$B$4>0,M195/Config!$B$4,0) | S195: =IF(Config!$B$4>0,K195/Config!$B$4,0) | T195: =R195*Config!$B$7 | U195: =S195*Config!$B$7 | V195: 12 | W195: 60 | X195: =IF(T195>0,V195/T195,0) | Y195: =IF(U195>0,W195/U195,0) | Z195: =T195-V195 | AA195: =U195-W195 | AB195: =IF(Config!$B$7>0,(V195/Config!$B$7)*Config!$B$4,0) | AC195: =IF(Config!$B$7>0,(W195/Config!$B$7)*Config!$B$4,0)
E196: Dry Fruit Mix_15-2402 | G196: Dry Fruit Mix | H196: Trail Mix Farmley Standee Pouch 200 g | J196: 0 | K196: 0 | L196: CPC -KPKB Master Bhandar -East Khasi Hills -Meghalaya- 793012 | M196: 0 | N196: CPC KPKB | O196: Indore | Q196: Trail Mixes | R196: =IF(Config!$B$4>0,M196/Config!$B$4,0) | S196: =IF(Config!$B$4>0,K196/Config!$B$4,0) | T196: =R196*Config!$B$7 | U196: =S196*Config!$B$7 | V196: 12 | W196: 60 | X196: =IF(T196>0,V196/T196,0) | Y196: =IF(U196>0,W196/U196,0) | Z196: =T196-V196 | AA196: =U196-W196 | AB196: =IF(Config!$B$7>0,(V196/Config!$B$7)*Config!$B$4,0) | AC196: =IF(Config!$B$7>0,(W196/Config!$B$7)*Config!$B$4,0)
E197: Dry Fruit Mix_15-2402 | G197: Dry Fruit Mix | H197: Trail Mix Farmley Standee Pouch 200 g | J197: 0 | K197: 0 | L197: CPC -KPKB Master Bhandar Cisf Unit RSP Rourkela | M197: 0 | N197: CPC KPKB | O197: Indore | Q197: Trail Mixes | R197: =IF(Config!$B$4>0,M197/Config!$B$4,0) | S197: =IF(Config!$B$4>0,K197/Config!$B$4,0) | T197: =R197*Config!$B$7 | U197: =S197*Config!$B$7 | V197: 36 | W197: 180 | X197: =IF(T197>0,V197/T197,0) | Y197: =IF(U197>0,W197/U197,0) | Z197: =T197-V197 | AA197: =U197-W197 | AB197: =IF(Config!$B$7>0,(V197/Config!$B$7)*Config!$B$4,0) | AC197: =IF(Config!$B$7>0,(W197/Config!$B$7)*Config!$B$4,0)
E198: Dry Fruit Mix_15-2402 | G198: Dry Fruit Mix | H198: Trail Mix Farmley Standee Pouch 200 g | J198: 0 | K198: 0 | L198: CPC -Master Bhandar RTC CRPF Srinagar | M198: 0 | N198: CPC KPKB | O198: Indore | Q198: Trail Mixes | R198: =IF(Config!$B$4>0,M198/Config!$B$4,0) | S198: =IF(Config!$B$4>0,K198/Config!$B$4,0) | T198: =R198*Config!$B$7 | U198: =S198*Config!$B$7 | V198: 6 | W198: 30 | X198: =IF(T198>0,V198/T198,0) | Y198: =IF(U198>0,W198/U198,0) | Z198: =T198-V198 | AA198: =U198-W198 | AB198: =IF(Config!$B$7>0,(V198/Config!$B$7)*Config!$B$4,0) | AC198: =IF(Config!$B$7>0,(W198/Config!$B$7)*Config!$B$4,0)
E199: Dry Fruit Mix_15-2402 | G199: Dry Fruit Mix | H199: Trail Mix Farmley Standee Pouch 200 g | J199: 0 | K199: 0 | L199: CPC -Master Bhandar TPT Bn Itbp | M199: 0 | N199: CPC KPKB | O199: Indore | Q199: Trail Mixes | R199: =IF(Config!$B$4>0,M199/Config!$B$4,0) | S199: =IF(Config!$B$4>0,K199/Config!$B$4,0) | T199: =R199*Config!$B$7 | U199: =S199*Config!$B$7 | V199: 6 | W199: 30 | X199: =IF(T199>0,V199/T199,0) | Y199: =IF(U199>0,W199/U199,0) | Z199: =T199-V199 | AA199: =U199-W199 | AB199: =IF(Config!$B$7>0,(V199/Config!$B$7)*Config!$B$4,0) | AC199: =IF(Config!$B$7>0,(W199/Config!$B$7)*Config!$B$4,0)
E200: Dry Fruit Mix_15-2402 | G200: Dry Fruit Mix | H200: Trail Mix Farmley Standee Pouch 200 g | J200: 0 | K200: 0 | L200: CPC-C P C Master Canteen | M200: 0 | N200: CPC KPKB | O200: Indore | Q200: Trail Mixes | R200: =IF(Config!$B$4>0,M200/Config!$B$4,0) | S200: =IF(Config!$B$4>0,K200/Config!$B$4,0) | T200: =R200*Config!$B$7 | U200: =S200*Config!$B$7 | V200: 6 | W200: 30 | X200: =IF(T200>0,V200/T200,0) | Y200: =IF(U200>0,W200/U200,0) | Z200: =T200-V200 | AA200: =U200-W200 | AB200: =IF(Config!$B$7>0,(V200/Config!$B$7)*Config!$B$4,0) | AC200: =IF(Config!$B$7>0,(W200/Config!$B$7)*Config!$B$4,0)
E201: Dry Fruit Mix_15-2402 | G201: Dry Fruit Mix | H201: Trail Mix Farmley Standee Pouch 200 g | J201: 0 | K201: 0 | L201: CPC-CPC Master Canteen 7th Res Bn Jaipur | M201: 0 | N201: CPC KPKB | O201: Indore | Q201: Trail Mixes | R201: =IF(Config!$B$4>0,M201/Config!$B$4,0) | S201: =IF(Config!$B$4>0,K201/Config!$B$4,0) | T201: =R201*Config!$B$7 | U201: =S201*Config!$B$7 | V201: 12 | W201: 60 | X201: =IF(T201>0,V201/T201,0) | Y201: =IF(U201>0,W201/U201,0) | Z201: =T201-V201 | AA201: =U201-W201 | AB201: =IF(Config!$B$7>0,(V201/Config!$B$7)*Config!$B$4,0) | AC201: =IF(Config!$B$7>0,(W201/Config!$B$7)*Config!$B$4,0)
... E216: Dry Fruit Mix_15-2402 | G216: Dry Fruit Mix | H216: Trail Mix Farmley Standee Pouch 200 g | J216: 0 | K216: 0 | L216: PJTJ Technologies Private Limited | M216: 0 | N216: Quick Commerce | O216: Indore | Q216: Trail Mixes | R216: =IF(Config!$B$4>0,M216/Config!$B$4,0) | S216: =IF(Config!$B$4>0,K216/Config!$B$4,0) | T216: =R216*Config!$B$7 | U216: =S216*Config!$B$7 | V216: 174 | W216: 870 | X216: =IF(T216>0,V216/T216,0) | Y216: =IF(U216>0,W216/U216,0) | Z216: =T216-V216 | AA216: =U216-W216 | AB216: =IF(Config!$B$7>0,(V216/Config!$B$7)*Config!$B$4,0) | AC216: =IF(Config!$B$7>0,(W216/Config!$B$7)*Config!$B$4,0)
A217: May | B217: 2026 | C217: 29-04-2026 | D217: 0.47065972 | E217: Dry Fruit Mix_15-2404 | F217: FG | G217: Berry Mix | H217: Berry Mix Farmley Standee Pouch 200 g | I217: Berry Mix | J217: 0.2 | K217: 76398 | L217: 46 Customers | M217: 15279.6 | N217: Multiple | O217: Indore | P217: Value Added | Q217: Berry Mix | R217: =IF(Config!$B$4>0,M217/Config!$B$4,0) | S217: =IF(Config!$B$4>0,K217/Config!$B$4,0) | T217: =R217*Config!$B$7 | U217: =S217*Config!$B$7 | V217: 7650 | W217: 38250 | X217: =IF(T217>0,V217/T217,0) | Y217: =IF(U217>0,W217/U217,0) | Z217: =T217-V217 | AA217: =U217-W217 | AB217: =IF(Config!$B$7>0,(V217/Config!$B$7)*Config!$B$4,0) | AC217: =IF(Config!$B$7>0,(W217/Config!$B$7)*Config!$B$4,0)
A218: May | B218: 2026 | C218: 29-04-2026 | D218: 0.47065972 | E218: Dry Fruit Mix_15-2404 | F218: FG | G218: Berry Mix | H218: Berry Mix Farmley Standee Pouch 200 g | I218: Berry Mix | J218: 0.2 | K218: 3600 | L218: CPC KPKB | M218: 720 | N218: CPC | O218: Indore | P218: Value Added | Q218: Berry Mix | R218: =IF(Config!$B$4>0,M218/Config!$B$4,0) | S218: =IF(Config!$B$4>0,K218/Config!$B$4,0) | T218: =R218*Config!$B$7 | U218: =S218*Config!$B$7 | V218: 0 | W218: 0 | X218: =IF(T218>0,V218/T218,0) | Y218: =IF(U218>0,W218/U218,0) | Z218: =T218-V218 | AA218: =U218-W218 | AB218: =IF(Config!$B$7>0,(V218/Config!$B$7)*Config!$B$4,0) | AC218: =IF(Config!$B$7>0,(W218/Config!$B$7)*Config!$B$4,0)
A219: May | B219: 2026 | C219: 29-04-2026 | D219: 0.53009259 | E219: Dry Fruit Mix_15-2404 | F219: FG | G219: Berry Mix | H219: Berry Mix Farmley Standee Pouch 200 g | I219: Berry Mix | J219: 0.2 | K219: 1600 | L219: Metro Cash & Carry India Private Limited | M219: 320 | N219: Modern Trade | O219: Indore | P219: Value Added | Q219: Berry Mix | R219: =IF(Config!$B$4>0,M219/Config!$B$4,0) | S219: =IF(Config!$B$4>0,K219/Config!$B$4,0) | T219: =R219*Config!$B$7 | U219: =S219*Config!$B$7 | V219: 126 | W219: 630 | X219: =IF(T219>0,V219/T219,0) | Y219: =IF(U219>0,W219/U219,0) | Z219: =T219-V219 | AA219: =U219-W219 | AB219: =IF(Config!$B$7>0,(V219/Config!$B$7)*Config!$B$4,0) | AC219: =IF(Config!$B$7>0,(W219/Config!$B$7)*Config!$B$4,0)
A220: May | B220: 2026 | C220: 29-04-2026 | D220: 0.68865741 | E220: Dry Fruit Mix_15-2404 | F220: FG | G220: Berry Mix | H220: Berry Mix Farmley Standee Pouch 200 g | I220: Berry Mix | J220: 0.2 | K220: 434 | L220: Farmley Website B2C | M220: 86.8 | N220: Own Website | O220: Indore | P220: Value Added | Q220: Berry Mix | R220: =IF(Config!$B$4>0,M220/Config!$B$4,0) | S220: =IF(Config!$B$4>0,K220/Config!$B$4,0) | T220: =R220*Config!$B$7 | U220: =S220*Config!$B$7 | V220: 0 | W220: 0 | X220: =IF(T220>0,V220/T220,0) | Y220: =IF(U220>0,W220/U220,0) | Z220: =T220-V220 | AA220: =U220-W220 | AB220: =IF(Config!$B$7>0,(V220/Config!$B$7)*Config!$B$4,0) | AC220: =IF(Config!$B$7>0,(W220/Config!$B$7)*Config!$B$4,0)
A221: May | B221: 2026 | C221: 27-04-2026 | D221: 0.72568287 | E221: Dry Fruit Mix_15-2404 | F221: FG | G221: Berry Mix | H221: Berry Mix Farmley Standee Pouch 200 g | I221: Berry Mix | J221: 0.2 | K221: 90 | L221: Mumbai Travel Retail Private Limited | M221: 18 | N221: Other Institutions | O221: Indore | P221: Value Added | Q221: Berry Mix | R221: =IF(Config!$B$4>0,M221/Config!$B$4,0) | S221: =IF(Config!$B$4>0,K221/Config!$B$4,0) | T221: =R221*Config!$B$7 | U221: =S221*Config!$B$7 | V221: 0 | W221: 0 | X221: =IF(T221>0,V221/T221,0) | Y221: =IF(U221>0,W221/U221,0) | Z221: =T221-V221 | AA221: =U221-W221 | AB221: =IF(Config!$B$7>0,(V221/Config!$B$7)*Config!$B$4,0) | AC221: =IF(Config!$B$7>0,(W221/Config!$B$7)*Config!$B$4,0)
A222: May | B222: 2026 | C222: 27-04-2026 | D222: 0.72568287 | E222: Dry Fruit Mix_15-2404 | F222: FG | G222: Berry Mix | H222: Berry Mix Farmley Standee Pouch 200 g | I222: Berry Mix | J222: 0.2 | K222: 150 | L222: April Moon Retail Limited | M222: 30 | N222: Other Institutions | O222: Indore | P222: Value Added | Q222: Berry Mix | R222: =IF(Config!$B$4>0,M222/Config!$B$4,0) | S222: =IF(Config!$B$4>0,K222/Config!$B$4,0) | T222: =R222*Config!$B$7 | U222: =S222*Config!$B$7 | V222: 0 | W222: 0 | X222: =IF(T222>0,V222/T222,0) | Y222: =IF(U222>0,W222/U222,0) | Z222: =T222-V222 | AA222: =U222-W222 | AB222: =IF(Config!$B$7>0,(V222/Config!$B$7)*Config!$B$4,0) | AC222: =IF(Config!$B$7>0,(W222/Config!$B$7)*Config!$B$4,0)
...

Sheet RunRate by Cust Group
A1: Month | B1: Year | C1: Last Modified Date | D1: Last Modified Time | E1: Item Code | F1: BOM Item Type | G1: Item Group | H1: Item Name | I1: Item Parent | J1: Conversion Factor | K1: Projection Units | L1: Customer | M1: Total KGs | N1: Customer Group | O1: Origin | P1: Item Type | Q1: New MIS Item Group | R1: Daily Demand(Total KGs) | S1: Daily Demand(Projection Units) | T1: Projected KGs as of period | U1: Projected Units as of period | V1: Actual SO KGs | W1: Actual SO Units | X1: Achievement % KGs | Y1: Achievement % Units | Z1: Diff Proj-SO KGs | AA1: Diff Proj-SO Units | AB1: Run Rate Month-End KGs | AC1: Run Rate Month-End Units
A2: May | B2: 2026 | C2: 29-04-2026 | D2: 0.47064815 | E2: Multiple | F2: FG | G2: Roasted & Flavoured Makhana | H2: CSD | I2: Prasadam Roasted Makhana | J2: 0.083 | K2: 11418 | L2: Canteen Store Department (CSD) | M2: 1273.7 | N2: CSD | O2: Multiple | P2: Value Added | Q2: Roasted & Flavoured Makhana | R2: =IF(Config!$B$4>0,M2/Config!$B$4,0) | S2: =IF(Config!$B$4>0,K2/Config!$B$4,0) | T2: =R2*Config!$B$7 | U2: =S2*Config!$B$7 | V2: 0 | W2: 0 | X2: =IF(T2>0,V2/T2,0) | Y2: =IF(U2>0,W2/U2,0) | Z2: =T2-V2 | AA2: =U2-W2 | AB2: =IF(Config!$B$7>0,(V2/Config!$B$7)*Config!$B$4,0) | AC2: =IF(Config!$B$7>0,(W2/Config!$B$7)*Config!$B$4,0)
A3: May | B3: 2026 | C3: 29-04-2026 | D3: 0.47064815 | E3: Makhana_7-30163 | F3: FG | G3: Roasted & Flavoured Makhana | H3: Roasted & Flavored Makhana - Tangy Tomato Farmley Composite Jar 83 g | I3: Prasadam Roasted Makhana | J3: 0.083 | K3: 2904 | L3: Canteen Store Department (CSD) | M3: 241.03 | N3: CSD | O3: Purnea | P3: Value Added | Q3: Roasted & Flavoured Makhana | R3: =IF(Config!$B$4>0,M3/Config!$B$4,0) | S3: =IF(Config!$B$4>0,K3/Config!$B$4,0) | T3: =R3*Config!$B$7 | U3: =S3*Config!$B$7 | V3: 0 | W3: 0 | X3: =IF(T3>0,V3/T3,0) | Y3: =IF(U3>0,W3/U3,0) | Z3: =T3-V3 | AA3: =U3-W3 | AB3: =IF(Config!$B$7>0,(V3/Config!$B$7)*Config!$B$4,0) | AC3: =IF(Config!$B$7>0,(W3/Config!$B$7)*Config!$B$4,0)
A4: May | B4: 2026 | C4: 29-04-2026 | D4: 0.47065972 | E4: Makhana_7-30166 | F4: FG | G4: Roasted & Flavoured Makhana | H4: Roasted & Flavored Makhana - Mint Farmley Composite Jar 83 g | I4: Prasadam Roasted Makhana | J4: 0.083 | K4: 2736 | L4: Canteen Store Department (CSD) | M4: 227.09 | N4: CSD | O4: Purnea | P4: Value Added | Q4: Roasted & Flavoured Makhana | R4: =IF(Config!$B$4>0,M4/Config!$B$4,0) | S4: =IF(Config!$B$4>0,K4/Config!$B$4,0) | T4: =R4*Config!$B$7 | U4: =S4*Config!$B$7 | V4: 0 | W4: 0 | X4: =IF(T4>0,V4/T4,0) | Y4: =IF(U4>0,W4/U4,0) | Z4: =T4-V4 | AA4: =U4-W4 | AB4: =IF(Config!$B$7>0,(V4/Config!$B$7)*Config!$B$4,0) | AC4: =IF(Config!$B$7>0,(W4/Config!$B$7)*Config!$B$4,0)
A5: May | B5: 2026 | C5: 29-04-2026 | D5: 0.47065972 | E5: Makhana_7-30167 | F5: FG | G5: Roasted & Flavoured Makhana | H5: Roasted & Salted Makhana Farmley Composite Jar 83 g | I5: Prasadam Roasted Makhana | J5: 0.083 | K5: 2448 | L5: Canteen Store Department (CSD) | M5: 203.18 | N5: CSD | O5: Purnea | P5: Value Added | Q5: Roasted & Flavoured Makhana | R5: =IF(Config!$B$4>0,M5/Config!$B$4,0) | S5: =IF(Config!$B$4>0,K5/Config!$B$4,0) | T5: =R5*Config!$B$7 | U5: =S5*Config!$B$7 | V5: 0 | W5: 0 | X5: =IF(T5>0,V5/T5,0) | Y5: =IF(U5>0,W5/U5,0) | Z5: =T5-V5 | AA5: =U5-W5 | AB5: =IF(Config!$B$7>0,(V5/Config!$B$7)*Config!$B$4,0) | AC5: =IF(Config!$B$7>0,(W5/Config!$B$7)*Config!$B$4,0)
A6: May | B6: 2026 | C6: 29-04-2026 | D6: 0.47065972 | E6: Dry Fruit Mix_15-2941 | F6: FG | G6: Seed Mix | H6: Seed mix Farmley 160g Standee Pouches | I6: Seed Mix | J6: 0.16 | K6: 1590 | L6: Canteen Store Department (CSD) | M6: 254.4 | N6: CSD | O6: Indore | P6: Value Added | Q6: Seed Mix | R6: =IF(Config!$B$4>0,M6/Config!$B$4,0) | S6: =IF(Config!$B$4>0,K6/Config!$B$4,0) | T6: =R6*Config!$B$7 | U6: =S6*Config!$B$7 | V6: 0 | W6: 0 | X6: =IF(T6>0,V6/T6,0) | Y6: =IF(U6>0,W6/U6,0) | Z6: =T6-V6 | AA6: =U6-W6 | AB6: =IF(Config!$B$7>0,(V6/Config!$B$7)*Config!$B$4,0) | AC6: =IF(Config!$B$7>0,(W6/Config!$B$7)*Config!$B$4,0)
A7: May | B7: 2026 | C7: 29-04-2026 | D7: 0.47065972 | E7: Seeds_11-2541 | F7: FG | G7: Chia Seeds | H7: Premium Chia Seeds Farmley Standee Pouch 200 g | I7: Premium Chia Seeds | J7: 0.2 | K7: 1740 | L7: Canteen Store Department (CSD) | M7: 348 | N7: CSD | O7: Indore | P7: KVI | Q7: Chia Seeds | R7: =IF(Config!$B$4>0,M7/Config!$B$4,0) | S7: =IF(Config!$B$4>0,K7/Config!$B$4,0) | T7: =R7*Config!$B$7 | U7: =S7*Config!$B$7 | V7: 0 | W7: 0 | X7: =IF(T7>0,V7/T7,0) | Y7: =IF(U7>0,W7/U7,0) | Z7: =T7-V7 | AA7: =U7-W7 | AB7: =IF(Config!$B$7>0,(V7/Config!$B$7)*Config!$B$4,0) | AC7: =IF(Config!$B$7>0,(W7/Config!$B$7)*Config!$B$4,0)
A8: May | B8: 2026 | C8: 29-04-2026 | D8: 0.47065972 | E8: Multiple | F8: FG | G8: Cashew | H8: CPC | I8: Premium W320 Cashew | J8: 0.5 | K8: 116224 | L8: CPC KPKB | M8: 33831.95 | N8: CPC | O8: Multiple | P8: KVI | Q8: Cashew | R8: =IF(Config!$B$4>0,M8/Config!$B$4,0) | S8: =IF(Config!$B$4>0,K8/Config!$B$4,0) | T8: =R8*Config!$B$7 | U8: =S8*Config!$B$7 | V8: 0 | W8: 0 | X8: =IF(T8>0,V8/T8,0) | Y8: =IF(U8>0,W8/U8,0) | Z8: =T8-V8 | AA8: =U8-W8 | AB8: =IF(Config!$B$7>0,(V8/Config!$B$7)*Config!$B$4,0) | AC8: =IF(Config!$B$7>0,(W8/Config!$B$7)*Config!$B$4,0)
A9: May | B9: 2026 | C9: 29-04-2026 | D9: 0.47065972 | E9: Cashewnut_3-1987 | F9: FG | G9: Cashew | H9: Premium W320 Cashew Farmley Standee Pouch 500 g | I9: Premium W320 Cashew | J9: 0.5 | K9: 8700 | L9: CPC KPKB | M9: 4350 | N9: CPC | O9: Indore | P9: KVI | Q9: Cashew | R9: =IF(Config!$B$4>0,M9/Config!$B$4,0) | S9: =IF(Config!$B$4>0,K9/Config!$B$4,0) | T9: =R9*Config!$B$7 | U9: =S9*Config!$B$7 | V9: 0 | W9: 0 | X9: =IF(T9>0,V9/T9,0) | Y9: =IF(U9>0,W9/U9,0) | Z9: =T9-V9 | AA9: =U9-W9 | AB9: =IF(Config!$B$7>0,(V9/Config!$B$7)*Config!$B$4,0) | AC9: =IF(Config!$B$7>0,(W9/Config!$B$7)*Config!$B$4,0)
A10: May | B10: 2026 | C10: 29-04-2026 | D10: 0.47065972 | E10: Almonds_1-1748 | F10: FG | G10: Almonds | H10: Premium California Almonds Farmley Standee Pouch 500 g | I10: Premium California Almonds | J10: 0.5 | K10: 9840 | L10: CPC KPKB | M10: 4920 | N10: CPC | O10: Indore | P10: KVI | Q10: Almonds | R10: =IF(Config!$B$4>0,M10/Config!$B$4,0) | S10: =IF(Config!$B$4>0,K10/Config!$B$4,0) | T10: =R10*Config!$B$7 | U10: =S10*Config!$B$7 | V10: 0 | W10: 0 | X10: =IF(T10>0,V10/T10,0) | Y10: =IF(U10>0,W10/U10,0) | Z10: =T10-V10 | AA10: =U10-W10 | AB10: =IF(Config!$B$7>0,(V10/Config!$B$7)*Config!$B$4,0) | AC10: =IF(Config!$B$7>0,(W10/Config!$B$7)*Config!$B$4,0)
A11: May | B11: 2026 | C11: 29-04-2026 | D11: 0.47065972 | E11: Dry Fruit Mix_15-2402 | F11: FG | G11: Trail Mixes | H11: Trail Mix Farmley Standee Pouch 200 g | I11: Trail Mix | J11: 0.2 | K11: 3600 | L11: CPC KPKB | M11: 720 | N11: CPC | O11: Indore | P11: Value Added | Q11: Trail Mixes | R11: =IF(Config!$B$4>0,M11/Config!$B$4,0) | S11: =IF(Config!$B$4>0,K11/Config!$B$4,0) | T11: =R11*Config!$B$7 | U11: =S11*Config!$B$7 | V11: 0 | W11: 0 | X11: =IF(T11>0,V11/T11,0) | Y11: =IF(U11>0,W11/U11,0) | Z11: =T11-V11 | AA11: =U11-W11 | AB11: =IF(Config!$B$7>0,(V11/Config!$B$7)*Config!$B$4,0) | AC11: =IF(Config!$B$7>0,(W11/Config!$B$7)*Config!$B$4,0)
A12: May | B12: 2026 | C12: 29-04-2026 | D12: 0.47065972 | E12: Dry Fruit Mix_15-2404 | F12: FG | G12: Berry Mix | H12: Berry Mix Farmley Standee Pouch 200 g | I12: Berry Mix | J12: 0.2 | K12: 3600 | L12: CPC KPKB | M12: 720 | N12: CPC | O12: Indore | P12: Value Added | Q12: Berry Mix | R12: =IF(Config!$B$4>0,M12/Config!$B$4,0) | S12: =IF(Config!$B$4>0,K12/Config!$B$4,0) | T12: =R12*Config!$B$7 | U12: =S12*Config!$B$7 | V12: 0 | W12: 0 | X12: =IF(T12>0,V12/T12,0) | Y12: =IF(U12>0,W12/U12,0) | Z12: =T12-V12 | AA12: =U12-W12 | AB12: =IF(Config!$B$7>0,(V12/Config!$B$7)*Config!$B$4,0) | AC12: =IF(Config!$B$7>0,(W12/Config!$B$7)*Config!$B$4,0)
A13: May | B13: 2026 | C13: 29-04-2026 | D13: 0.47065972 | E13: Cashewnut_3-2472 | F13: FG | G13: Roasted & Flavoured Cashew | H13: Roasted and Salted Cashew - Farmley Standee Pouch 200 g | I13: Roasted and Salted Cashew | J13: 0.2 | K13: 4500 | L13: CPC KPKB | M13: 900 | N13: CPC | O13: Indore | P13: Value Added | Q13: Roasted & Flavoured Cashew | R13: =IF(Config!$B$4>0,M13/Config!$B$4,0) | S13: =IF(Config!$B$4>0,K13/Config!$B$4,0) | T13: =R13*Config!$B$7 | U13: =S13*Config!$B$7 | V13: 0 | W13: 0 | X13: =IF(T13>0,V13/T13,0) | Y13: =IF(U13>0,W13/U13,0) | Z13: =T13-V13 | AA13: =U13-W13 | AB13: =IF(Config!$B$7>0,(V13/Config!$B$7)*Config!$B$4,0) | AC13: =IF(Config!$B$7>0,(W13/Config!$B$7)*Config!$B$4,0)
... A31: May | B31: 2026 | C31: 29-04-2026 | D31: 0.47068287 | E31: Seeds_11-2550 | F31: FG | G31: Other Seeds | H31: Premium Flax Seeds Farmley Standee Pouch 200 g | I31: Premium Flax Seeds | J31: 0.2 | K31: 720 | L31: CPC KPKB | M31: 144 | N31: CPC | O31: Indore | P31: KVI | Q31: Other Seeds | R31: =IF(Config!$B$4>0,M31/Config!$B$4,0) | S31: =IF(Config!$B$4>0,K31/Config!$B$4,0) | T31: =R31*Config!$B$7 | U31: =S31*Config!$B$7 | V31: 0 | W31: 0 | X31: =IF(T31>0,V31/T31,0) | Y31: =IF(U31>0,W31/U31,0) | Z31: =T31-V31 | AA31: =U31-W31 | AB31: =IF(Config!$B$7>0,(V31/Config!$B$7)*Config!$B$4,0) | AC31: =IF(Config!$B$7>0,(W31/Config!$B$7)*Config!$B$4,0)
A32: May | B32: 2026 | C32: 29-04-2026 | D32: 0.47068287 | E32: Raisins_10-2382 | F32: FG | G32: Raisins | H32: Premium Munakka Farmley Standee Pouch 200 g | I32: Premium Munakka | J32: 0.2 | K32: 6150 | L32: CPC KPKB | M32: 1230 | N32: CPC | O32: Indore | P32: KVI | R32: =IF(Config!$B$4>0,M32/Config!$B$4,0) | S32: =IF(Config!$B$4>0,K32/Config!$B$4,0) | T32: =R32*Config!$B$7 | U32: =S32*Config!$B$7 | V32: 0 | W32: 0 | X32: =IF(T32>0,V32/T32,0) | Y32: =IF(U32>0,W32/U32,0) | Z32: =T32-V32 | AA32: =U32-W32 | AB32: =IF(Config!$B$7>0,(V32/Config!$B$7)*Config!$B$4,0) | AC32: =IF(Config!$B$7>0,(W32/Config!$B$7)*Config!$B$4,0)
A33: May | B33: 2026 | C33: 29-04-2026 | D33: 0.47068287 | E33: Dry Fruit Mix_15-2923 | F33: FG | G33: Trail Mixes | H33: Trail Mix Farmley Jar 450 g | I33: Trail Mix | J33: 0.45 | K33: 2064 | L33: CPC KPKB | M33: 928.8 | N33: CPC | O33: Indore | P33: Value Added | Q33: Trail Mixes | R33: =IF(Config!$B$4>0,M33/Config!$B$4,0) | S33: =IF(Config!$B$4>0,K33/Config!$B$4,0) | T33: =R33*Config!$B$7 | U33: =S33*Config!$B$7 | V33: 0 | W33: 0 | X33: =IF(T33>0,V33/T33,0) | Y33: =IF(U33>0,W33/U33,0) | Z33: =T33-V33 | AA33: =U33-W33 | AB33: =IF(Config!$B$7>0,(V33/Config!$B$7)*Config!$B$4,0) | AC33: =IF(Config!$B$7>0,(W33/Config!$B$7)*Config!$B$4,0)
A34: May | B34: 2026 | C34: 29-04-2026 | D34: 0.53008102 | E34: Multiple | F34: FG | G34: Makhana Raw | H34: Modern Trade | I34: Prasadam Makhana | J34: 0.2 | K34: 96825 | L34: 15 Customers | M34: 23848.5 | N34: Modern Trade | O34: Multiple | P34: KVI | Q34: Makhana Raw | R34: =IF(Config!$B$4>0,M34/Config!$B$4,0) | S34: =IF(Config!$B$4>0,K34/Config!$B$4,0) | T34: =R34*Config!$B$7 | U34: =S34*Config!$B$7 | V34: 9197.38 | W34: 40023 | X34: =IF(T34>0,V34/T34,0) | Y34: =IF(U34>0,W34/U34,0) | Z34: =T34-V34 | AA34: =U34-W34 | AB34: =IF(Config!$B$7>0,(V34/Config!$B$7)*Config!$B$4,0) | AC34: =IF(Config!$B$7>0,(W34/Config!$B$7)*Config!$B$4,0)
A35: May | B35: 2026 | C35: 29-04-2026 | D35: 0.53008102 | E35: Makhana_7-30098 | F35: FG | G35: Makhana Raw | H35: Prasadam Makhana Center Seal Pouch 200 g- NEW | I35: Prasadam Makhana | J35: 0.2 | K35: 3000 | L35: Metro Cash & Carry India Private Limited | M35: 600 | N35: Modern Trade | O35: Purnea | P35: KVI | Q35: Makhana Raw | R35: =IF(Config!$B$4>0,M35/Config!$B$4,0) | S35: =IF(Config!$B$4>0,K35/Config!$B$4,0) | T35: =R35*Config!$B$7 | U35: =S35*Config!$B$7 | V35: 456 | W35: 2280 | X35: =IF(T35>0,V35/T35,0) | Y35: =IF(U35>0,W35/U35,0) | Z35: =T35-V35 | AA35: =U35-W35 | AB35: =IF(Config!$B$7>0,(V35/Config!$B$7)*Config!$B$4,0) | AC35: =IF(Config!$B$7>0,(W35/Config!$B$7)*Config!$B$4,0)
A36: May | B36: 2026 | C36: 29-04-2026 | D36: 0.53008102 | E36: Dry Fruit Mix_15-2800 | F36: FG | G36: Trail Mixes | H36: Premium Panchmeva Farmley Jar 425 g- Institutional | I36: Premium Panchmewa Superfood | J36: 0.425 | K36: 4500 | L36: Metro Cash & Carry India Private Limited | M36: 1912.5 | N36: Modern Trade | O36: Indore | P36: Value Added | Q36: Trail Mixes | R36: =IF(Config!$B$4>0,M36/Config!$B$4,0) | S36: =IF(Config!$B$4>0,K36/Config!$B$4,0) | T36: =R36*Config!$B$7 | U36: =S36*Config!$B$7 | V36: 40.8 | W36: 96 | X36: =IF(T36>0,V36/T36,0) | Y36: =IF(U36>0,W36/U36,0) | Z36: =T36-V36 | AA36: =U36-W36 | AB36: =IF(Config!$B$7>0,(V36/Config!$B$7)*Config!$B$4,0) | AC36: =IF(Config!$B$7>0,(W36/Config!$B$7)*Config!$B$4,0)
A37: May | B37: 2026 | C37: 29-04-2026 | D37: 0.53008102 | E37: Almonds_1-196 | F37: FG | G37: Almonds | H37: Popular California Almonds Farmley Standee Pouch 1 kg | I37: Popular California Almonds | J37: 1 | K37: 400 | L37: Metro Cash & Carry India Private Limited | M37: 400 | N37: Modern Trade | O37: Indore | P37: KVI | Q37: Almonds | R37: =IF(Config!$B$4>0,M37/Config!$B$4,0) | S37: =IF(Config!$B$4>0,K37/Config!$B$4,0) | T37: =R37*Config!$B$7 | U37: =S37*Config!$B$7 | V37: 312 | W37: 312 | X37: =IF(T37>0,V37/T37,0) | Y37: =IF(U37>0,W37/U37,0) | Z37: =T37-V37 | AA37: =U37-W37 | AB37: =IF(Config!$B$7>0,(V37/Config!$B$7)*Config!$B$4,0) | AC37: =IF(Config!$B$7>0,(W37/Config!$B$7)*Config!$B$4,0)
A38: May | B38: 2026 | C38: 29-04-2026 | D38: 0.53008102 | E38: Almonds_1-1750 | F38: FG | G38: Almonds | H38: Popular California Almonds Farmley Standee Pouch 500 g | I38: Popular California Almonds | J38: 0.5 | K38: 1500 | L38: Metro Cash & Carry India Private Limited | M38: 750 | N38: Modern Trade | O38: Indore | P38: KVI | Q38: Almonds | R38: =IF(Config!$B$4>0,M38/Config!$B$4,0) | S38: =IF(Config!$B$4>0,K38/Config!$B$4,0) | T38: =R38*Config!$B$7 | U38: =S38*Config!$B$7 | V38: 392 | W38: 784 | X38: =IF(T38>0,V38/T38,0) | Y38: =IF(U38>0,W38/U38,0) | Z38: =T38-V38 | AA38: =U38-W38 | AB38: =IF(Config!$B$7>0,(V38/Config!$B$7)*Config!$B$4,0) | AC38: =IF(Config!$B$7>0,(W38/Config!$B$7)*Config!$B$4,0)
A39: May | B39: 2026 | C39: 29-04-2026 | D39: 0.53008102 | E39: Makhana_7-30096 | F39: FG | G39: Makhana Raw | H39: Prasadam Makhana Center Seal Pouch 100 g- NEW | I39: Prasadam Makhana | J39: 0.1 | K39: 800 | L39: Metro Cash & Carry India Private Limited | M39: 80 | N39: Modern Trade | O39: Purnea | P39: KVI | Q39: Makhana Raw | R39: =IF(Config!$B$4>0,M39/Config!$B$4,0) | S39: =IF(Config!$B$4>0,K39/Config!$B$4,0) | T39: =R39*Config!$B$7 | U39: =S39*Config!$B$7 | V39: 136 | W39: 1360 | X39: =IF(T39>0,V39/T39,0) | Y39: =IF(U39>0,W39/U39,0) | Z39: =T39-V39 | AA39: =U39-W39 | AB39: =IF(Config!$B$7>0,(V39/Config!$B$7)*Config!$B$4,0) | AC39: =IF(Config!$B$7>0,(W39/Config!$B$7)*Config!$B$4,0)
A40: May | B40: 2026 | C40: 29-04-2026 | D40: 0.53008102 | E40: Seeds_11-2541 | F40: FG | G40: Chia Seeds | H40: Premium Chia Seeds Farmley Standee Pouch 200 g | I40: Premium Chia Seeds | J40: 0.2 | K40: 4000 | L40: Metro Cash & Carry India Private Limited | M40: 800 | N40: Modern Trade | O40: Indore | P40: KVI | Q40: Chia Seeds | R40: =IF(Config!$B$4>0,M40/Config!$B$4,0) | S40: =IF(Config!$B$4>0,K40/Config!$B$4,0) | T40: =R40*Config!$B$7 | U40: =S40*Config!$B$7 | V40: 390 | W40: 1950 | X40: =IF(T40>0,V40/T40,0) | Y40: =IF(U40>0,W40/U40,0) | Z40: =T40-V40 | AA40: =U40-W40 | AB40: =IF(Config!$B$7>0,(V40/Config!$B$7)*Config!$B$4,0) | AC40: =IF(Config!$B$7>0,(W40/Config!$B$7)*Config!$B$4,0)
A41: May | B41: 2026 | C41: 29-04-2026 | D41: 0.53009259 | E41: Dates_4-2469 | F41: FG | G41: Dates | H41: Premium Omani Fard Dates Farmley standee pouch 400 g | I41: Premium Fard Dates | J41: 0.4 | K41: 2800 | L41: Metro Cash & Carry India Private Limited | M41: 1120 | N41: Modern Trade | O41: Indore | P41: KVI | Q41: Dates | R41: =IF(Config!$B$4>0,M41/Config!$B$4,0) | S41: =IF(Config!$B$4>0,K41/Config!$B$4,0) | T41: =R41*Config!$B$7 | U41: =S41*Config!$B$7 | V41: 828 | W41: 2070 | X41: =IF(T41>0,V41/T41,0) | Y41: =IF(U41>0,W41/U41,0) | Z41: =T41-V41 | AA41: =U41-W41 | AB41: =IF(Config!$B$7>0,(V41/Config!$B$7)*Config!$B$4,0) | AC41: =IF(Config!$B$7>0,(W41/Config!$B$7)*Config!$B$4,0)
A42: May | B42: 2026 | C42: 29-04-2026 | D42: 0.53009259 | E42: Dry Fruit Mix_15-2403 | F42: FG | G42: Seed Mix | H42: Seed Mix Farmley Standee Pouch 200 g | I42: Seed Mix | J42: 0.2 | K42: 1000 | L42: Metro Cash & Carry India Private Limited | M42: 200 | N42: Modern Trade | O42: Indore | P42: Value Added | Q42: Seed Mix | R42: =IF(Config!$B$4>0,M42/Config!$B$4,0) | S42: =IF(Config!$B$4>0,K42/Config!$B$4,0) | T42: =R42*Config!$B$7 | U42: =S42*Config!$B$7 | V42: 72 | W42: 360 | X42: =IF(T42>0,V42/T42,0) | Y42: =IF(U42>0,W42/U42,0) | Z42: =T42-V42 | AA42: =U42-W42 | AB42: =IF(Config!$B$7>0,(V42/Config!$B$7)*Config!$B$4,0) | AC42: =IF(Config!$B$7>0,(W42/Config!$B$7)*Config!$B$4,0)
A43: May | B43: 2026 | C43: 29-04-2026 | D43: 0.53009259 | E43: Dry Fruit Mix_15-2404 | F43: FG | G43: Berry Mix | H43: Berry Mix Farmley Standee Pouch 200 g | I43: Berry Mix | J43: 0.2 | K43: 1600 | L43: Metro Cash & Carry India Private Limited | M43: 320 | N43: Modern Trade | O43: Indore | P43: Value Added | Q43: Berry Mix | R43: =IF(Config!$B$4>0,M43/Config!$B$4,0) | S43: =IF(Config!$B$4>0,K43/Config!$B$4,0) | T43: =R43*Config!$B$7 | U43: =S43*Config!$B$7 | V43: 126 | W43: 630 | X43: =IF(T43>0,V43/T43,0) | Y43: =IF(U43>0,W43/U43,0) | Z43: =T43-V43 | AA43: =U43-W43 | AB43: =IF(Config!$B$7>0,(V43/Config!$B$7)*Config!$B$4,0) | AC43: =IF(Config!$B$7>0,(W43/Config!$B$7)*Config!$B$4,0)
A44: May | B44: 2026 | C44: 29-04-2026 | D44: 0.53009259 | E44: Dry Fruit Mix_15-2402 | F44: FG | G44: Trail Mixes | H44: Trail Mix Farmley Standee Pouch 200 g | I44: Trail Mix | J44: 0.2 | K44: 800 | L44: Metro Cash & Carry India Private Limited | M44: 160 | N44: Modern Trade | O44: Indore | P44: Value Added | Q44: Trail Mixes | R44: =IF(Config!$B$4>0,M44/Config!$B$4,0) | S44: =IF(Config!$B$4>0,K44/Config!$B$4,0) | T44: =R44*Config!$B$7 | U44: =S44*Config!$B$7 | V44: 132 | W44: 660 | X44: =IF(T44>0,V44/T44,0) | Y44: =IF(U44>0,W44/U44,0) | Z44: =T44-V44 | AA44: =U44-W44 | AB44: =IF(Config!$B$7>0,(V44/Config!$B$7)*Config!$B$4,0) | AC44: =IF(Config!$B$7>0,(W44/Config!$B$7)*Config!$B$4,0)
... A56: May | B56: 2026 | C56: 29-04-2026 | D56: 0.53010417 | E56: Dates_4-20162 | F56: FG | G56: Healthy Desserts | H56: Coffee Rush Date Bite Farmley Tin Jar 200g | I56: Coffee Date Bites | J56: 0.2 | K56: 1000 | L56: Metro Cash & Carry India Private Limited | M56: 200 | N56: Modern Trade | O56: Indore | P56: Value Added | Q56: Healthy Desserts | R56: =IF(Config!$B$4>0,M56/Config!$B$4,0) | S56: =IF(Config!$B$4>0,K56/Config!$B$4,0) | T56: =R56*Config!$B$7 | U56: =S56*Config!$B$7 | V56: 0 | W56: 0 | X56: =IF(T56>0,V56/T56,0) | Y56: =IF(U56>0,W56/U56,0) | Z56: =T56-V56 | AA56: =U56-W56 | AB56: =IF(Config!$B$7>0,(V56/Config!$B$7)*Config!$B$4,0) | AC56: =IF(Config!$B$7>0,(W56/Config!$B$7)*Config!$B$4,0)
A57: May | B57: 2026 | C57: 30-04-2026 | D57: 0.69038194 | E57: Dates_4-20173 | F57: FG | G57: Healthy Desserts | H57: Dark Choco-Orange Date Bite Farmley Monocarton 360g -Pack of 6 (60g each)- with SRP | I57: Date bites choco-Orange | J57: 0.36 | K57: 167 | L57: Metro Cash & Carry India Private Limited | M57: 60.12 | N57: Modern Trade | O57: Indore | P57: Value Added | R57: =IF(Config!$B$4>0,M57/Config!$B$4,0) | S57: =IF(Config!$B$4>0,K57/Config!$B$4,0) | T57: =R57*Config!$B$7 | U57: =S57*Config!$B$7 | V57: 0 | W57: 0 | X57: =IF(T57>0,V57/T57,0) | Y57: =IF(U57>0,W57/U57,0) | Z57: =T57-V57 | AA57: =U57-W57 | AB57: =IF(Config!$B$7>0,(V57/Config!$B$7)*Config!$B$4,0) | AC57: =IF(Config!$B$7>0,(W57/Config!$B$7)*Config!$B$4,0)
A58: May | B58: 2026 | C58: 30-04-2026 | D58: 0.69038194 | E58: Dates_4-20174 | F58: FG | G58: Healthy Desserts | H58: Classic Date Bite Farmley Monocarton 360g- Pack of 6 (60g each)- With SRP | I58: Classic Date bites | J58: 0.36 | K58: 333 | L58: Metro Cash & Carry India Private Limited | M58: 119.88 | N58: Modern Trade | O58: Indore | P58: Value Added | Q58: Healthy Desserts | R58: =IF(Config!$B$4>0,M58/Config!$B$4,0) | S58: =IF(Config!$B$4>0,K58/Config!$B$4,0) | T58: =R58*Config!$B$7 | U58: =S58*Config!$B$7 | V58: 0 | W58: 0 | X58: =IF(T58>0,V58/T58,0) | Y58: =IF(U58>0,W58/U58,0) | Z58: =T58-V58 | AA58: =U58-W58 | AB58: =IF(Config!$B$7>0,(V58/Config!$B$7)*Config!$B$4,0) | AC58: =IF(Config!$B$7>0,(W58/Config!$B$7)*Config!$B$4,0)
A59: May | B59: 2026 | C59: 25-04-2026 | D59: 0.7266088 | E59: Dry Fruit Mix_15-2402 | F59: FG | G59: Trail Mixes | H59: Trail Mix Farmley Standee Pouch 200 g | I59: Trail Mix | J59: 0.2 | K59: 100 | L59: Wal-Mart India Private Limited | M59: 20 | N59: Modern Trade | O59: Indore | P59: Value Added | Q59: Trail Mixes | R59: =IF(Config!$B$4>0,M59/Config!$B$4,0) | S59: =IF(Config!$B$4>0,K59/Config!$B$4,0) | T59: =R59*Config!$B$7 | U59: =S59*Config!$B$7 | V59: 6 | W59: 30 | X59: =IF(T59>0,V59/T59,0) | Y59: =IF(U59>0,W59/U59,0) | Z59: =T59-V59 | AA59: =U59-W59 | AB59: =IF(Config!$B$7>0,(V59/Config!$B$7)*Config!$B$4,0) | AC59: =IF(Config!$B$7>0,(W59/Config!$B$7)*Config!$B$4,0)
A60: May | B60: 2026 | C60: 25-04-2026 | D60: 0.7266088 | E60: Dry Fruit Mix_15-2403 | F60: FG | G60: Seed Mix | H60: Seed Mix Farmley Standee Pouch 200 g | I60: Seed Mix | J60: 0.2 | K60: 150 | L60: Wal-Mart India Private Limited | M60: 30 | N60: Modern Trade | O60: Indore | P60: Value Added | Q60: Seed Mix | R60: =IF(Config!$B$4>0,M60/Config!$B$4,0) | S60: =IF(Config!$B$4>0,K60/Config!$B$4,0) | T60: =R60*Config!$B$7 | U60: =S60*Config!$B$7 | V60: 24 | W60: 120 | X60: =IF(T60>0,V60/T60,0) | Y60: =IF(U60>0,W60/U60,0) | Z60: =T60-V60 | AA60: =U60-W60 | AB60: =IF(Config!$B$7>0,(V60/Config!$B$7)*Config!$B$4,0) | AC60: =IF(Config!$B$7>0,(W60/Config!$B$7)*Config!$B$4,0)
A61: May | B61: 2026 | C61: 25-04-2026 | D61: 0.7266088 | E61: Dry Fruit Mix_15-2404 | F61: FG | G61: Berry Mix | H61: Berry Mix Farmley Standee Pouch 200 g | I61: Berry Mix | J61: 0.2 | K61: 400 | L61: Wal-Mart India Private Limited | M61: 80 | N61: Modern Trade | O61: Indore | P61: Value Added | Q61: Berry Mix | R61: =IF(Config!$B$4>0,M61/Config!$B$4,0) | S61: =IF(Config!$B$4>0,K61/Config!$B$4,0) | T61: =R61*Config!$B$7 | U61: =S61*Config!$B$7 | V61: 36 | W61: 180 | X61: =IF(T61>0,V61/T61,0) | Y61: =IF(U61>0,W61/U61,0) | Z61: =T61-V61 | AA61: =U61-W61 | AB61: =IF(Config!$B$7>0,(V61/Config!$B$7)*Config!$B$4,0) | AC61: =IF(Config!$B$7>0,(W61/Config!$B$7)*Config!$B$4,0)
A62: May | B62: 2026 | C62: 25-04-2026 | D62: 0.7266088 | E62: Walnut_12-1535 | F62: FG | G62: Walnut | H62: Premium Broken Walnut Kernels Farmley Standee Pouch 200 g | I62: Premium Broken Walnut Kernels | J62: 0.2 | K62: 200 | L62: Wal-Mart India Private Limited | M62: 40 | N62: Modern Trade | O62: Indore | P62: KVI | Q62: Walnut | R62: =IF(Config!$B$4>0,M62/Config!$B$4,0) | S62: =IF(Config!$B$4>0,K62/Config!$B$4,0) | T62: =R62*Config!$B$7 | U62: =S62*Config!$B$7 | V62: 19.2 | W62: 96 | X62: =IF(T62>0,V62/T62,0) | Y62: =IF(U62>0,W62/U62,0) | Z62: =T62-V62 | AA62: =U62-W62 | AB62: =IF(Config!$B$7>0,(V62/Config!$B$7)*Config!$B$4,0) | AC62: =IF(Config!$B$7>0,(W62/Config!$B$7)*Config!$B$4,0)
A63: May | B63: 2026 | C63: 25-04-2026 | D63: 0.7266088 | E63: Fig_6-2464 | F63: FG | G63: Figs | H63: Premium Anjeer Farmley Standee Pouch 200 g | I63: Premium Anjeer | J63: 0.2 | K63: 300 | L63: Wal-Mart India Private Limited | M63: 60 | N63: Modern Trade | O63: Indore | P63: KVI | Q63: Figs | R63: =IF(Config!$B$4>0,M63/Config!$B$4,0) | S63: =IF(Config!$B$4>0,K63/Config!$B$4,0) | T63: =R63*Config!$B$7 | U63: =S63*Config!$B$7 | V63: 30 | W63: 150 | X63: =IF(T63>0,V63/T63,0) | Y63: =IF(U63>0,W63/U63,0) | Z63: =T63-V63 | AA63: =U63-W63 | AB63: =IF(Config!$B$7>0,(V63/Config!$B$7)*Config!$B$4,0) | AC63: =IF(Config!$B$7>0,(W63/Config!$B$7)*Config!$B$4,0)
A64: May | B64: 2026 | C64: 25-04-2026 | D64: 0.7266088 | E64: Dates_4-2469 | F64: FG | G64: Dates | H64: Premium Omani Fard Dates Farmley standee pouch 400 g | I64: Premium Fard Dates | J64: 0.4 | K64: 1100 | L64: Wal-Mart India Private Limited | M64: 440 | N64: Modern Trade | O64: Indore | P64: KVI | Q64: Dates | R64: =IF(Config!$B$4>0,M64/Config!$B$4,0) | S64: =IF(Config!$B$4>0,K64/Config!$B$4,0) | T64: =R64*Config!$B$7 | U64: =S64*Config!$B$7 | V64: 0 | W64: 0 | X64: =IF(T64>0,V64/T64,0) | Y64: =IF(U64>0,W64/U64,0) | Z64: =T64-V64 | AA64: =U64-W64 | AB64: =IF(Config!$B$7>0,(V64/Config!$B$7)*Config!$B$4,0) | AC64: =IF(Config!$B$7>0,(W64/Config!$B$7)*Config!$B$4,0)
A65: May | B65: 2026 | C65: 25-04-2026 | D65: 0.7266088 | E65: Dry Fruit Mix_15-2800 | F65: FG | G65: Trail Mixes | H65: Premium Panchmeva Farmley Jar 425 g- Institutional | I65: Premium Panchmewa Superfood | J65: 0.425 | K65: 200 | L65: Wal-Mart India Private Limited | M65: 85 | N65: Modern Trade | O65: Indore | P65: Value Added | Q65: Trail Mixes | R65: =IF(Config!$B$4>0,M65/Config!$B$4,0) | S65: =IF(Config!$B$4>0,K65/Config!$B$4,0) | T65: =R65*Config!$B$7 | U65: =S65*Config!$B$7 | V65: 61.2 | W65: 144 | X65: =IF(T65>0,V65/T65,0) | Y65: =IF(U65>0,W65/U65,0) | Z65: =T65-V65 | AA65: =U65-W65 | AB65: =IF(Config!$B$7>0,(V65/Config!$B$7)*Config!$B$4,0) | AC65: =IF(Config!$B$7>0,(W65/Config!$B$7)*Config!$B$4,0)
A66: May | B66: 2026 | C66: 25-04-2026 | D66: 0.7266088 | E66: Cashewnut_3-1987 | F66: FG | G66: Cashew | H66: Premium W320 Cashew Farmley Standee Pouch 500 g | I66: Premium W320 Cashew | J66: 0.5 | K66: 100 | L66: Wal-Mart India Private Limited | M66: 50 | N66: Modern Trade | O66: Udupi | P66: KVI | Q66: Cashew | R66: =IF(Config!$B$4>0,M66/Config!$B$4,0) | S66: =IF(Config!$B$4>0,K66/Config!$B$4,0) | T66: =R66*Config!$B$7 | U66: =S66*Config!$B$7 | V66: 100 | W66: 200 | X66: =IF(T66>0,V66/T66,0) | Y66: =IF(U66>0,W66/U66,0) | Z66: =T66-V66 | AA66: =U66-W66 | AB66: =IF(Config!$B$7>0,(V66/Config!$B$7)*Config!$B$4,0) | AC66: =IF(Config!$B$7>0,(W66/Config!$B$7)*Config!$B$4,0)
A67: May | B67: 2026 | C67: 25-04-2026 | D67: 0.7266088 | E67: Makhana_7-30098 | F67: FG | G67: Makhana Raw | H67: Prasadam Makhana Center Seal Pouch 200 g- NEW | I67: Prasadam Makhana | J67: 0.2 | K67: 400 | L67: Wal-Mart India Private Limited | M67: 80 | N67: Modern Trade | O67: Purnea | P67: KVI | Q67: Makhana Raw | R67: =IF(Config!$B$4>0,M67/Config!$B$4,0) | S67: =IF(Config!$B$4>0,K67/Config!$B$4,0) | T67: =R67*Config!$B$7 | U67: =S67*Config!$B$7 | V67: 48 | W67: 240 | X67: =IF(T67>0,V67/T67,0) | Y67: =IF(U67>0,W67/U67,0) | Z67: =T67-V67 | AA67: =U67-W67 | AB67: =IF(Config!$B$7>0,(V67/Config!$B$7)*Config!$B$4,0) | AC67: =IF(Config!$B$7>0,(W67/Config!$B$7)*Config!$B$4,0)
A68: May | B68: 2026 | C68: 25-04-2026 | D68: 0.72662037 | E68: Seeds_11-2541 | F68: FG | G68: Chia Seeds | H68: Premium Chia Seeds Farmley Standee Pouch 200 g | I68: Premium Chia Seeds | J68: 0.2 | K68: 1000 | L68: Wal-Mart India Private Limited | M68: 200 | N68: Modern Trade | O68: Indore | P68: KVI | Q68: Chia Seeds | R68: =IF(Config!$B$4>0,M68/Config!$B$4,0) | S68: =IF(Config!$B$4>0,K68/Config!$B$4,0) | T68: =R68*Config!$B$7 | U68: =S68*Config!$B$7 | V68: 174 | W68: 870 | X68: =IF(T68>0,V68/T68,0) | Y68: =IF(U68>0,W68/U68,0) | Z68: =T68-V68 | AA68: =U68-W68 | AB68: =IF(Config!$B$7>0,(V68/Config!$B$7)*Config!$B$4,0) | AC68: =IF(Config!$B$7>0,(W68/Config!$B$7)*Config!$B$4,0)
A69: May | B69: 2026 | C69: 25-04-2026 | D69: 0.72662037 | E69: Almonds_1-1750 | F69: FG | G69: Almonds | H69: Popular California Almonds Farmley Standee Pouch 500 g | I69: Popular California Almonds | J69: 0.5 | K69: 200 | L69: Wal-Mart India Private Limited | M69: 100 | N69: Modern Trade | O69: Indore | P69: KVI | Q69: Almonds | R69: =IF(Config!$B$4>0,M69/Config!$B$4,0) | S69: =IF(Config!$B$4>0,K69/Config!$B$4,0) | T69: =R69*Config!$B$7 | U69: =S69*Config!$B$7 | V69: 144 | W69: 288 | X69: =IF(T69>0,V69/T69,0) | Y69: =IF(U69>0,W69/U69,0) | Z69: =T69-V69 | AA69: =U69-W69 | AB69: =IF(Config!$B$7>0,(V69/Config!$B$7)*Config!$B$4,0) | AC69: =IF(Config!$B$7>0,(W69/Config!$B$7)*Config!$B$4,0)
... A72: May | B72: 2026 | C72: 25-04-2026 | D72: 0.72662037 | E72: Dates_4-20162 | F72: FG | G72: Healthy Desserts | H72: Coffee Rush Date Bite Farmley Tin Jar 200g | I72: Coffee Date Bites | J72: 0.2 | K72: 360 | L72: Wal-Mart India Private Limited | M72: 72 | N72: Modern Trade | O72: Indore | P72: Value Added | Q72: Healthy Desserts | R72: =IF(Config!$B$4>0,M72/Config!$B$4,0) | S72: =IF(Config!$B$4>0,K72/Config!$B$4,0) | T72: =R72*Config!$B$7 | U72: =S72*Config!$B$7 | V72: 0 | W72: 0 | X72: =IF(T72>0,V72/T72,0) | Y72: =IF(U72>0,W72/U72,0) | Z72: =T72-V72 | AA72: =U72-W72 | AB72: =IF(Config!$B$7>0,(V72/Config!$B$7)*Config!$B$4,0) | AC72: =IF(Config!$B$7>0,(W72/Config!$B$7)*Config!$B$4,0)
A73: May | B73: 2026 | C73: 30-04-2026 | D73: 0.69040509 | E73: Dates_4-20173 | F73: FG | G73: Healthy Desserts | H73: Dark Choco-Orange Date Bite Farmley Monocarton 360g -Pack of 6 (60g each)- with SRP | I73: Date bites choco-Orange | J73: 0.36 | K73: 167 | L73: Wal-Mart India Private Limited | M73: 60.12 | N73: Modern Trade | O73: Indore | P73: Value Added | R73: =IF(Config!$B$4>0,M73/Config!$B$4,0) | S73: =IF(Config!$B$4>0,K73/Config!$B$4,0) | T73: =R73*Config!$B$7 | U73: =S73*Config!$B$7 | V73: 0 | W73: 0 | X73: =IF(T73>0,V73/T73,0) | Y73: =IF(U73>0,W73/U73,0) | Z73: =T73-V73 | AA73: =U73-W73 | AB73: =IF(Config!$B$7>0,(V73/Config!$B$7)*Config!$B$4,0) | AC73: =IF(Config!$B$7>0,(W73/Config!$B$7)*Config!$B$4,0)
A74: May | B74: 2026 | C74: 25-04-2026 | D74: 0.72662037 | E74: Dates_4-30101 | F74: FG | G74: Healthy Desserts | H74: Dark Choco-Orange Date Bite Farmley Tin Jar 200g | I74: Date bites choco-Orange | J74: 0.2 | K74: 360 | L74: Wal-Mart India Private Limited | M74: 72 | N74: Modern Trade | O74: Indore | P74: Value Added | Q74: Healthy Desserts | R74: =IF(Config!$B$4>0,M74/Config!$B$4,0) | S74: =IF(Config!$B$4>0,K74/Config!$B$4,0) | T74: =R74*Config!$B$7 | U74: =S74*Config!$B$7 | V74: 0 | W74: 0 | X74: =IF(T74>0,V74/T74,0) | Y74: =IF(U74>0,W74/U74,0) | Z74: =T74-V74 | AA74: =U74-W74 | AB74: =IF(Config!$B$7>0,(V74/Config!$B$7)*Config!$B$4,0) | AC74: =IF(Config!$B$7>0,(W74/Config!$B$7)*Config!$B$4,0)
A75: May | B75: 2026 | C75: 25-04-2026 | D75: 0.72662037 | E75: Dry Fruit Mix_15-30159 | F75: FG | G75: Savoury Mixes | H75: Mexican Peri Peri Snack Mix Farmley Composite Jar 325 g | I75: Mexican Peri Peri Snack Mix | J75: 0.325 | K75: 350 | L75: Wal-Mart India Private Limited | M75: 113.75 | N75: Modern Trade | O75: Indore | P75: Value Added | Q75: Savoury Mixes | R75: =IF(Config!$B$4>0,M75/Config!$B$4,0) | S75: =IF(Config!$B$4>0,K75/Config!$B$4,0) | T75: =R75*Config!$B$7 | U75: =S75*Config!$B$7 | V75: 0 | W75: 0 | X75: =IF(T75>0,V75/T75,0) | Y75: =IF(U75>0,W75/U75,0) | Z75: =T75-V75 | AA75: =U75-W75 | AB75: =IF(Config!$B$7>0,(V75/Config!$B$7)*Config!$B$4,0) | AC75: =IF(Config!$B$7>0,(W75/Config!$B$7)*Config!$B$4,0)
A76: May | B76: 2026 | C76: 25-04-2026 | D76: 0.72662037 | E76: Seeds_11-2550 | F76: FG | G76: Other Seeds | H76: Premium Flax Seeds Farmley Standee Pouch 200 g | I76: Premium Flax Seeds | J76: 0.2 | K76: 450 | L76: Wal-Mart India Private Limited | M76: 90 | N76: Modern Trade | O76: Indore | P76: KVI | Q76: Other Seeds | R76: =IF(Config!$B$4>0,M76/Config!$B$4,0) | S76: =IF(Config!$B$4>0,K76/Config!$B$4,0) | T76: =R76*Config!$B$7 | U76: =S76*Config!$B$7 | V76: 0 | W76: 0 | X76: =IF(T76>0,V76/T76,0) | Y76: =IF(U76>0,W76/U76,0) | Z76: =T76-V76 | AA76: =U76-W76 | AB76: =IF(Config!$B$7>0,(V76/Config!$B$7)*Config!$B$4,0) | AC76: =IF(Config!$B$7>0,(W76/Config!$B$7)*Config!$B$4,0)
A77: May | B77: 2026 | C77: 25-04-2026 | D77: 0.72662037 | E77: Dry Fruit Mix_15-2923 | F77: FG | G77: Trail Mixes | H77: Trail Mix Farmley Jar 450 g | I77: Trail Mix | J77: 0.45 | K77: 360 | L77: Wal-Mart India Private Limited | M77: 162 | N77: Modern Trade | O77: Indore | P77: Value Added | Q77: Trail Mixes | R77: =IF(Config!$B$4>0,M77/Config!$B$4,0) | S77: =IF(Config!$B$4>0,K77/Config!$B$4,0) | T77: =R77*Config!$B$7 | U77: =S77*Config!$B$7 | V77: 0 | W77: 0 | X77: =IF(T77>0,V77/T77,0) | Y77: =IF(U77>0,W77/U77,0) | Z77: =T77-V77 | AA77: =U77-W77 | AB77: =IF(Config!$B$7>0,(V77/Config!$B$7)*Config!$B$4,0) | AC77: =IF(Config!$B$7>0,(W77/Config!$B$7)*Config!$B$4,0)
E78: Seeds_11-2542 | G78: Seeds | H78: Premium Jumbo Pumpkin Seeds Farmley Standee Pouch 200 g | J78: 0 | K78: 0 | L78: Wal-Mart India Private Limited | M78: 0 | N78: Modern Trade | O78: Indore | Q78: Other Seeds | R78: =IF(Config!$B$4>0,M78/Config!$B$4,0) | S78: =IF(Config!$B$4>0,K78/Config!$B$4,0) | T78: =R78*Config!$B$7 | U78: =S78*Config!$B$7 | V78: 18 | W78: 90 | X78: =IF(T78>0,V78/T78,0) | Y78: =IF(U78>0,W78/U78,0) | Z78: =T78-V78 | AA78: =U78-W78 | AB78: =IF(Config!$B$7>0,(V78/Config!$B$7)*Config!$B$4,0) | AC78: =IF(Config!$B$7>0,(W78/Config!$B$7)*Config!$B$4,0)
E79: Seeds_11-2953 | G79: Seeds | H79: Watermelon Seeds Farmley Standee Pouch 500g | J79: 0 | K79: 0 | L79: Wal-Mart India Private Limited | M79: 0 | N79: Modern Trade | O79: Indore | Q79: Other Seeds | R79: =IF(Config!$B$4>0,M79/Config!$B$4,0) | S79: =IF(Config!$B$4>0,K79/Config!$B$4,0) | T79: =R79*Config!$B$7 | U79: =S79*Config!$B$7 | V79: 24 | W79: 48 | X79: =IF(T79>0,V79/T79,0) | Y79: =IF(U79>0,W79/U79,0) | Z79: =T79-V79 | AA79: =U79-W79 | AB79: =IF(Config!$B$7>0,(V79/Config!$B$7)*Config!$B$4,0) | AC79: =IF(Config!$B$7>0,(W79/Config!$B$7)*Config!$B$4,0)
E80: Makhana_7-30096 | G80: Makhana | H80: Prasadam Makhana Center Seal Pouch 100 g- NEW | J80: 0 | K80: 0 | L80: Wal-Mart India Private Limited | M80: 0 | N80: Modern Trade | O80: Purnea | Q80: Makhana Raw | R80: =IF(Config!$B$4>0,M80/Config!$B$4,0) | S80: =IF(Config!$B$4>0,K80/Config!$B$4,0) | T80: =R80*Config!$B$7 | U80: =S80*Config!$B$7 | V80: 8 | W80: 80 | X80: =IF(T80>0,V80/T80,0) | Y80: =IF(U80>0,W80/U80,0) | Z80: =T80-V80 | AA80: =U80-W80 | AB80: =IF(Config!$B$7>0,(V80/Config!$B$7)*Config!$B$4,0) | AC80: =IF(Config!$B$7>0,(W80/Config!$B$7)*Config!$B$4,0)
A81: May | B81: 2026 | C81: 25-04-2026 | D81: 0.72662037 | E81: Seeds_11-2541 | F81: FG | G81: Chia Seeds | H81: Premium Chia Seeds Farmley Standee Pouch 200 g | I81: Premium Chia Seeds | J81: 0.2 | K81: 1300 | L81: SPENCER'S RETAIL LIMITED | M81: 260 | N81: Modern Trade | O81: Indore | P81: KVI | Q81: Chia Seeds | R81: =IF(Config!$B$4>0,M81/Config!$B$4,0) | S81: =IF(Config!$B$4>0,K81/Config!$B$4,0) | T81: =R81*Config!$B$7 | U81: =S81*Config!$B$7 | V81: 0 | W81: 0 | X81: =IF(T81>0,V81/T81,0) | Y81: =IF(U81>0,W81/U81,0) | Z81: =T81-V81 | AA81: =U81-W81 | AB81: =IF(Config!$B$7>0,(V81/Config!$B$7)*Config!$B$4,0) | AC81: =IF(Config!$B$7>0,(W81/Config!$B$7)*Config!$B$4,0)
A82: May | B82: 2026 | C82: 25-04-2026 | D82: 0.72662037 | E82: Dry Fruit Mix_15-2801 | F82: FG | G82: Trail Mixes | H82: Premium Panchmeva Farmley Jar 405 g | I82: Premium Panchmewa Superfood | J82: 0.405 | K82: 500 | L82: SPENCER'S RETAIL LIMITED | M82: 202.5 | N82: Modern Trade | O82: Indore | P82: Value Added | Q82: Trail Mixes | R82: =IF(Config!$B$4>0,M82/Config!$B$4,0) | S82: =IF(Config!$B$4>0,K82/Config!$B$4,0) | T82: =R82*Config!$B$7 | U82: =S82*Config!$B$7 | V82: 0 | W82: 0 | X82: =IF(T82>0,V82/T82,0) | Y82: =IF(U82>0,W82/U82,0) | Z82: =T82-V82 | AA82: =U82-W82 | AB82: =IF(Config!$B$7>0,(V82/Config!$B$7)*Config!$B$4,0) | AC82: =IF(Config!$B$7>0,(W82/Config!$B$7)*Config!$B$4,0)
A83: May | B83: 2026 | C83: 25-04-2026 | D83: 0.72662037 | E83: Dry Fruit Mix_15-2402 | F83: FG | G83: Trail Mixes | H83: Trail Mix Farmley Standee Pouch 200 g | I83: Trail Mix | J83: 0.2 | K83: 200 | L83: SPENCER'S RETAIL LIMITED | M83: 40 | N83: Modern Trade | O83: Indore | P83: Value Added | Q83: Trail Mixes | R83: =IF(Config!$B$4>0,M83/Config!$B$4,0) | S83: =IF(Config!$B$4>0,K83/Config!$B$4,0) | T83: =R83*Config!$B$7 | U83: =S83*Config!$B$7 | V83: 0 | W83: 0 | X83: =IF(T83>0,V83/T83,0) | Y83: =IF(U83>0,W83/U83,0) | Z83: =T83-V83 | AA83: =U83-W83 | AB83: =IF(Config!$B$7>0,(V83/Config!$B$7)*Config!$B$4,0) | AC83: =IF(Config!$B$7>0,(W83/Config!$B$7)*Config!$B$4,0)
A84: May | B84: 2026 | C84: 25-04-2026 | D84: 0.72662037 | E84: Dry Fruit Mix_15-2923 | F84: FG | G84: Trail Mixes | H84: Trail Mix Farmley Jar 450 g | I84: Trail Mix | J84: 0.45 | K84: 2000 | L84: SPENCER'S RETAIL LIMITED | M84: 900 | N84: Modern Trade | O84: Indore | P84: Value Added | Q84: Trail Mixes | R84: =IF(Config!$B$4>0,M84/Config!$B$4,0) | S84: =IF(Config!$B$4>0,K84/Config!$B$4,0) | T84: =R84*Config!$B$7 | U84: =S84*Config!$B$7 | V84: 0 | W84: 0 | X84: =IF(T84>0,V84/T84,0) | Y84: =IF(U84>0,W84/U84,0) | Z84: =T84-V84 | AA84: =U84-W84 | AB84: =IF(Config!$B$7>0,(V84/Config!$B$7)*Config!$B$4,0) | AC84: =IF(Config!$B$7>0,(W84/Config!$B$7)*Config!$B$4,0)
A85: May | B85: 2026 | C85: 25-04-2026 | D85: 0.72662037 | E85: Walnut_12-1535 | F85: FG | G85: Walnut | H85: Premium Broken Walnut Kernels Farmley Standee Pouch 200 g | I85: Premium Broken Walnut Kernels | J85: 0.2 | K85: 300 | L85: SPENCER'S RETAIL LIMITED | M85: 60 | N85: Modern Trade | O85: Indore | P85: KVI | Q85: Walnut | R85: =IF(Config!$B$4>0,M85/Config!$B$4,0) | S85: =IF(Config!$B$4>0,K85/Config!$B$4,0) | T85: =R85*Config!$B$7 | U85: =S85*Config!$B$7 | V85: 0 | W85: 0 | X85: =IF(T85>0,V85/T85,0) | Y85: =IF(U85>0,W85/U85,0) | Z85: =T85-V85 | AA85: =U85-W85 | AB85: =IF(Config!$B$7>0,(V85/Config!$B$7)*Config!$B$4,0) | AC85: =IF(Config!$B$7>0,(W85/Config!$B$7)*Config!$B$4,0)
A86: May | B86: 2026 | C86: 25-04-2026 | D86: 0.72662037 | E86: Dates_4-2469 | F86: FG | G86: Dates | H86: Premium Omani Fard Dates Farmley standee pouch 400 g | I86: Premium Fard Dates | J86: 0.4 | K86: 800 | L86: SPENCER'S RETAIL LIMITED | M86: 320 | N86: Modern Trade | O86: Indore | P86: KVI | Q86: Dates | R86: =IF(Config!$B$4>0,M86/Config!$B$4,0) | S86: =IF(Config!$B$4>0,K86/Config!$B$4,0) | T86: =R86*Config!$B$7 | U86: =S86*Config!$B$7 | V86: 129.6 | W86: 324 | X86: =IF(T86>0,V86/T86,0) | Y86: =IF(U86>0,W86/U86,0) | Z86: =T86-V86 | AA86: =U86-W86 | AB86: =IF(Config!$B$7>0,(V86/Config!$B$7)*Config!$B$4,0) | AC86: =IF(Config!$B$7>0,(W86/Config!$B$7)*Config!$B$4,0)
A87: May | B87: 2026 | C87: 25-04-2026 | D87: 0.72662037 | E87: Walnut_12-2655 | F87: FG | G87: Walnut | H87: Premium Extra Light Halves Walnut Kernels Farmley Standee Pouch 200 g | I87: Premium Extra Light Halves Walnut Kernels | J87: 0.2 | K87: 300 | L87: SPENCER'S RETAIL LIMITED | M87: 60 | N87: Modern Trade | O87: Indore | P87: KVI | Q87: Walnut | R87: =IF(Config!$B$4>0,M87/Config!$B$4,0) | S87: =IF(Config!$B$4>0,K87/Config!$B$4,0) | T87: =R87*Config!$B$7 | U87: =S87*Config!$B$7 | V87: 9.6 | W87: 48 | X87: =IF(T87>0,V87/T87,0) | Y87: =IF(U87>0,W87/U87,0) | Z87: =T87-V87 | AA87: =U87-W87 | AB87: =IF(Config!$B$7>0,(V87/Config!$B$7)*Config!$B$4,0) | AC87: =IF(Config!$B$7>0,(W87/Config!$B$7)*Config!$B$4,0)
A88: May | B88: 2026 | C88: 25-04-2026 | D88: 0.72663194 | E88: Makhana_7-30096 | F88: FG | G88: Makhana Raw | H88: Prasadam Makhana Center Seal Pouch 100 g- NEW | I88: Prasadam Makhana | J88: 0.1 | K88: 900 | L88: SPENCER'S RETAIL LIMITED | M88: 90 | N88: Modern Trade | O88: Purnea | P88: KVI | Q88: Makhana Raw | R88: =IF(Config!$B$4>0,M88/Config!$B$4,0) | S88: =IF(Config!$B$4>0,K88/Config!$B$4,0) | T88: =R88*Config!$B$7 | U88: =S88*Config!$B$7 | V88: 8 | W88: 80 | X88: =IF(T88>0,V88/T88,0) | Y88: =IF(U88>0,W88/U88,0) | Z88: =T88-V88 | AA88: =U88-W88 | AB88: =IF(Config!$B$7>0,(V88/Config!$B$7)*Config!$B$4,0) | AC88: =IF(Config!$B$7>0,(W88/Config!$B$7)*Config!$B$4,0)
A89: May | B89: 2026 | C89: 25-04-2026 | D89: 0.72663194 | E89: Makhana_7-30098 | F89: FG | G89: Makhana Raw | H89: Prasadam Makhana Center Seal Pouch 200 g- NEW | I89: Prasadam Makhana | J89: 0.2 | K89: 700 | L89: SPENCER'S RETAIL LIMITED | M89: 140 | N89: Modern Trade | O89: Purnea | P89: KVI | Q89: Makhana Raw | R89: =IF(Config!$B$4>0,M89/Config!$B$4,0) | S89: =IF(Config!$B$4>0,K89/Config!$B$4,0) | T89: =R89*Config!$B$7 | U89: =S89*Config!$B$7 | V89: 104 | W89: 520 | X89: =IF(T89>0,V89/T89,0) | Y89: =IF(U89>0,W89/U89,0) | Z89: =T89-V89 | AA89: =U89-W89 | AB89: =IF(Config!$B$7>0,(V89/Config!$B$7)*Config!$B$4,0) | AC89: =IF(Config!$B$7>0,(W89/Config!$B$7)*Config!$B$4,0)
A90: May | B90: 2026 | C90: 25-04-2026 | D90: 0.72663194 | E90: Makhana_7-2983 | F90: FG | G90: Roasted & Flavoured Makhana | H90: Roasted & Flavored Makhana - Peri Peri Farmley Composite Jar 77 g | I90: Prasadam Roasted Makhana | J90: 0.077 | K90: 250 | L90: SPENCER'S RETAIL LIMITED | M90: 19.25 | N90: Modern Trade | O90: Purnea | P90: Value Added | Q90: Roasted & Flavoured Makhana | R90: =IF(Config!$B$4>0,M90/Config!$B$4,0) | S90: =IF(Config!$B$4>0,K90/Config!$B$4,0) | T90: =R90*Config!$B$7 | U90: =S90*Config!$B$7 | V90: 0 | W90: 0 | X90: =IF(T90>0,V90/T90,0) | Y90: =IF(U90>0,W90/U90,0) | Z90: =T90-V90 | AA90: =U90-W90 | AB90: =IF(Config!$B$7>0,(V90/Config!$B$7)*Config!$B$4,0) | AC90: =IF(Config!$B$7>0,(W90/Config!$B$7)*Config!$B$4,0)
A91: May | B91: 2026 | C91: 25-04-2026 | D91: 0.72663194 | E91: Makhana_7-2984 | F91: FG | G91: Roasted & Flavoured Makhana | H91: Roasted & Salted Makhana Farmley Composite Jar 77 g | I91: Prasadam Roasted Makhana | J91: 0.077 | K91: 250 | L91: SPENCER'S RETAIL LIMITED | M91: 19.25 | N91: Modern Trade | O91: Purnea | P91: Value Added | Q91: Roasted & Flavoured Makhana | R91: =IF(Config!$B$4>0,M91/Config!$B$4,0) | S91: =IF(Config!$B$4>0,K91/Config!$B$4,0) | T91: =R91*Config!$B$7 | U91: =S91*Config!$B$7 | V91: 3.7 | W91: 48 | X91: =IF(T91>0,V91/T91,0) | Y91: =IF(U91>0,W91/U91,0) | Z91: =T91-V91 | AA91: =U91-W91 | AB91: =IF(Config!$B$7>0,(V91/Config!$B$7)*Config!$B$4,0) | AC91: =IF(Config!$B$7>0,(W91/Config!$B$7)*Config!$B$4,0)
A92: May | B92: 2026 | C92: 25-04-2026 | D92: 0.72663194 | E92: Dry Fruit Mix_15-2404 | F92: FG | G92: Berry Mix | H92: Berry Mix Farmley Standee Pouch 200 g | I92: Berry Mix | J92: 0.2 | K92: 100 | L92: SPENCER'S RETAIL LIMITED | M92: 20 | N92: Modern Trade | O92: Indore | P92: Value Added | Q92: Berry Mix | R92: =IF(Config!$B$4>0,M92/Config!$B$4,0) | S92: =IF(Config!$B$4>0,K92/Config!$B$4,0) | T92: =R92*Config!$B$7 | U92: =S92*Config!$B$7 | V92: 0 | W92: 0 | X92: =IF(T92>0,V92/T92,0) | Y92: =IF(U92>0,W92/U92,0) | Z92: =T92-V92 | AA92: =U92-W92 | AB92: =IF(Config!$B$7>0,(V92/Config!$B$7)*Config!$B$4,0) | AC92: =IF(Config!$B$7>0,(W92/Config!$B$7)*Config!$B$4,0)
... A103: May | B103: 2026 | C103: 25-04-2026 | D103: 0.72663194 | E103: Seeds_11-20155 | F103: FG | G103: Other Seeds | H103: Premium Watermelon Seeds Farmley Standee Pouch 100 gms | I103: Premium Watermelon Seeds | J103: 0.1 | K103: 1200 | L103: SPENCER'S RETAIL LIMITED | M103: 120 | N103: Modern Trade | O103: Indore | P103: KVI | Q103: Other Seeds | R103: =IF(Config!$B$4>0,M103/Config!$B$4,0) | S103: =IF(Config!$B$4>0,K103/Config!$B$4,0) | T103: =R103*Config!$B$7 | U103: =S103*Config!$B$7 | V103: 0 | W103: 0 | X103: =IF(T103>0,V103/T103,0) | Y103: =IF(U103>0,W103/U103,0) | Z103: =T103-V103 | AA103: =U103-W103 | AB103: =IF(Config!$B$7>0,(V103/Config!$B$7)*Config!$B$4,0) | AC103: =IF(Config!$B$7>0,(W103/Config!$B$7)*Config!$B$4,0)
E104: Apricot_2-2540 | G104: Apricot | H104: Premium Turkish Dried Apricot Farmley Standee Pouch 200 g | J104: 0 | K104: 0 | L104: SPENCER'S RETAIL LIMITED | M104: 0 | N104: Modern Trade | O104: Indore | Q104: Apricots | R104: =IF(Config!$B$4>0,M104/Config!$B$4,0) | S104: =IF(Config!$B$4>0,K104/Config!$B$4,0) | T104: =R104*Config!$B$7 | U104: =S104*Config!$B$7 | V104: 12 | W104: 60 | X104: =IF(T104>0,V104/T104,0) | Y104: =IF(U104>0,W104/U104,0) | Z104: =T104-V104 | AA104: =U104-W104 | AB104: =IF(Config!$B$7>0,(V104/Config!$B$7)*Config!$B$4,0) | AC104: =IF(Config!$B$7>0,(W104/Config!$B$7)*Config!$B$4,0)
E105: Makhana_7-2980 | G105: Makhana | H105: Roasted & Flavored Makhana - Mint Farmley Composite Jar 77 g | J105: 0 | K105: 0 | L105: SPENCER'S RETAIL LIMITED | M105: 0 | N105: Modern Trade | O105: Purnea | Q105: Roasted & Flavoured Makhana | R105: =IF(Config!$B$4>0,M105/Config!$B$4,0) | S105: =IF(Config!$B$4>0,K105/Config!$B$4,0) | T105: =R105*Config!$B$7 | U105: =S105*Config!$B$7 | V105: 3.7 | W105: 48 | X105: =IF(T105>0,V105/T105,0) | Y105: =IF(U105>0,W105/U105,0) | Z105: =T105-V105 | AA105: =U105-W105 | AB105: =IF(Config!$B$7>0,(V105/Config!$B$7)*Config!$B$4,0) | AC105: =IF(Config!$B$7>0,(W105/Config!$B$7)*Config!$B$4,0)
E106: Makhana_7-2985 | G106: Makhana | H106: Roasted & Flavored Makhana - Tangy Tomato Farmley Composite Jar 77 g | J106: 0 | K106: 0 | L106: SPENCER'S RETAIL LIMITED | M106: 0 | N106: Modern Trade | O106: Purnea | Q106: Roasted & Flavoured Makhana | R106: =IF(Config!$B$4>0,M106/Config!$B$4,0) | S106: =IF(Config!$B$4>0,K106/Config!$B$4,0) | T106: =R106*Config!$B$7 | U106: =S106*Config!$B$7 | V106: 3.7 | W106: 48 | X106: =IF(T106>0,V106/T106,0) | Y106: =IF(U106>0,W106/U106,0) | Z106: =T106-V106 | AA106: =U106-W106 | AB106: =IF(Config!$B$7>0,(V106/Config!$B$7)*Config!$B$4,0) | AC106: =IF(Config!$B$7>0,(W106/Config!$B$7)*Config!$B$4,0)
A107: May | B107: 2026 | C107: 25-04-2026 | D107: 0.72663194 | E107: Dry Fruit Mix_15-2404 | F107: FG | G107: Berry Mix | H107: Berry Mix Farmley Standee Pouch 200 g | I107: Berry Mix | J107: 0.2 | K107: 150 | L107: MAX HYPERMARKET INDIA PRIVATE LIMITED | M107: 30 | N107: Modern Trade | O107: Indore | P107: Value Added | Q107: Berry Mix | R107: =IF(Config!$B$4>0,M107/Config!$B$4,0) | S107: =IF(Config!$B$4>0,K107/Config!$B$4,0) | T107: =R107*Config!$B$7 | U107: =S107*Config!$B$7 | V107: 6 | W107: 30 | X107: =IF(T107>0,V107/T107,0) | Y107: =IF(U107>0,W107/U107,0) | Z107: =T107-V107 | AA107: =U107-W107 | AB107: =IF(Config!$B$7>0,(V107/Config!$B$7)*Config!$B$4,0) | AC107: =IF(Config!$B$7>0,(W107/Config!$B$7)*Config!$B$4,0)
A108: May | B108: 2026 | C108: 25-04-2026 | D108: 0.72663194 | E108: Dates_4-30567 | F108: FG | G108: Healthy Desserts | H108: Classic Date Bites Farmley Tin Jar 200 g | I108: Classic Date bites | J108: 0.2 | K108: 100 | L108: MAX HYPERMARKET INDIA PRIVATE LIMITED | M108: 20 | N108: Modern Trade | O108: Indore | P108: Value Added | Q108: Healthy Desserts | R108: =IF(Config!$B$4>0,M108/Config!$B$4,0) | S108: =IF(Config!$B$4>0,K108/Config!$B$4,0) | T108: =R108*Config!$B$7 | U108: =S108*Config!$B$7 | V108: 9.6 | W108: 48 | X108: =IF(T108>0,V108/T108,0) | Y108: =IF(U108>0,W108/U108,0) | Z108: =T108-V108 | AA108: =U108-W108 | AB108: =IF(Config!$B$7>0,(V108/Config!$B$7)*Config!$B$4,0) | AC108: =IF(Config!$B$7>0,(W108/Config!$B$7)*Config!$B$4,0)
A109: May | B109: 2026 | C109: 25-04-2026 | D109: 0.72664352 | E109: Dates_4-30101 | F109: FG | G109: Healthy Desserts | H109: Dark Choco-Orange Date Bite Farmley Tin Jar 200g | I109: Date bites choco-Orange | J109: 0.2 | K109: 100 | L109: MAX HYPERMARKET INDIA PRIVATE LIMITED | M109: 20 | N109: Modern Trade | O109: Indore | P109: Value Added | Q109: Healthy Desserts | R109: =IF(Config!$B$4>0,M109/Config!$B$4,0) | S109: =IF(Config!$B$4>0,K109/Config!$B$4,0) | T109: =R109*Config!$B$7 | U109: =S109*Config!$B$7 | V109: 0 | W109: 0 | X109: =IF(T109>0,V109/T109,0) | Y109: =IF(U109>0,W109/U109,0) | Z109: =T109-V109 | AA109: =U109-W109 | AB109: =IF(Config!$B$7>0,(V109/Config!$B$7)*Config!$B$4,0) | AC109: =IF(Config!$B$7>0,(W109/Config!$B$7)*Config!$B$4,0)
A110: May | B110: 2026 | C110: 25-04-2026 | D110: 0.72664352 | E110: Makhana_7-30098 | F110: FG | G110: Makhana Raw | H110: Prasadam Makhana Center Seal Pouch 200 g- NEW | I110: Prasadam Makhana | J110: 0.2 | K110: 700 | L110: MAX HYPERMARKET INDIA PRIVATE LIMITED | M110: 140 | N110: Modern Trade | O110: Purnea | P110: KVI | Q110: Makhana Raw | R110: =IF(Config!$B$4>0,M110/Config!$B$4,0) | S110: =IF(Config!$B$4>0,K110/Config!$B$4,0) | T110: =R110*Config!$B$7 | U110: =S110*Config!$B$7 | V110: 88 | W110: 440 | X110: =IF(T110>0,V110/T110,0) | Y110: =IF(U110>0,W110/U110,0) | Z110: =T110-V110 | AA110: =U110-W110 | AB110: =IF(Config!$B$7>0,(V110/Config!$B$7)*Config!$B$4,0) | AC110: =IF(Config!$B$7>0,(W110/Config!$B$7)*Config!$B$4,0)
A111: May | B111: 2026 | C111: 25-04-2026 | D111: 0.72664352 | E111: Walnut_12-1535 | F111: FG | G111: Walnut | H111: Premium Broken Walnut Kernels Farmley Standee Pouch 200 g | I111: Premium Broken Walnut Kernels | J111: 0.2 | K111: 300 | L111: MAX HYPERMARKET INDIA PRIVATE LIMITED | M111: 60 | N111: Modern Trade | O111: Indore | P111: KVI | Q111: Walnut | R111: =IF(Config!$B$4>0,M111/Config!$B$4,0) | S111: =IF(Config!$B$4>0,K111/Config!$B$4,0) | T111: =R111*Config!$B$7 | U111: =S111*Config!$B$7 | V111: 28.8 | W111: 144 | X111: =IF(T111>0,V111/T111,0) | Y111: =IF(U111>0,W111/U111,0) | Z111: =T111-V111 | AA111: =U111-W111 | AB111: =IF(Config!$B$7>0,(V111/Config!$B$7)*Config!$B$4,0) | AC111: =IF(Config!$B$7>0,(W111/Config!$B$7)*Config!$B$4,0)
A112: May | B112: 2026 | C112: 25-04-2026 | D112: 0.72664352 | E112: Fig_6-2464 | F112: FG | G112: Figs | H112: Premium Anjeer Farmley Standee Pouch 200 g | I112: Premium Anjeer | J112: 0.2 | K112: 100 | L112: MAX HYPERMARKET INDIA PRIVATE LIMITED | M112: 20 | N112: Modern Trade | O112: Indore | P112: KVI | Q112: Figs | R112: =IF(Config!$B$4>0,M112/Config!$B$4,0) | S112: =IF(Config!$B$4>0,K112/Config!$B$4,0) | T112: =R112*Config!$B$7 | U112: =S112*Config!$B$7 | V112: 18 | W112: 90 | X112: =IF(T112>0,V112/T112,0) | Y112: =IF(U112>0,W112/U112,0) | Z112: =T112-V112 | AA112: =U112-W112 | AB112: =IF(Config!$B$7>0,(V112/Config!$B$7)*Config!$B$4,0) | AC112: =IF(Config!$B$7>0,(W112/Config!$B$7)*Config!$B$4,0)
A113: May | B113: 2026 | C113: 25-04-2026 | D113: 0.72664352 | E113: Seeds_11-2541 | F113: FG | G113: Chia Seeds | H113: Premium Chia Seeds Farmley Standee Pouch 200 g | I113: Premium Chia Seeds | J113: 0.2 | K113: 200 | L113: MAX HYPERMARKET INDIA PRIVATE LIMITED | M113: 40 | N113: Modern Trade | O113: Indore | P113: KVI | Q113: Chia Seeds | R113: =IF(Config!$B$4>0,M113/Config!$B$4,0) | S113: =IF(Config!$B$4>0,K113/Config!$B$4,0) | T113: =R113*Config!$B$7 | U113: =S113*Config!$B$7 | V113: 12 | W113: 60 | X113: =IF(T113>0,V113/T113,0) | Y113: =IF(U113>0,W113/U113,0) | Z113: =T113-V113 | AA113: =U113-W113 | AB113: =IF(Config!$B$7>0,(V113/Config!$B$7)*Config!$B$4,0) | AC113: =IF(Config!$B$7>0,(W113/Config!$B$7)*Config!$B$4,0)
A114: May | B114: 2026 | C114: 25-04-2026 | D114: 0.72664352 | E114: Dates_4-2469 | F114: FG | G114: Dates | H114: Premium Omani Fard Dates Farmley standee pouch 400 g | I114: Premium Fard Dates | J114: 0.4 | K114: 100 | L114: MAX HYPERMARKET INDIA PRIVATE LIMITED | M114: 40 | N114: Modern Trade | O114: Indore | P114: KVI | Q114: Dates | R114: =IF(Config!$B$4>0,M114/Config!$B$4,0) | S114: =IF(Config!$B$4>0,K114/Config!$B$4,0) | T114: =R114*Config!$B$7 | U114: =S114*Config!$B$7 | V114: 50.4 | W114: 126 | X114: =IF(T114>0,V114/T114,0) | Y114: =IF(U114>0,W114/U114,0) | Z114: =T114-V114 | AA114: =U114-W114 | AB114: =IF(Config!$B$7>0,(V114/Config!$B$7)*Config!$B$4,0) | AC114: =IF(Config!$B$7>0,(W114/Config!$B$7)*Config!$B$4,0)
A115: May | B115: 2026 | C115: 25-04-2026 | D115: 0.72664352 | E115: Seeds_11-2542 | F115: FG | G115: Other Seeds | H115: Premium Jumbo Pumpkin Seeds Farmley Standee Pouch 200 g | I115: Premium Pumpkin Seeds | J115: 0.2 | K115: 200 | L115: MAX HYPERMARKET INDIA PRIVATE LIMITED | M115: 40 | N115: Modern Trade | O115: Indore | P115: KVI | Q115: Other Seeds | R115: =IF(Config!$B$4>0,M115/Config!$B$4,0) | S115: =IF(Config!$B$4>0,K115/Config!$B$4,0) | T115: =R115*Config!$B$7 | U115: =S115*Config!$B$7 | V115: 12 | W115: 60 | X115: =IF(T115>0,V115/T115,0) | Y115: =IF(U115>0,W115/U115,0) | Z115: =T115-V115 | AA115: =U115-W115 | AB115: =IF(Config!$B$7>0,(V115/Config!$B$7)*Config!$B$4,0) | AC115: =IF(Config!$B$7>0,(W115/Config!$B$7)*Config!$B$4,0)
A116: May | B116: 2026 | C116: 25-04-2026 | D116: 0.72664352 | E116: Dry Fruit Mix_15-2801 | F116: FG | G116: Trail Mixes | H116: Premium Panchmeva Farmley Jar 405 g | I116: Premium Panchmewa Superfood | J116: 0.405 | K116: 300 | L116: MAX HYPERMARKET INDIA PRIVATE LIMITED | M116: 121.5 | N116: Modern Trade | O116: Indore | P116: Value Added | Q116: Trail Mixes | R116: =IF(Config!$B$4>0,M116/Config!$B$4,0) | S116: =IF(Config!$B$4>0,K116/Config!$B$4,0) | T116: =R116*Config!$B$7 | U116: =S116*Config!$B$7 | V116: 19.44 | W116: 48 | X116: =IF(T116>0,V116/T116,0) | Y116: =IF(U116>0,W116/U116,0) | Z116: =T116-V116 | AA116: =U116-W116 | AB116: =IF(Config!$B$7>0,(V116/Config!$B$7)*Config!$B$4,0) | AC116: =IF(Config!$B$7>0,(W116/Config!$B$7)*Config!$B$4,0)
A117: May | B117: 2026 | C117: 25-04-2026 | D117: 0.72664352 | E117: Makhana_7-2980 | F117: FG | G117: Roasted & Flavoured Makhana | H117: Roasted & Flavored Makhana - Mint Farmley Composite Jar 77 g | I117: Prasadam Roasted Makhana | J117: 0.077 | K117: 300 | L117: MAX HYPERMARKET INDIA PRIVATE LIMITED | M117: 23.1 | N117: Modern Trade | O117: Purnea | P117: Value Added | Q117: Roasted & Flavoured Makhana | R117: =IF(Config!$B$4>0,M117/Config!$B$4,0) | S117: =IF(Config!$B$4>0,K117/Config!$B$4,0) | T117: =R117*Config!$B$7 | U117: =S117*Config!$B$7 | V117: 0 | W117: 0 | X117: =IF(T117>0,V117/T117,0) | Y117: =IF(U117>0,W117/U117,0) | Z117: =T117-V117 | AA117: =U117-W117 | AB117: =IF(Config!$B$7>0,(V117/Config!$B$7)*Config!$B$4,0) | AC117: =IF(Config!$B$7>0,(W117/Config!$B$7)*Config!$B$4,0)
A118: May | B118: 2026 | C118: 25-04-2026 | D118: 0.72664352 | E118: Makhana_7-2983 | F118: FG | G118: Roasted & Flavoured Makhana | H118: Roasted & Flavored Makhana - Peri Peri Farmley Composite Jar 77 g | I118: Prasadam Roasted Makhana | J118: 0.077 | K118: 200 | L118: MAX HYPERMARKET INDIA PRIVATE LIMITED | M118: 15.4 | N118: Modern Trade | O118: Purnea | P118: Value Added | Q118: Roasted & Flavoured Makhana | R118: =IF(Config!$B$4>0,M118/Config!$B$4,0) | S118: =IF(Config!$B$4>0,K118/Config!$B$4,0) | T118: =R118*Config!$B$7 | U118: =S118*Config!$B$7 | V118: 0 | W118: 0 | X118: =IF(T118>0,V118/T118,0) | Y118: =IF(U118>0,W118/U118,0) | Z118: =T118-V118 | AA118: =U118-W118 | AB118: =IF(Config!$B$7>0,(V118/Config!$B$7)*Config!$B$4,0) | AC118: =IF(Config!$B$7>0,(W118/Config!$B$7)*Config!$B$4,0)
... A126: May | B126: 2026 | C126: 25-04-2026 | D126: 0.72664352 | E126: Dates_4-20162 | F126: FG | G126: Healthy Desserts | H126: Coffee Rush Date Bite Farmley Tin Jar 200g | I126: Coffee Date Bites | J126: 0.2 | K126: 100 | L126: MAX HYPERMARKET INDIA PRIVATE LIMITED | M126: 20 | N126: Modern Trade | O126: Indore | P126: Value Added | Q126: Healthy Desserts | R126: =IF(Config!$B$4>0,M126/Config!$B$4,0) | S126: =IF(Config!$B$4>0,K126/Config!$B$4,0) | T126: =R126*Config!$B$7 | U126: =S126*Config!$B$7 | V126: 4.8 | W126: 24 | X126: =IF(T126>0,V126/T126,0) | Y126: =IF(U126>0,W126/U126,0) | Z126: =T126-V126 | AA126: =U126-W126 | AB126: =IF(Config!$B$7>0,(V126/Config!$B$7)*Config!$B$4,0) | AC126: =IF(Config!$B$7>0,(W126/Config!$B$7)*Config!$B$4,0)
A127: May | B127: 2026 | C127: 30-04-2026 | D127: 0.69039352 | E127: Dates_4-20173 | F127: FG | G127: Healthy Desserts | H127: Dark Choco-Orange Date Bite Farmley Monocarton 360g -Pack of 6 (60g each)- with SRP | I127: Date bites choco-Orange | J127: 0.36 | K127: 17 | L127: MAX HYPERMARKET INDIA PRIVATE LIMITED | M127: 6.12 | N127: Modern Trade | O127: Indore | P127: Value Added | R127: =IF(Config!$B$4>0,M127/Config!$B$4,0) | S127: =IF(Config!$B$4>0,K127/Config!$B$4,0) | T127: =R127*Config!$B$7 | U127: =S127*Config!$B$7 | V127: 0 | W127: 0 | X127: =IF(T127>0,V127/T127,0) | Y127: =IF(U127>0,W127/U127,0) | Z127: =T127-V127 | AA127: =U127-W127 | AB127: =IF(Config!$B$7>0,(V127/Config!$B$7)*Config!$B$4,0) | AC127: =IF(Config!$B$7>0,(W127/Config!$B$7)*Config!$B$4,0)
A128: May | B128: 2026 | C128: 25-04-2026 | D128: 0.72665509 | E128: Seeds_11-2549 | F128: FG | G128: Other Seeds | H128: Premium Sunflower Seeds Farmley Standee Pouch 200 g | I128: Premium Sunflower Seeds | J128: 0.2 | K128: 100 | L128: MAX HYPERMARKET INDIA PRIVATE LIMITED | M128: 20 | N128: Modern Trade | O128: Indore | P128: KVI | Q128: Other Seeds | R128: =IF(Config!$B$4>0,M128/Config!$B$4,0) | S128: =IF(Config!$B$4>0,K128/Config!$B$4,0) | T128: =R128*Config!$B$7 | U128: =S128*Config!$B$7 | V128: 18 | W128: 90 | X128: =IF(T128>0,V128/T128,0) | Y128: =IF(U128>0,W128/U128,0) | Z128: =T128-V128 | AA128: =U128-W128 | AB128: =IF(Config!$B$7>0,(V128/Config!$B$7)*Config!$B$4,0) | AC128: =IF(Config!$B$7>0,(W128/Config!$B$7)*Config!$B$4,0)
A129: May | B129: 2026 | C129: 30-04-2026 | D129: 0.69039352 | E129: Dates_4-20174 | F129: FG | G129: Healthy Desserts | H129: Classic Date Bite Farmley Monocarton 360g- Pack of 6 (60g each)- With SRP | I129: Classic Date bites | J129: 0.36 | K129: 50 | L129: MAX HYPERMARKET INDIA PRIVATE LIMITED | M129: 18 | N129: Modern Trade | O129: Indore | P129: Value Added | Q129: Healthy Desserts | R129: =IF(Config!$B$4>0,M129/Config!$B$4,0) | S129: =IF(Config!$B$4>0,K129/Config!$B$4,0) | T129: =R129*Config!$B$7 | U129: =S129*Config!$B$7 | V129: 0 | W129: 0 | X129: =IF(T129>0,V129/T129,0) | Y129: =IF(U129>0,W129/U129,0) | Z129: =T129-V129 | AA129: =U129-W129 | AB129: =IF(Config!$B$7>0,(V129/Config!$B$7)*Config!$B$4,0) | AC129: =IF(Config!$B$7>0,(W129/Config!$B$7)*Config!$B$4,0)
A130: May | B130: 2026 | C130: 25-04-2026 | D130: 0.72665509 | E130: Makhana_7-30165 | F130: FG | G130: Roasted & Flavoured Makhana | H130: Roasted & Flavored Makhana - Cream N Onion Farmley Composite Jar 83 g | I130: Prasadam Roasted Makhana | J130: 0.083 | K130: 312 | L130: Avenue Supermarts Ltd | M130: 25.9 | N130: Modern Trade | O130: Purnea | P130: Value Added | Q130: Roasted & Flavoured Makhana | R130: =IF(Config!$B$4>0,M130/Config!$B$4,0) | S130: =IF(Config!$B$4>0,K130/Config!$B$4,0) | T130: =R130*Config!$B$7 | U130: =S130*Config!$B$7 | V130: 3.98 | W130: 48 | X130: =IF(T130>0,V130/T130,0) | Y130: =IF(U130>0,W130/U130,0) | Z130: =T130-V130 | AA130: =U130-W130 | AB130: =IF(Config!$B$7>0,(V130/Config!$B$7)*Config!$B$4,0) | AC130: =IF(Config!$B$7>0,(W130/Config!$B$7)*Config!$B$4,0)
A131: May | B131: 2026 | C131: 25-04-2026 | D131: 0.72665509 | E131: Makhana_7-30166 | F131: FG | G131: Roasted & Flavoured Makhana | H131: Roasted & Flavored Makhana - Mint Farmley Composite Jar 83 g | I131: Prasadam Roasted Makhana | J131: 0.083 | K131: 312 | L131: Avenue Supermarts Ltd | M131: 25.9 | N131: Modern Trade | O131: Purnea | P131: Value Added | Q131: Roasted & Flavoured Makhana | R131: =IF(Config!$B$4>0,M131/Config!$B$4,0) | S131: =IF(Config!$B$4>0,K131/Config!$B$4,0) | T131: =R131*Config!$B$7 | U131: =S131*Config!$B$7 | V131: 3.98 | W131: 48 | X131: =IF(T131>0,V131/T131,0) | Y131: =IF(U131>0,W131/U131,0) | Z131: =T131-V131 | AA131: =U131-W131 | AB131: =IF(Config!$B$7>0,(V131/Config!$B$7)*Config!$B$4,0) | AC131: =IF(Config!$B$7>0,(W131/Config!$B$7)*Config!$B$4,0)
A132: May | B132: 2026 | C132: 25-04-2026 | D132: 0.72665509 | E132: Makhana_7-30167 | F132: FG | G132: Roasted & Flavoured Makhana | H132: Roasted & Salted Makhana Farmley Composite Jar 83 g | I132: Prasadam Roasted Makhana | J132: 0.083 | K132: 312 | L132: Avenue Supermarts Ltd | M132: 25.9 | N132: Modern Trade | O132: Purnea | P132: Value Added | Q132: Roasted & Flavoured Makhana | R132: =IF(Config!$B$4>0,M132/Config!$B$4,0) | S132: =IF(Config!$B$4>0,K132/Config!$B$4,0) | T132: =R132*Config!$B$7 | U132: =S132*Config!$B$7 | V132: 15.94 | W132: 192 | X132: =IF(T132>0,V132/T132,0) | Y132: =IF(U132>0,W132/U132,0) | Z132: =T132-V132 | AA132: =U132-W132 | AB132: =IF(Config!$B$7>0,(V132/Config!$B$7)*Config!$B$4,0) | AC132: =IF(Config!$B$7>0,(W132/Config!$B$7)*Config!$B$4,0)
A133: May | B133: 2026 | C133: 25-04-2026 | D133: 0.72665509 | E133: Makhana_7-30164 | F133: FG | G133: Roasted & Flavoured Makhana | H133: Roasted & Flavored Makhana - Peri Peri Farmley Composite Jar 83 g | I133: Prasadam Roasted Makhana | J133: 0.083 | K133: 312 | L133: Avenue Supermarts Ltd | M133: 25.9 | N133: Modern Trade | O133: Purnea | P133: Value Added | Q133: Roasted & Flavoured Makhana | R133: =IF(Config!$B$4>0,M133/Config!$B$4,0) | S133: =IF(Config!$B$4>0,K133/Config!$B$4,0) | T133: =R133*Config!$B$7 | U133: =S133*Config!$B$7 | V133: 11.95 | W133: 144 | X133: =IF(T133>0,V133/T133,0) | Y133: =IF(U133>0,W133/U133,0) | Z133: =T133-V133 | AA133: =U133-W133 | AB133: =IF(Config!$B$7>0,(V133/Config!$B$7)*Config!$B$4,0) | AC133: =IF(Config!$B$7>0,(W133/Config!$B$7)*Config!$B$4,0)
A134: May | B134: 2026 | C134: 25-04-2026 | D134: 0.72665509 | E134: Makhana_7-2995 | F134: FG | G134: Roasted & Flavoured Makhana | H134: Roasted & Flavoured Cream & Onion Makhana Farmley Jar 55 g | I134: Prasadam Roasted Makhana | J134: 0.055 | K134: 350 | L134: Market Ninety Nine Private Limited | M134: 19.25 | N134: Modern Trade | O134: Purnea | P134: Value Added | Q134: Roasted & Flavoured Makhana | R134: =IF(Config!$B$4>0,M134/Config!$B$4,0) | S134: =IF(Config!$B$4>0,K134/Config!$B$4,0) | T134: =R134*Config!$B$7 | U134: =S134*Config!$B$7 | V134: 15.4 | W134: 280 | X134: =IF(T134>0,V134/T134,0) | Y134: =IF(U134>0,W134/U134,0) | Z134: =T134-V134 | AA134: =U134-W134 | AB134: =IF(Config!$B$7>0,(V134/Config!$B$7)*Config!$B$4,0) | AC134: =IF(Config!$B$7>0,(W134/Config!$B$7)*Config!$B$4,0)
A135: May | B135: 2026 | C135: 25-04-2026 | D135: 0.72665509 | E135: Dates_15-30144 | F135: FG | G135: Healthy Desserts | H135: Assorted Pack Farmley 60g Dark Choco Orange Date Bite 20g, Classic Date Bite 20g, Apple Pie Date Bite 20g | I135: Assorted Date Bites | J135: 0.06 | K135: 600 | L135: Market Ninety Nine Private Limited | M135: 36 | N135: Modern Trade | O135: Indore | P135: Value Added | Q135: Healthy Desserts | R135: =IF(Config!$B$4>0,M135/Config!$B$4,0) | S135: =IF(Config!$B$4>0,K135/Config!$B$4,0) | T135: =R135*Config!$B$7 | U135: =S135*Config!$B$7 | V135: 0 | W135: 0 | X135: =IF(T135>0,V135/T135,0) | Y135: =IF(U135>0,W135/U135,0) | Z135: =T135-V135 | AA135: =U135-W135 | AB135: =IF(Config!$B$7>0,(V135/Config!$B$7)*Config!$B$4,0) | AC135: =IF(Config!$B$7>0,(W135/Config!$B$7)*Config!$B$4,0)
A136: May | B136: 2026 | C136: 25-04-2026 | D136: 0.72665509 | E136: Dry Fruit Mix_15-2941 | F136: FG | G136: Seed Mix | H136: Seed mix Farmley 160g Standee Pouches | I136: Seed Mix | J136: 0.16 | K136: 250 | L136: Market Ninety Nine Private Limited | M136: 40 | N136: Modern Trade | O136: Indore | P136: Value Added | Q136: Seed Mix | R136: =IF(Config!$B$4>0,M136/Config!$B$4,0) | S136: =IF(Config!$B$4>0,K136/Config!$B$4,0) | T136: =R136*Config!$B$7 | U136: =S136*Config!$B$7 | V136: 28.8 | W136: 180 | X136: =IF(T136>0,V136/T136,0) | Y136: =IF(U136>0,W136/U136,0) | Z136: =T136-V136 | AA136: =U136-W136 | AB136: =IF(Config!$B$7>0,(V136/Config!$B$7)*Config!$B$4,0) | AC136: =IF(Config!$B$7>0,(W136/Config!$B$7)*Config!$B$4,0)
A137: May | B137: 2026 | C137: 25-04-2026 | D137: 0.72665509 | E137: Seeds_11-2542 | F137: FG | G137: Other Seeds | H137: Premium Jumbo Pumpkin Seeds Farmley Standee Pouch 200 g | I137: Premium Pumpkin Seeds | J137: 0.2 | K137: 140 | L137: Market Ninety Nine Private Limited | M137: 28 | N137: Modern Trade | O137: Indore | P137: KVI | Q137: Other Seeds | R137: =IF(Config!$B$4>0,M137/Config!$B$4,0) | S137: =IF(Config!$B$4>0,K137/Config!$B$4,0) | T137: =R137*Config!$B$7 | U137: =S137*Config!$B$7 | V137: 24 | W137: 120 | X137: =IF(T137>0,V137/T137,0) | Y137: =IF(U137>0,W137/U137,0) | Z137: =T137-V137 | AA137: =U137-W137 | AB137: =IF(Config!$B$7>0,(V137/Config!$B$7)*Config!$B$4,0) | AC137: =IF(Config!$B$7>0,(W137/Config!$B$7)*Config!$B$4,0)
A138: May | B138: 2026 | C138: 25-04-2026 | D138: 0.72665509 | E138: Dry Fruit Mix_15-2402 | F138: FG | G138: Trail Mixes | H138: Trail Mix Farmley Standee Pouch 200 g | I138: Trail Mix | J138: 0.2 | K138: 250 | L138: Market Ninety Nine Private Limited | M138: 50 | N138: Modern Trade | O138: Indore | P138: Value Added | Q138: Trail Mixes | R138: =IF(Config!$B$4>0,M138/Config!$B$4,0) | S138: =IF(Config!$B$4>0,K138/Config!$B$4,0) | T138: =R138*Config!$B$7 | U138: =S138*Config!$B$7 | V138: 42 | W138: 210 | X138: =IF(T138>0,V138/T138,0) | Y138: =IF(U138>0,W138/U138,0) | Z138: =T138-V138 | AA138: =U138-W138 | AB138: =IF(Config!$B$7>0,(V138/Config!$B$7)*Config!$B$4,0) | AC138: =IF(Config!$B$7>0,(W138/Config!$B$7)*Config!$B$4,0)
A139: May | B139: 2026 | C139: 25-04-2026 | D139: 0.72665509 | E139: Makhana_7-2994 | F139: FG | G139: Roasted & Flavoured Makhana | H139: Roasted & Salted Makhana Farmley Jar 55 g | I139: Prasadam Roasted Makhana | J139: 0.055 | K139: 245 | L139: Market Ninety Nine Private Limited | M139: 13.47 | N139: Modern Trade | O139: Purnea | P139: Value Added | Q139: Roasted & Flavoured Makhana | R139: =IF(Config!$B$4>0,M139/Config!$B$4,0) | S139: =IF(Config!$B$4>0,K139/Config!$B$4,0) | T139: =R139*Config!$B$7 | U139: =S139*Config!$B$7 | V139: 23.1 | W139: 420 | X139: =IF(T139>0,V139/T139,0) | Y139: =IF(U139>0,W139/U139,0) | Z139: =T139-V139 | AA139: =U139-W139 | AB139: =IF(Config!$B$7>0,(V139/Config!$B$7)*Config!$B$4,0) | AC139: =IF(Config!$B$7>0,(W139/Config!$B$7)*Config!$B$4,0)
... A187: May | B187: 2026 | C187: 25-04-2026 | D187: 0.72668981 | E187: Dates_4-30101 | F187: FG | G187: Healthy Desserts | H187: Dark Choco-Orange Date Bite Farmley Tin Jar 200g | I187: Date bites choco-Orange | J187: 0.2 | K187: 240 | L187: Reliance Retail Limited_Smart Bazar | M187: 48 | N187: Modern Trade | O187: Indore | P187: Value Added | Q187: Healthy Desserts | R187: =IF(Config!$B$4>0,M187/Config!$B$4,0) | S187: =IF(Config!$B$4>0,K187/Config!$B$4,0) | T187: =R187*Config!$B$7 | U187: =S187*Config!$B$7 | V187: 0 | W187: 0 | X187: =IF(T187>0,V187/T187,0) | Y187: =IF(U187>0,W187/U187,0) | Z187: =T187-V187 | AA187: =U187-W187 | AB187: =IF(Config!$B$7>0,(V187/Config!$B$7)*Config!$B$4,0) | AC187: =IF(Config!$B$7>0,(W187/Config!$B$7)*Config!$B$4,0)
A188: May | B188: 2026 | C188: 30-04-2026 | D188: 0.69039352 | E188: Dates_4-20173 | F188: FG | G188: Healthy Desserts | H188: Dark Choco-Orange Date Bite Farmley Monocarton 360g -Pack of 6 (60g each)- with SRP | I188: Date bites choco-Orange | J188: 0.36 | K188: 72 | L188: Reliance Retail Limited_Smart Bazar | M188: 25.92 | N188: Modern Trade | O188: Indore | P188: Value Added | R188: =IF(Config!$B$4>0,M188/Config!$B$4,0) | S188: =IF(Config!$B$4>0,K188/Config!$B$4,0) | T188: =R188*Config!$B$7 | U188: =S188*Config!$B$7 | V188: 0 | W188: 0 | X188: =IF(T188>0,V188/T188,0) | Y188: =IF(U188>0,W188/U188,0) | Z188: =T188-V188 | AA188: =U188-W188 | AB188: =IF(Config!$B$7>0,(V188/Config!$B$7)*Config!$B$4,0) | AC188: =IF(Config!$B$7>0,(W188/Config!$B$7)*Config!$B$4,0)
A189: May | B189: 2026 | C189: 30-04-2026 | D189: 0.69039352 | E189: Dates_4-20174 | F189: FG | G189: Healthy Desserts | H189: Classic Date Bite Farmley Monocarton 360g- Pack of 6 (60g each)- With SRP | I189: Classic Date bites | J189: 0.36 | K189: 224 | L189: Reliance Retail Limited_Smart Bazar | M189: 80.64 | N189: Modern Trade | O189: Indore | P189: Value Added | Q189: Healthy Desserts | R189: =IF(Config!$B$4>0,M189/Config!$B$4,0) | S189: =IF(Config!$B$4>0,K189/Config!$B$4,0) | T189: =R189*Config!$B$7 | U189: =S189*Config!$B$7 | V189: 77.76 | W189: 1056 | X189: =IF(T189>0,V189/T189,0) | Y189: =IF(U189>0,W189/U189,0) | Z189: =T189-V189 | AA189: =U189-W189 | AB189: =IF(Config!$B$7>0,(V189/Config!$B$7)*Config!$B$4,0) | AC189: =IF(Config!$B$7>0,(W189/Config!$B$7)*Config!$B$4,0)
A190: May | B190: 2026 | C190: 25-04-2026 | D190: 0.72668981 | E190: Dates_15-30144 | F190: FG | G190: Healthy Desserts | H190: Assorted Pack Farmley 60g Dark Choco Orange Date Bite 20g, Classic Date Bite 20g, Apple Pie Date Bite 20g | I190: Assorted Date Bites | J190: 0.06 | K190: 432 | L190: Reliance Retail Limited_Smart Bazar | M190: 25.92 | N190: Modern Trade | O190: Indore | P190: Value Added | Q190: Healthy Desserts | R190: =IF(Config!$B$4>0,M190/Config!$B$4,0) | S190: =IF(Config!$B$4>0,K190/Config!$B$4,0) | T190: =R190*Config!$B$7 | U190: =S190*Config!$B$7 | V190: 22.5 | W190: 375 | X190: =IF(T190>0,V190/T190,0) | Y190: =IF(U190>0,W190/U190,0) | Z190: =T190-V190 | AA190: =U190-W190 | AB190: =IF(Config!$B$7>0,(V190/Config!$B$7)*Config!$B$4,0) | AC190: =IF(Config!$B$7>0,(W190/Config!$B$7)*Config!$B$4,0)
A191: May | B191: 2026 | C191: 30-04-2026 | D191: 0.73998843 | E191: Dates_4-30106 | F191: FG | G191: Healthy Desserts | H191: Dark Choco-Orange Date Bites Monocarton 240 g - Pack of 12 (20 g Each) | I191: Date bites choco-Orange | J191: 0.24 | K191: 210 | L191: Reliance Retail Limited_Smart Bazar | M191: 50.4 | N191: Modern Trade | O191: Indore | P191: Value Added | Q191: Healthy Desserts | R191: =IF(Config!$B$4>0,M191/Config!$B$4,0) | S191: =IF(Config!$B$4>0,K191/Config!$B$4,0) | T191: =R191*Config!$B$7 | U191: =S191*Config!$B$7 | V191: 0 | W191: 0 | X191: =IF(T191>0,V191/T191,0) | Y191: =IF(U191>0,W191/U191,0) | Z191: =T191-V191 | AA191: =U191-W191 | AB191: =IF(Config!$B$7>0,(V191/Config!$B$7)*Config!$B$4,0) | AC191: =IF(Config!$B$7>0,(W191/Config!$B$7)*Config!$B$4,0)
A192: May | B192: 2026 | C192: 25-04-2026 | D192: 0.72668981 | E192: Dates_04-30057 | F192: FG | G192: Healthy Desserts | H192: Apple Pie Date Bite Farmley Tin Jar 200g | I192: Apple Pie Date Bites | J192: 0.2 | K192: 24 | L192: Shoppers Stop Limited | M192: 4.8 | N192: Modern Trade | O192: Indore | P192: Value Added | Q192: Healthy Desserts | R192: =IF(Config!$B$4>0,M192/Config!$B$4,0) | S192: =IF(Config!$B$4>0,K192/Config!$B$4,0) | T192: =R192*Config!$B$7 | U192: =S192*Config!$B$7 | V192: 0 | W192: 0 | X192: =IF(T192>0,V192/T192,0) | Y192: =IF(U192>0,W192/U192,0) | Z192: =T192-V192 | AA192: =U192-W192 | AB192: =IF(Config!$B$7>0,(V192/Config!$B$7)*Config!$B$4,0) | AC192: =IF(Config!$B$7>0,(W192/Config!$B$7)*Config!$B$4,0)
A193: May | B193: 2026 | C193: 25-04-2026 | D193: 0.72668981 | E193: Dates_4-30101 | F193: FG | G193: Healthy Desserts | H193: Dark Choco-Orange Date Bite Farmley Tin Jar 200g | I193: Date bites choco-Orange | J193: 0.2 | K193: 30 | L193: Shoppers Stop Limited | M193: 6 | N193: Modern Trade | O193: Indore | P193: Value Added | Q193: Healthy Desserts | R193: =IF(Config!$B$4>0,M193/Config!$B$4,0) | S193: =IF(Config!$B$4>0,K193/Config!$B$4,0) | T193: =R193*Config!$B$7 | U193: =S193*Config!$B$7 | V193: 0 | W193: 0 | X193: =IF(T193>0,V193/T193,0) | Y193: =IF(U193>0,W193/U193,0) | Z193: =T193-V193 | AA193: =U193-W193 | AB193: =IF(Config!$B$7>0,(V193/Config!$B$7)*Config!$B$4,0) | AC193: =IF(Config!$B$7>0,(W193/Config!$B$7)*Config!$B$4,0)
A194: May | B194: 2026 | C194: 30-04-2026 | D194: 0.69039352 | E194: Dates_4-20173 | F194: FG | G194: Healthy Desserts | H194: Dark Choco-Orange Date Bite Farmley Monocarton 360g -Pack of 6 (60g each)- with SRP | I194: Date bites choco-Orange | J194: 0.36 | K194: 72 | L194: Shoppers Stop Limited | M194: 25.92 | N194: Modern Trade | O194: Indore | P194: Value Added | R194: =IF(Config!$B$4>0,M194/Config!$B$4,0) | S194: =IF(Config!$B$4>0,K194/Config!$B$4,0) | T194: =R194*Config!$B$7 | U194: =S194*Config!$B$7 | V194: 0 | W194: 0 | X194: =IF(T194>0,V194/T194,0) | Y194: =IF(U194>0,W194/U194,0) | Z194: =T194-V194 | AA194: =U194-W194 | AB194: =IF(Config!$B$7>0,(V194/Config!$B$7)*Config!$B$4,0) | AC194: =IF(Config!$B$7>0,(W194/Config!$B$7)*Config!$B$4,0)
...

Sheet RunRate by Origin
A1: Month | B1: Year | C1: Last Modified Date | D1: Last Modified Time | E1: Item Code | F1: BOM Item Type | G1: Item Group | H1: Item Name | I1: Item Parent | J1: Conversion Factor | K1: Projection Units | L1: Customer | M1: Total KGs | N1: Customer Group | O1: Origin | P1: Item Type | Q1: New MIS Item Group | R1: Daily Demand(Total KGs) | S1: Daily Demand(Projection Units) | T1: Projected KGs as of period | U1: Projected Units as of period | V1: Actual SO KGs | W1: Actual SO Units | X1: Achievement % KGs | Y1: Achievement % Units | Z1: Diff Proj-SO KGs | AA1: Diff Proj-SO Units | AB1: Run Rate Month-End KGs | AC1: Run Rate Month-End Units
A2: May | B2: 2026 | C2: 29-04-2026 | D2: 0.47064815 | E2: Multiple | F2: FG | G2: Roasted & Flavoured Makhana | H2: Purnea | I2: Prasadam Roasted Makhana | J2: 0.083 | K2: 1736945 | L2: 75 Customers | M2: 93669.05 | N2: Multiple | O2: Purnea | P2: Value Added | Q2: Roasted & Flavoured Makhana | R2: =IF(Config!$B$4>0,M2/Config!$B$4,0) | S2: =IF(Config!$B$4>0,K2/Config!$B$4,0) | T2: =R2*Config!$B$7 | U2: =S2*Config!$B$7 | V2: 45055.85 | W2: 902419 | X2: =IF(T2>0,V2/T2,0) | Y2: =IF(U2>0,W2/U2,0) | Z2: =T2-V2 | AA2: =U2-W2 | AB2: =IF(Config!$B$7>0,(V2/Config!$B$7)*Config!$B$4,0) | AC2: =IF(Config!$B$7>0,(W2/Config!$B$7)*Config!$B$4,0)
A3: May | B3: 2026 | C3: 29-04-2026 | D3: 0.47064815 | E3: Makhana_7-30163 | F3: FG | G3: Roasted & Flavoured Makhana | H3: Roasted & Flavored Makhana - Tangy Tomato Farmley Composite Jar 83 g | I3: Prasadam Roasted Makhana | J3: 0.083 | K3: 2904 | L3: Canteen Store Department (CSD) | M3: 241.03 | N3: CSD | O3: Purnea | P3: Value Added | Q3: Roasted & Flavoured Makhana | R3: =IF(Config!$B$4>0,M3/Config!$B$4,0) | S3: =IF(Config!$B$4>0,K3/Config!$B$4,0) | T3: =R3*Config!$B$7 | U3: =S3*Config!$B$7 | V3: 0 | W3: 0 | X3: =IF(T3>0,V3/T3,0) | Y3: =IF(U3>0,W3/U3,0) | Z3: =T3-V3 | AA3: =U3-W3 | AB3: =IF(Config!$B$7>0,(V3/Config!$B$7)*Config!$B$4,0) | AC3: =IF(Config!$B$7>0,(W3/Config!$B$7)*Config!$B$4,0)
A4: May | B4: 2026 | C4: 29-04-2026 | D4: 0.47065972 | E4: Makhana_7-30166 | F4: FG | G4: Roasted & Flavoured Makhana | H4: Roasted & Flavored Makhana - Mint Farmley Composite Jar 83 g | I4: Prasadam Roasted Makhana | J4: 0.083 | K4: 2736 | L4: Canteen Store Department (CSD) | M4: 227.09 | N4: CSD | O4: Purnea | P4: Value Added | Q4: Roasted & Flavoured Makhana | R4: =IF(Config!$B$4>0,M4/Config!$B$4,0) | S4: =IF(Config!$B$4>0,K4/Config!$B$4,0) | T4: =R4*Config!$B$7 | U4: =S4*Config!$B$7 | V4: 0 | W4: 0 | X4: =IF(T4>0,V4/T4,0) | Y4: =IF(U4>0,W4/U4,0) | Z4: =T4-V4 | AA4: =U4-W4 | AB4: =IF(Config!$B$7>0,(V4/Config!$B$7)*Config!$B$4,0) | AC4: =IF(Config!$B$7>0,(W4/Config!$B$7)*Config!$B$4,0)
A5: May | B5: 2026 | C5: 29-04-2026 | D5: 0.47065972 | E5: Makhana_7-30167 | F5: FG | G5: Roasted & Flavoured Makhana | H5: Roasted & Salted Makhana Farmley Composite Jar 83 g | I5: Prasadam Roasted Makhana | J5: 0.083 | K5: 2448 | L5: Canteen Store Department (CSD) | M5: 203.18 | N5: CSD | O5: Purnea | P5: Value Added | Q5: Roasted & Flavoured Makhana | R5: =IF(Config!$B$4>0,M5/Config!$B$4,0) | S5: =IF(Config!$B$4>0,K5/Config!$B$4,0) | T5: =R5*Config!$B$7 | U5: =S5*Config!$B$7 | V5: 0 | W5: 0 | X5: =IF(T5>0,V5/T5,0) | Y5: =IF(U5>0,W5/U5,0) | Z5: =T5-V5 | AA5: =U5-W5 | AB5: =IF(Config!$B$7>0,(V5/Config!$B$7)*Config!$B$4,0) | AC5: =IF(Config!$B$7>0,(W5/Config!$B$7)*Config!$B$4,0)
A6: May | B6: 2026 | C6: 29-04-2026 | D6: 0.4706713 | E6: Makhana_7-30098 | F6: FG | G6: Makhana Raw | H6: Prasadam Makhana Center Seal Pouch 200 g- NEW | I6: Prasadam Makhana | J6: 0.2 | K6: 7000 | L6: CPC KPKB | M6: 1400 | N6: CPC | O6: Purnea | P6: KVI | Q6: Makhana Raw | R6: =IF(Config!$B$4>0,M6/Config!$B$4,0) | S6: =IF(Config!$B$4>0,K6/Config!$B$4,0) | T6: =R6*Config!$B$7 | U6: =S6*Config!$B$7 | V6: 0 | W6: 0 | X6: =IF(T6>0,V6/T6,0) | Y6: =IF(U6>0,W6/U6,0) | Z6: =T6-V6 | AA6: =U6-W6 | AB6: =IF(Config!$B$7>0,(V6/Config!$B$7)*Config!$B$4,0) | AC6: =IF(Config!$B$7>0,(W6/Config!$B$7)*Config!$B$4,0)
A7: May | B7: 2026 | C7: 29-04-2026 | D7: 0.4706713 | E7: Makhana_7-30096 | F7: FG | G7: Makhana Raw | H7: Prasadam Makhana Center Seal Pouch 100 g- NEW | I7: Prasadam Makhana | J7: 0.1 | K7: 9600 | L7: CPC KPKB | M7: 960 | N7: CPC | O7: Purnea | P7: KVI | Q7: Makhana Raw | R7: =IF(Config!$B$4>0,M7/Config!$B$4,0) | S7: =IF(Config!$B$4>0,K7/Config!$B$4,0) | T7: =R7*Config!$B$7 | U7: =S7*Config!$B$7 | V7: 0 | W7: 0 | X7: =IF(T7>0,V7/T7,0) | Y7: =IF(U7>0,W7/U7,0) | Z7: =T7-V7 | AA7: =U7-W7 | AB7: =IF(Config!$B$7>0,(V7/Config!$B$7)*Config!$B$4,0) | AC7: =IF(Config!$B$7>0,(W7/Config!$B$7)*Config!$B$4,0)
A8: May | B8: 2026 | C8: 29-04-2026 | D8: 0.4706713 | E8: Makhana_7-2995 | F8: FG | G8: Roasted & Flavoured Makhana | H8: Roasted & Flavoured Cream & Onion Makhana Farmley Jar 55 g | I8: Prasadam Roasted Makhana | J8: 0.055 | K8: 1050 | L8: CPC KPKB | M8: 57.75 | N8: CPC | O8: Purnea | P8: Value Added | Q8: Roasted & Flavoured Makhana | R8: =IF(Config!$B$4>0,M8/Config!$B$4,0) | S8: =IF(Config!$B$4>0,K8/Config!$B$4,0) | T8: =R8*Config!$B$7 | U8: =S8*Config!$B$7 | V8: 0 | W8: 0 | X8: =IF(T8>0,V8/T8,0) | Y8: =IF(U8>0,W8/U8,0) | Z8: =T8-V8 | AA8: =U8-W8 | AB8: =IF(Config!$B$7>0,(V8/Config!$B$7)*Config!$B$4,0) | AC8: =IF(Config!$B$7>0,(W8/Config!$B$7)*Config!$B$4,0)
A9: May | B9: 2026 | C9: 29-04-2026 | D9: 0.4706713 | E9: Makhana_7-2992 | F9: FG | G9: Roasted & Flavoured Makhana | H9: Roasted & Flavoured Peri Peri Makhana Farmley Jar 55 g | I9: Prasadam Roasted Makhana | J9: 0.055 | K9: 1050 | L9: CPC KPKB | M9: 57.75 | N9: CPC | O9: Purnea | P9: Value Added | Q9: Roasted & Flavoured Makhana | R9: =IF(Config!$B$4>0,M9/Config!$B$4,0) | S9: =IF(Config!$B$4>0,K9/Config!$B$4,0) | T9: =R9*Config!$B$7 | U9: =S9*Config!$B$7 | V9: 0 | W9: 0 | X9: =IF(T9>0,V9/T9,0) | Y9: =IF(U9>0,W9/U9,0) | Z9: =T9-V9 | AA9: =U9-W9 | AB9: =IF(Config!$B$7>0,(V9/Config!$B$7)*Config!$B$4,0) | AC9: =IF(Config!$B$7>0,(W9/Config!$B$7)*Config!$B$4,0)
A10: May | B10: 2026 | C10: 29-04-2026 | D10: 0.47068287 | E10: Makhana_7-2994 | F10: FG | G10: Roasted & Flavoured Makhana | H10: Roasted & Salted Makhana Farmley Jar 55 g | I10: Prasadam Roasted Makhana | J10: 0.055 | K10: 1050 | L10: CPC KPKB | M10: 57.75 | N10: CPC | O10: Purnea | P10: Value Added | Q10: Roasted & Flavoured Makhana | R10: =IF(Config!$B$4>0,M10/Config!$B$4,0) | S10: =IF(Config!$B$4>0,K10/Config!$B$4,0) | T10: =R10*Config!$B$7 | U10: =S10*Config!$B$7 | V10: 0 | W10: 0 | X10: =IF(T10>0,V10/T10,0) | Y10: =IF(U10>0,W10/U10,0) | Z10: =T10-V10 | AA10: =U10-W10 | AB10: =IF(Config!$B$7>0,(V10/Config!$B$7)*Config!$B$4,0) | AC10: =IF(Config!$B$7>0,(W10/Config!$B$7)*Config!$B$4,0)
A11: May | B11: 2026 | C11: 29-04-2026 | D11: 0.47068287 | E11: Makhana_7-2993 | F11: FG | G11: Roasted & Flavoured Makhana | H11: Roasted & Flavoured Minty Pudina Makhana Farmley Jar 55 g | I11: Prasadam Roasted Makhana | J11: 0.055 | K11: 1050 | L11: CPC KPKB | M11: 57.75 | N11: CPC | O11: Purnea | P11: Value Added | Q11: Roasted & Flavoured Makhana | R11: =IF(Config!$B$4>0,M11/Config!$B$4,0) | S11: =IF(Config!$B$4>0,K11/Config!$B$4,0) | T11: =R11*Config!$B$7 | U11: =S11*Config!$B$7 | V11: 0 | W11: 0 | X11: =IF(T11>0,V11/T11,0) | Y11: =IF(U11>0,W11/U11,0) | Z11: =T11-V11 | AA11: =U11-W11 | AB11: =IF(Config!$B$7>0,(V11/Config!$B$7)*Config!$B$4,0) | AC11: =IF(Config!$B$7>0,(W11/Config!$B$7)*Config!$B$4,0)
A12: May | B12: 2026 | C12: 29-04-2026 | D12: 0.47068287 | E12: Makhana_7-2997 | F12: FG | G12: Roasted & Flavoured Makhana | H12: Roasted & Flavoured Achaari Makhana Farmley Jar 55 g | I12: Prasadam Roasted Makhana | J12: 0.055 | K12: 1050 | L12: CPC KPKB | M12: 57.75 | N12: CPC | O12: Purnea | P12: Value Added | Q12: Roasted & Flavoured Makhana | R12: =IF(Config!$B$4>0,M12/Config!$B$4,0) | S12: =IF(Config!$B$4>0,K12/Config!$B$4,0) | T12: =R12*Config!$B$7 | U12: =S12*Config!$B$7 | V12: 0 | W12: 0 | X12: =IF(T12>0,V12/T12,0) | Y12: =IF(U12>0,W12/U12,0) | Z12: =T12-V12 | AA12: =U12-W12 | AB12: =IF(Config!$B$7>0,(V12/Config!$B$7)*Config!$B$4,0) | AC12: =IF(Config!$B$7>0,(W12/Config!$B$7)*Config!$B$4,0)
A13: May | B13: 2026 | C13: 29-04-2026 | D13: 0.53008102 | E13: Makhana_7-30098 | F13: FG | G13: Makhana Raw | H13: Prasadam Makhana Center Seal Pouch 200 g- NEW | I13: Prasadam Makhana | J13: 0.2 | K13: 3000 | L13: Metro Cash & Carry India Private Limited | M13: 600 | N13: Modern Trade | O13: Purnea | P13: KVI | Q13: Makhana Raw | R13: =IF(Config!$B$4>0,M13/Config!$B$4,0) | S13: =IF(Config!$B$4>0,K13/Config!$B$4,0) | T13: =R13*Config!$B$7 | U13: =S13*Config!$B$7 | V13: 456 | W13: 2280 | X13: =IF(T13>0,V13/T13,0) | Y13: =IF(U13>0,W13/U13,0) | Z13: =T13-V13 | AA13: =U13-W13 | AB13: =IF(Config!$B$7>0,(V13/Config!$B$7)*Config!$B$4,0) | AC13: =IF(Config!$B$7>0,(W13/Config!$B$7)*Config!$B$4,0)
... A17: May | B17: 2026 | C17: 29-04-2026 | D17: 0.62037037 | E17: Makhana_7-30042 | F17: FG | G17: Makhana Raw | H17: Prasadam Makhana Farmley Center Seal Pouch 250g | I17: Prasadam Makhana | J17: 0.25 | K17: 4514 | L17: Amazon Retail India Private Limited | M17: 1128.5 | N17: Amazon Retail India | O17: Purnea | P17: KVI | Q17: Makhana Raw | R17: =IF(Config!$B$4>0,M17/Config!$B$4,0) | S17: =IF(Config!$B$4>0,K17/Config!$B$4,0) | T17: =R17*Config!$B$7 | U17: =S17*Config!$B$7 | V17: 24 | W17: 96 | X17: =IF(T17>0,V17/T17,0) | Y17: =IF(U17>0,W17/U17,0) | Z17: =T17-V17 | AA17: =U17-W17 | AB17: =IF(Config!$B$7>0,(V17/Config!$B$7)*Config!$B$4,0) | AC17: =IF(Config!$B$7>0,(W17/Config!$B$7)*Config!$B$4,0)
A18: May | B18: 2026 | C18: 30-04-2026 | D18: 0.73998843 | E18: Makhana_7-30184 | F18: FG | G18: Roasted & Flavoured Makhana | H18: Roasted & Flavored Makhana - Tangy Tomato Farmley Composite Jar 83 g - Pack of 2 | I18: Prasadam Roasted Makhana | J18: 0.166 | K18: 259 | L18: Amazon Retail India Private Limited | M18: 42.99 | N18: Amazon Retail India | O18: Purnea | P18: Value Added | R18: =IF(Config!$B$4>0,M18/Config!$B$4,0) | S18: =IF(Config!$B$4>0,K18/Config!$B$4,0) | T18: =R18*Config!$B$7 | U18: =S18*Config!$B$7 | V18: 0 | W18: 0 | X18: =IF(T18>0,V18/T18,0) | Y18: =IF(U18>0,W18/U18,0) | Z18: =T18-V18 | AA18: =U18-W18 | AB18: =IF(Config!$B$7>0,(V18/Config!$B$7)*Config!$B$4,0) | AC18: =IF(Config!$B$7>0,(W18/Config!$B$7)*Config!$B$4,0)
A19: May | B19: 2026 | C19: 30-04-2026 | D19: 0.69038194 | E19: Makhana_7-30185 | F19: FG | G19: Roasted & Flavoured Makhana | H19: Roasted & Flavored Makhana - Peri Peri Farmley Composite Jar 83 g - Pack of 2 | I19: Prasadam Roasted Makhana | J19: 0.166 | K19: 342 | L19: Amazon Retail India Private Limited | M19: 56.77 | N19: Amazon Retail India | O19: Purnea | P19: Value Added | R19: =IF(Config!$B$4>0,M19/Config!$B$4,0) | S19: =IF(Config!$B$4>0,K19/Config!$B$4,0) | T19: =R19*Config!$B$7 | U19: =S19*Config!$B$7 | V19: 0 | W19: 0 | X19: =IF(T19>0,V19/T19,0) | Y19: =IF(U19>0,W19/U19,0) | Z19: =T19-V19 | AA19: =U19-W19 | AB19: =IF(Config!$B$7>0,(V19/Config!$B$7)*Config!$B$4,0) | AC19: =IF(Config!$B$7>0,(W19/Config!$B$7)*Config!$B$4,0)
A20: May | B20: 2026 | C20: 30-04-2026 | D20: 0.69038194 | E20: Makhana_7-30161 | F20: FG | G20: Roasted & Flavoured Makhana | H20: Roasted & Flavoured Makhana - Cheddar Cheese Farmley Composite Jar 83 g | I20: Prasadam Roasted Makhana | J20: 0.083 | K20: 1097 | L20: Amazon Retail India Private Limited | M20: 91.05 | N20: Amazon Retail India | O20: Purnea | P20: Value Added | Q20: Roasted & Flavoured Makhana | R20: =IF(Config!$B$4>0,M20/Config!$B$4,0) | S20: =IF(Config!$B$4>0,K20/Config!$B$4,0) | T20: =R20*Config!$B$7 | U20: =S20*Config!$B$7 | V20: 0 | W20: 0 | X20: =IF(T20>0,V20/T20,0) | Y20: =IF(U20>0,W20/U20,0) | Z20: =T20-V20 | AA20: =U20-W20 | AB20: =IF(Config!$B$7>0,(V20/Config!$B$7)*Config!$B$4,0) | AC20: =IF(Config!$B$7>0,(W20/Config!$B$7)*Config!$B$4,0)
A21: May | B21: 2026 | C21: 29-04-2026 | D21: 0.62037037 | E21: Makhana_7-2982 | F21: FG | G21: Roasted & Flavoured Makhana | H21: Roasted & Flavored Makhana - Achaari Farmley Composite Jar 77 g | I21: Prasadam Roasted Makhana | J21: 0.077 | K21: 832 | L21: Amazon Retail India Private Limited | M21: 64.06 | N21: Amazon Retail India | O21: Purnea | P21: Value Added | Q21: Roasted & Flavoured Makhana | R21: =IF(Config!$B$4>0,M21/Config!$B$4,0) | S21: =IF(Config!$B$4>0,K21/Config!$B$4,0) | T21: =R21*Config!$B$7 | U21: =S21*Config!$B$7 | V21: 24.02 | W21: 312 | X21: =IF(T21>0,V21/T21,0) | Y21: =IF(U21>0,W21/U21,0) | Z21: =T21-V21 | AA21: =U21-W21 | AB21: =IF(Config!$B$7>0,(V21/Config!$B$7)*Config!$B$4,0) | AC21: =IF(Config!$B$7>0,(W21/Config!$B$7)*Config!$B$4,0)
A22: May | B22: 2026 | C22: 30-04-2026 | D22: 0.73998843 | E22: Makhana_7-30186 | F22: FG | G22: Roasted & Flavoured Makhana | H22: Roasted & Flavored Makhana - Cream N Onion Farmley Composite Jar 83 g - Pack of 2 | I22: Prasadam Roasted Makhana | J22: 0.166 | K22: 509 | L22: Amazon Retail India Private Limited | M22: 84.49 | N22: Amazon Retail India | O22: Purnea | P22: Value Added | R22: =IF(Config!$B$4>0,M22/Config!$B$4,0) | S22: =IF(Config!$B$4>0,K22/Config!$B$4,0) | T22: =R22*Config!$B$7 | U22: =S22*Config!$B$7 | V22: 0 | W22: 0 | X22: =IF(T22>0,V22/T22,0) | Y22: =IF(U22>0,W22/U22,0) | Z22: =T22-V22 | AA22: =U22-W22 | AB22: =IF(Config!$B$7>0,(V22/Config!$B$7)*Config!$B$4,0) | AC22: =IF(Config!$B$7>0,(W22/Config!$B$7)*Config!$B$4,0)
A23: May | B23: 2026 | C23: 30-04-2026 | D23: 0.69038194 | E23: Makhana_7-30166 | F23: FG | G23: Roasted & Flavoured Makhana | H23: Roasted & Flavored Makhana - Mint Farmley Composite Jar 83 g | I23: Prasadam Roasted Makhana | J23: 0.083 | K23: 1281 | L23: Amazon Retail India Private Limited | M23: 106.32 | N23: Amazon Retail India | O23: Purnea | P23: Value Added | Q23: Roasted & Flavoured Makhana | R23: =IF(Config!$B$4>0,M23/Config!$B$4,0) | S23: =IF(Config!$B$4>0,K23/Config!$B$4,0) | T23: =R23*Config!$B$7 | U23: =S23*Config!$B$7 | V23: 0 | W23: 0 | X23: =IF(T23>0,V23/T23,0) | Y23: =IF(U23>0,W23/U23,0) | Z23: =T23-V23 | AA23: =U23-W23 | AB23: =IF(Config!$B$7>0,(V23/Config!$B$7)*Config!$B$4,0) | AC23: =IF(Config!$B$7>0,(W23/Config!$B$7)*Config!$B$4,0)
A24: May | B24: 2026 | C24: 30-04-2026 | D24: 0.69040509 | E24: Makhana_7-30164 | F24: FG | G24: Roasted & Flavoured Makhana | H24: Roasted & Flavored Makhana - Peri Peri Farmley Composite Jar 83 g | I24: Prasadam Roasted Makhana | J24: 0.083 | K24: 1812 | L24: Amazon Retail India Private Limited | M24: 150.4 | N24: Amazon Retail India | O24: Purnea | P24: Value Added | Q24: Roasted & Flavoured Makhana | R24: =IF(Config!$B$4>0,M24/Config!$B$4,0) | S24: =IF(Config!$B$4>0,K24/Config!$B$4,0) | T24: =R24*Config!$B$7 | U24: =S24*Config!$B$7 | V24: 0 | W24: 0 | X24: =IF(T24>0,V24/T24,0) | Y24: =IF(U24>0,W24/U24,0) | Z24: =T24-V24 | AA24: =U24-W24 | AB24: =IF(Config!$B$7>0,(V24/Config!$B$7)*Config!$B$4,0) | AC24: =IF(Config!$B$7>0,(W24/Config!$B$7)*Config!$B$4,0)
A25: May | B25: 2026 | C25: 30-04-2026 | D25: 0.69040509 | E25: Makhana_7-30167 | F25: FG | G25: Roasted & Flavoured Makhana | H25: Roasted & Salted Makhana Farmley Composite Jar 83 g | I25: Prasadam Roasted Makhana | J25: 0.083 | K25: 4545 | L25: Amazon Retail India Private Limited | M25: 377.24 | N25: Amazon Retail India | O25: Purnea | P25: Value Added | Q25: Roasted & Flavoured Makhana | R25: =IF(Config!$B$4>0,M25/Config!$B$4,0) | S25: =IF(Config!$B$4>0,K25/Config!$B$4,0) | T25: =R25*Config!$B$7 | U25: =S25*Config!$B$7 | V25: 0 | W25: 0 | X25: =IF(T25>0,V25/T25,0) | Y25: =IF(U25>0,W25/U25,0) | Z25: =T25-V25 | AA25: =U25-W25 | AB25: =IF(Config!$B$7>0,(V25/Config!$B$7)*Config!$B$4,0) | AC25: =IF(Config!$B$7>0,(W25/Config!$B$7)*Config!$B$4,0)
A26: May | B26: 2026 | C26: 30-04-2026 | D26: 0.69037037 | E26: Makhana_7-30189 | F26: FG | G26: Roasted & Flavoured Makhana | H26: Roasted & Salted Makhana Composite Jar 83 g - Pack of 2 | I26: Prasadam Roasted Makhana | J26: 0.166 | K26: 544 | L26: Amazon Retail India Private Limited | M26: 90.3 | N26: Amazon Retail India | O26: Purnea | P26: Value Added | R26: =IF(Config!$B$4>0,M26/Config!$B$4,0) | S26: =IF(Config!$B$4>0,K26/Config!$B$4,0) | T26: =R26*Config!$B$7 | U26: =S26*Config!$B$7 | V26: 0 | W26: 0 | X26: =IF(T26>0,V26/T26,0) | Y26: =IF(U26>0,W26/U26,0) | Z26: =T26-V26 | AA26: =U26-W26 | AB26: =IF(Config!$B$7>0,(V26/Config!$B$7)*Config!$B$4,0) | AC26: =IF(Config!$B$7>0,(W26/Config!$B$7)*Config!$B$4,0)
A27: May | B27: 2026 | C27: 29-04-2026 | D27: 0.62049769 | E27: Makhana_7-30097 | F27: FG | G27: Makhana Raw | H27: Prasadam Makhana Farmley Center Seal Pouch 60g-New | I27: Prasadam Makhana | J27: 0.06 | K27: 1260 | L27: Amazon Retail India Private Limited | M27: 75.6 | N27: Amazon Retail India | O27: Purnea | P27: KVI | Q27: Makhana Raw | R27: =IF(Config!$B$4>0,M27/Config!$B$4,0) | S27: =IF(Config!$B$4>0,K27/Config!$B$4,0) | T27: =R27*Config!$B$7 | U27: =S27*Config!$B$7 | V27: 27 | W27: 450 | X27: =IF(T27>0,V27/T27,0) | Y27: =IF(U27>0,W27/U27,0) | Z27: =T27-V27 | AA27: =U27-W27 | AB27: =IF(Config!$B$7>0,(V27/Config!$B$7)*Config!$B$4,0) | AC27: =IF(Config!$B$7>0,(W27/Config!$B$7)*Config!$B$4,0)
A28: May | B28: 2026 | C28: 29-04-2026 | D28: 0.62050926 | E28: Makhana_7-30152 | F28: FG | G28: Roasted & Flavoured Makhana | H28: Roasted & Flavored Makhana - Cream & Onion Farmley Pillow Pouch 20 g | I28: Prasadam Roasted Makhana | J28: 0.02 | K28: 2500 | L28: Amazon Retail India Private Limited | M28: 50 | N28: Amazon Retail India | O28: Purnea | P28: Value Added | Q28: Roasted & Flavoured Makhana | R28: =IF(Config!$B$4>0,M28/Config!$B$4,0) | S28: =IF(Config!$B$4>0,K28/Config!$B$4,0) | T28: =R28*Config!$B$7 | U28: =S28*Config!$B$7 | V28: 40.8 | W28: 2040 | X28: =IF(T28>0,V28/T28,0) | Y28: =IF(U28>0,W28/U28,0) | Z28: =T28-V28 | AA28: =U28-W28 | AB28: =IF(Config!$B$7>0,(V28/Config!$B$7)*Config!$B$4,0) | AC28: =IF(Config!$B$7>0,(W28/Config!$B$7)*Config!$B$4,0)
A29: May | B29: 2026 | C29: 29-04-2026 | D29: 0.62050926 | E29: Makhana_7-30153 | F29: FG | G29: Roasted & Flavoured Makhana | H29: Roasted & Flavored Makhana - Peri Peri Farmley Pillow Pouch 20 g | I29: Prasadam Roasted Makhana | J29: 0.02 | K29: 3375 | L29: Amazon Retail India Private Limited | M29: 67.5 | N29: Amazon Retail India | O29: Purnea | P29: Value Added | Q29: Roasted & Flavoured Makhana | R29: =IF(Config!$B$4>0,M29/Config!$B$4,0) | S29: =IF(Config!$B$4>0,K29/Config!$B$4,0) | T29: =R29*Config!$B$7 | U29: =S29*Config!$B$7 | V29: 33.6 | W29: 1680 | X29: =IF(T29>0,V29/T29,0) | Y29: =IF(U29>0,W29/U29,0) | Z29: =T29-V29 | AA29: =U29-W29 | AB29: =IF(Config!$B$7>0,(V29/Config!$B$7)*Config!$B$4,0) | AC29: =IF(Config!$B$7>0,(W29/Config!$B$7)*Config!$B$4,0)
A30: May | B30: 2026 | C30: 29-04-2026 | D30: 0.62050926 | E30: Makhana_7-30151 | F30: FG | G30: Roasted & Flavoured Makhana | H30: Roasted & Flavored Makhana - Tangy Tomato Farmley Pillow Pouch 20 g | I30: Prasadam Roasted Makhana | J30: 0.02 | K30: 1406 | L30: Amazon Retail India Private Limited | M30: 28.12 | N30: Amazon Retail India | O30: Purnea | P30: Value Added | Q30: Roasted & Flavoured Makhana | R30: =IF(Config!$B$4>0,M30/Config!$B$4,0) | S30: =IF(Config!$B$4>0,K30/Config!$B$4,0) | T30: =R30*Config!$B$7 | U30: =S30*Config!$B$7 | V30: 1.2 | W30: 60 | X30: =IF(T30>0,V30/T30,0) | Y30: =IF(U30>0,W30/U30,0) | Z30: =T30-V30 | AA30: =U30-W30 | AB30: =IF(Config!$B$7>0,(V30/Config!$B$7)*Config!$B$4,0) | AC30: =IF(Config!$B$7>0,(W30/Config!$B$7)*Config!$B$4,0)
A31: May | B31: 2026 | C31: 29-04-2026 | D31: 0.62052083 | E31: Makhana_7-30136 | F31: FG | G31: Roasted & Flavoured Makhana | H31: Roasted & Flavoured Makhana - Lemon Chilli Farmley Composite Jar 77 g | I31: Prasadam Roasted Makhana | J31: 0.077 | K31: 600 | L31: Amazon Retail India Private Limited | M31: 46.2 | N31: Amazon Retail India | O31: Purnea | P31: Value Added | Q31: Roasted & Flavoured Makhana | R31: =IF(Config!$B$4>0,M31/Config!$B$4,0) | S31: =IF(Config!$B$4>0,K31/Config!$B$4,0) | T31: =R31*Config!$B$7 | U31: =S31*Config!$B$7 | V31: 29.57 | W31: 384 | X31: =IF(T31>0,V31/T31,0) | Y31: =IF(U31>0,W31/U31,0) | Z31: =T31-V31 | AA31: =U31-W31 | AB31: =IF(Config!$B$7>0,(V31/Config!$B$7)*Config!$B$4,0) | AC31: =IF(Config!$B$7>0,(W31/Config!$B$7)*Config!$B$4,0)
A32: May | B32: 2026 | C32: 29-04-2026 | D32: 0.62052083 | E32: Makhana_7-30147 | F32: FG | G32: Roasted & Flavoured Makhana | H32: Roasted & Flavored Makhana-Lemon Chilli 20g | I32: Prasadam Roasted Makhana | J32: 0.02 | K32: 500 | L32: Amazon Retail India Private Limited | M32: 10 | N32: Amazon Retail India | O32: Purnea | P32: Value Added | Q32: Roasted & Flavoured Makhana | R32: =IF(Config!$B$4>0,M32/Config!$B$4,0) | S32: =IF(Config!$B$4>0,K32/Config!$B$4,0) | T32: =R32*Config!$B$7 | U32: =S32*Config!$B$7 | V32: 12 | W32: 600 | X32: =IF(T32>0,V32/T32,0) | Y32: =IF(U32>0,W32/U32,0) | Z32: =T32-V32 | AA32: =U32-W32 | AB32: =IF(Config!$B$7>0,(V32/Config!$B$7)*Config!$B$4,0) | AC32: =IF(Config!$B$7>0,(W32/Config!$B$7)*Config!$B$4,0)
A33: May | B33: 2026 | C33: 29-04-2026 | D33: 0.62052083 | E33: Makhana_7-30146 | F33: FG | G33: Roasted & Flavoured Makhana | H33: Roasted & Flavored Makhana- Cheesy cheddar 20g | I33: Prasadam Roasted Makhana | J33: 0.02 | K33: 500 | L33: Amazon Retail India Private Limited | M33: 10 | N33: Amazon Retail India | O33: Purnea | P33: Value Added | Q33: Roasted & Flavoured Makhana | R33: =IF(Config!$B$4>0,M33/Config!$B$4,0) | S33: =IF(Config!$B$4>0,K33/Config!$B$4,0) | T33: =R33*Config!$B$7 | U33: =S33*Config!$B$7 | V33: 12 | W33: 600 | X33: =IF(T33>0,V33/T33,0) | Y33: =IF(U33>0,W33/U33,0) | Z33: =T33-V33 | AA33: =U33-W33 | AB33: =IF(Config!$B$7>0,(V33/Config!$B$7)*Config!$B$4,0) | AC33: =IF(Config!$B$7>0,(W33/Config!$B$7)*Config!$B$4,0)
A34: May | B34: 2026 | C34: 29-04-2026 | D34: 0.62052083 | E34: Makhana_7-30149 | F34: FG | G34: Roasted & Flavoured Makhana | H34: Roasted & Flavored Makhana-Minty Pudina 20g | I34: Prasadam Roasted Makhana | J34: 0.02 | K34: 500 | L34: Amazon Retail India Private Limited | M34: 10 | N34: Amazon Retail India | O34: Purnea | P34: Value Added | Q34: Roasted & Flavoured Makhana | R34: =IF(Config!$B$4>0,M34/Config!$B$4,0) | S34: =IF(Config!$B$4>0,K34/Config!$B$4,0) | T34: =R34*Config!$B$7 | U34: =S34*Config!$B$7 | V34: 12 | W34: 600 | X34: =IF(T34>0,V34/T34,0) | Y34: =IF(U34>0,W34/U34,0) | Z34: =T34-V34 | AA34: =U34-W34 | AB34: =IF(Config!$B$7>0,(V34/Config!$B$7)*Config!$B$4,0) | AC34: =IF(Config!$B$7>0,(W34/Config!$B$7)*Config!$B$4,0)
A35: May | B35: 2026 | C35: 29-04-2026 | D35: 0.65148148 | E35: Makhana_7-2979 | F35: FG | G35: Roasted & Flavoured Makhana | H35: Roasted & Flavored Makhana -Cheddar Cheese Farmley Composite Jar 77 g | I35: Prasadam Roasted Makhana | J35: 0.077 | K35: 672 | L35: Exports | M35: 51.74 | N35: Exports | O35: Purnea | P35: Value Added | Q35: Roasted & Flavoured Makhana | R35: =IF(Config!$B$4>0,M35/Config!$B$4,0) | S35: =IF(Config!$B$4>0,K35/Config!$B$4,0) | T35: =R35*Config!$B$7 | U35: =S35*Config!$B$7 | V35: 0 | W35: 0 | X35: =IF(T35>0,V35/T35,0) | Y35: =IF(U35>0,W35/U35,0) | Z35: =T35-V35 | AA35: =U35-W35 | AB35: =IF(Config!$B$7>0,(V35/Config!$B$7)*Config!$B$4,0) | AC35: =IF(Config!$B$7>0,(W35/Config!$B$7)*Config!$B$4,0)
A36: May | B36: 2026 | C36: 29-04-2026 | D36: 0.65148148 | E36: Makhana_7-2980 | F36: FG | G36: Roasted & Flavoured Makhana | H36: Roasted & Flavored Makhana - Mint Farmley Composite Jar 77 g | I36: Prasadam Roasted Makhana | J36: 0.077 | K36: 576 | L36: Exports | M36: 44.35 | N36: Exports | O36: Purnea | P36: Value Added | Q36: Roasted & Flavoured Makhana | R36: =IF(Config!$B$4>0,M36/Config!$B$4,0) | S36: =IF(Config!$B$4>0,K36/Config!$B$4,0) | T36: =R36*Config!$B$7 | U36: =S36*Config!$B$7 | V36: 0 | W36: 0 | X36: =IF(T36>0,V36/T36,0) | Y36: =IF(U36>0,W36/U36,0) | Z36: =T36-V36 | AA36: =U36-W36 | AB36: =IF(Config!$B$7>0,(V36/Config!$B$7)*Config!$B$4,0) | AC36: =IF(Config!$B$7>0,(W36/Config!$B$7)*Config!$B$4,0)
A37: May | B37: 2026 | C37: 29-04-2026 | D37: 0.65148148 | E37: Makhana_7-2982 | F37: FG | G37: Roasted & Flavoured Makhana | H37: Roasted & Flavored Makhana - Achaari Farmley Composite Jar 77 g | I37: Prasadam Roasted Makhana | J37: 0.077 | K37: 576 | L37: Exports | M37: 44.35 | N37: Exports | O37: Purnea | P37: Value Added | Q37: Roasted & Flavoured Makhana | R37: =IF(Config!$B$4>0,M37/Config!$B$4,0) | S37: =IF(Config!$B$4>0,K37/Config!$B$4,0) | T37: =R37*Config!$B$7 | U37: =S37*Config!$B$7 | V37: 0 | W37: 0 | X37: =IF(T37>0,V37/T37,0) | Y37: =IF(U37>0,W37/U37,0) | Z37: =T37-V37 | AA37: =U37-W37 | AB37: =IF(Config!$B$7>0,(V37/Config!$B$7)*Config!$B$4,0) | AC37: =IF(Config!$B$7>0,(W37/Config!$B$7)*Config!$B$4,0)
A38: May | B38: 2026 | C38: 29-04-2026 | D38: 0.65148148 | E38: Makhana_7-2983 | F38: FG | G38: Roasted & Flavoured Makhana | H38: Roasted & Flavored Makhana - Peri Peri Farmley Composite Jar 77 g | I38: Prasadam Roasted Makhana | J38: 0.077 | K38: 672 | L38: Exports | M38: 51.74 | N38: Exports | O38: Purnea | P38: Value Added | Q38: Roasted & Flavoured Makhana | R38: =IF(Config!$B$4>0,M38/Config!$B$4,0) | S38: =IF(Config!$B$4>0,K38/Config!$B$4,0) | T38: =R38*Config!$B$7 | U38: =S38*Config!$B$7 | V38: 0 | W38: 0 | X38: =IF(T38>0,V38/T38,0) | Y38: =IF(U38>0,W38/U38,0) | Z38: =T38-V38 | AA38: =U38-W38 | AB38: =IF(Config!$B$7>0,(V38/Config!$B$7)*Config!$B$4,0) | AC38: =IF(Config!$B$7>0,(W38/Config!$B$7)*Config!$B$4,0)
... A49: May | B49: 2026 | C49: 27-04-2026 | D49: 0.72561343 | E49: Makhana_7-30153 | F49: FG | G49: Roasted & Flavoured Makhana | H49: Roasted & Flavored Makhana - Peri Peri Farmley Pillow Pouch 20 g | I49: Prasadam Roasted Makhana | J49: 0.02 | K49: 900 | L49: Justvend Private Limited | M49: 18 | N49: Vending | O49: Purnea | P49: Value Added | Q49: Roasted & Flavoured Makhana | R49: =IF(Config!$B$4>0,M49/Config!$B$4,0) | S49: =IF(Config!$B$4>0,K49/Config!$B$4,0) | T49: =R49*Config!$B$7 | U49: =S49*Config!$B$7 | V49: 0 | W49: 0 | X49: =IF(T49>0,V49/T49,0) | Y49: =IF(U49>0,W49/U49,0) | Z49: =T49-V49 | AA49: =U49-W49 | AB49: =IF(Config!$B$7>0,(V49/Config!$B$7)*Config!$B$4,0) | AC49: =IF(Config!$B$7>0,(W49/Config!$B$7)*Config!$B$4,0)
A50: May | B50: 2026 | C50: 27-04-2026 | D50: 0.72561343 | E50: Makhana_7-30154 | F50: FG | G50: Roasted & Flavoured Makhana | H50: Roasted & Flavored Makhana - Achaari Farmley Pillow Pouch 20 g | I50: Prasadam Roasted Makhana | J50: 0.02 | K50: 600 | L50: Justvend Private Limited | M50: 12 | N50: Vending | O50: Purnea | P50: Value Added | R50: =IF(Config!$B$4>0,M50/Config!$B$4,0) | S50: =IF(Config!$B$4>0,K50/Config!$B$4,0) | T50: =R50*Config!$B$7 | U50: =S50*Config!$B$7 | V50: 0 | W50: 0 | X50: =IF(T50>0,V50/T50,0) | Y50: =IF(U50>0,W50/U50,0) | Z50: =T50-V50 | AA50: =U50-W50 | AB50: =IF(Config!$B$7>0,(V50/Config!$B$7)*Config!$B$4,0) | AC50: =IF(Config!$B$7>0,(W50/Config!$B$7)*Config!$B$4,0)
A51: May | B51: 2026 | C51: 27-04-2026 | D51: 0.725625 | E51: Makhana_7-30152 | F51: FG | G51: Roasted & Flavoured Makhana | H51: Roasted & Flavored Makhana - Cream & Onion Farmley Pillow Pouch 20 g | I51: Prasadam Roasted Makhana | J51: 0.02 | K51: 600 | L51: Instant Retail India Limited | M51: 12 | N51: Vending | O51: Purnea | P51: Value Added | Q51: Roasted & Flavoured Makhana | R51: =IF(Config!$B$4>0,M51/Config!$B$4,0) | S51: =IF(Config!$B$4>0,K51/Config!$B$4,0) | T51: =R51*Config!$B$7 | U51: =S51*Config!$B$7 | V51: 0 | W51: 0 | X51: =IF(T51>0,V51/T51,0) | Y51: =IF(U51>0,W51/U51,0) | Z51: =T51-V51 | AA51: =U51-W51 | AB51: =IF(Config!$B$7>0,(V51/Config!$B$7)*Config!$B$4,0) | AC51: =IF(Config!$B$7>0,(W51/Config!$B$7)*Config!$B$4,0)
A52: May | B52: 2026 | C52: 27-04-2026 | D52: 0.725625 | E52: Makhana_7-30153 | F52: FG | G52: Roasted & Flavoured Makhana | H52: Roasted & Flavored Makhana - Peri Peri Farmley Pillow Pouch 20 g | I52: Prasadam Roasted Makhana | J52: 0.02 | K52: 600 | L52: Instant Retail India Limited | M52: 12 | N52: Vending | O52: Purnea | P52: Value Added | Q52: Roasted & Flavoured Makhana | R52: =IF(Config!$B$4>0,M52/Config!$B$4,0) | S52: =IF(Config!$B$4>0,K52/Config!$B$4,0) | T52: =R52*Config!$B$7 | U52: =S52*Config!$B$7 | V52: 0 | W52: 0 | X52: =IF(T52>0,V52/T52,0) | Y52: =IF(U52>0,W52/U52,0) | Z52: =T52-V52 | AA52: =U52-W52 | AB52: =IF(Config!$B$7>0,(V52/Config!$B$7)*Config!$B$4,0) | AC52: =IF(Config!$B$7>0,(W52/Config!$B$7)*Config!$B$4,0)
A53: May | B53: 2026 | C53: 27-04-2026 | D53: 0.725625 | E53: Makhana_7-30074 | F53: FG | G53: Roasted & Flavoured Makhana | H53: Roasted & Flavoured Makhana - Cream & Onion Farmley Pillow Pouch 14g-Ladi | I53: Prasadam Roasted Makhana | J53: 0.014 | K53: 6200 | L53: Daalchini Foods & Beverages Private Limited | M53: 86.8 | N53: Vending | O53: Purnea | P53: Value Added | Q53: Roasted & Flavoured Makhana | R53: =IF(Config!$B$4>0,M53/Config!$B$4,0) | S53: =IF(Config!$B$4>0,K53/Config!$B$4,0) | T53: =R53*Config!$B$7 | U53: =S53*Config!$B$7 | V53: 35.28 | W53: 2520 | X53: =IF(T53>0,V53/T53,0) | Y53: =IF(U53>0,W53/U53,0) | Z53: =T53-V53 | AA53: =U53-W53 | AB53: =IF(Config!$B$7>0,(V53/Config!$B$7)*Config!$B$4,0) | AC53: =IF(Config!$B$7>0,(W53/Config!$B$7)*Config!$B$4,0)
A54: May | B54: 2026 | C54: 27-04-2026 | D54: 0.725625 | E54: Makhana_7-30075 | F54: FG | G54: Roasted & Flavoured Makhana | H54: Roasted & Flavoured Makhana - Tangy Tomato Farmley Pillow Pouch 14g-Ladi | I54: Prasadam Roasted Makhana | J54: 0.014 | K54: 900 | L54: Daalchini Foods & Beverages Private Limited | M54: 12.6 | N54: Vending | O54: Purnea | P54: Value Added | Q54: Roasted & Flavoured Makhana | R54: =IF(Config!$B$4>0,M54/Config!$B$4,0) | S54: =IF(Config!$B$4>0,K54/Config!$B$4,0) | T54: =R54*Config!$B$7 | U54: =S54*Config!$B$7 | V54: 5.04 | W54: 360 | X54: =IF(T54>0,V54/T54,0) | Y54: =IF(U54>0,W54/U54,0) | Z54: =T54-V54 | AA54: =U54-W54 | AB54: =IF(Config!$B$7>0,(V54/Config!$B$7)*Config!$B$4,0) | AC54: =IF(Config!$B$7>0,(W54/Config!$B$7)*Config!$B$4,0)
A55: May | B55: 2026 | C55: 27-04-2026 | D55: 0.725625 | E55: Makhana_7-30073 | F55: FG | G55: Roasted & Flavoured Makhana | H55: Roasted & Flavored Makhana - Peri Peri Farmley Pillow Pouch 14 g-Ladi | I55: Prasadam Roasted Makhana | J55: 0.014 | K55: 2400 | L55: Daalchini Foods & Beverages Private Limited | M55: 33.6 | N55: Vending | O55: Purnea | P55: Value Added | Q55: Roasted & Flavoured Makhana | R55: =IF(Config!$B$4>0,M55/Config!$B$4,0) | S55: =IF(Config!$B$4>0,K55/Config!$B$4,0) | T55: =R55*Config!$B$7 | U55: =S55*Config!$B$7 | V55: 7.56 | W55: 540 | X55: =IF(T55>0,V55/T55,0) | Y55: =IF(U55>0,W55/U55,0) | Z55: =T55-V55 | AA55: =U55-W55 | AB55: =IF(Config!$B$7>0,(V55/Config!$B$7)*Config!$B$4,0) | AC55: =IF(Config!$B$7>0,(W55/Config!$B$7)*Config!$B$4,0)
A56: May | B56: 2026 | C56: 27-04-2026 | D56: 0.72564815 | E56: Makhana_7-2984 | F56: FG | G56: Roasted & Flavoured Makhana | H56: Roasted & Salted Makhana Farmley Composite Jar 77 g | I56: Prasadam Roasted Makhana | J56: 0.077 | K56: 150 | L56: Sodexo India Services Private Limited | M56: 11.55 | N56: HoReCa | O56: Purnea | P56: Value Added | Q56: Roasted & Flavoured Makhana | R56: =IF(Config!$B$4>0,M56/Config!$B$4,0) | S56: =IF(Config!$B$4>0,K56/Config!$B$4,0) | T56: =R56*Config!$B$7 | U56: =S56*Config!$B$7 | V56: 0 | W56: 0 | X56: =IF(T56>0,V56/T56,0) | Y56: =IF(U56>0,W56/U56,0) | Z56: =T56-V56 | AA56: =U56-W56 | AB56: =IF(Config!$B$7>0,(V56/Config!$B$7)*Config!$B$4,0) | AC56: =IF(Config!$B$7>0,(W56/Config!$B$7)*Config!$B$4,0)
A57: May | B57: 2026 | C57: 27-04-2026 | D57: 0.72564815 | E57: Makhana_7-2983 | F57: FG | G57: Roasted & Flavoured Makhana | H57: Roasted & Flavored Makhana - Peri Peri Farmley Composite Jar 77 g | I57: Prasadam Roasted Makhana | J57: 0.077 | K57: 48 | L57: Sodexo India Services Private Limited | M57: 3.7 | N57: HoReCa | O57: Purnea | P57: Value Added | Q57: Roasted & Flavoured Makhana | R57: =IF(Config!$B$4>0,M57/Config!$B$4,0) | S57: =IF(Config!$B$4>0,K57/Config!$B$4,0) | T57: =R57*Config!$B$7 | U57: =S57*Config!$B$7 | V57: 0 | W57: 0 | X57: =IF(T57>0,V57/T57,0) | Y57: =IF(U57>0,W57/U57,0) | Z57: =T57-V57 | AA57: =U57-W57 | AB57: =IF(Config!$B$7>0,(V57/Config!$B$7)*Config!$B$4,0) | AC57: =IF(Config!$B$7>0,(W57/Config!$B$7)*Config!$B$4,0)
A58: May | B58: 2026 | C58: 27-04-2026 | D58: 0.72564815 | E58: Makhana_7-2756 | F58: FG | G58: Roasted & Flavoured Makhana | H58: Roasted & Flavored Makhana - Minty Pudina Farmley Standee Pouch 180 g | I58: Prasadam Roasted Makhana | J58: 0.18 | K58: 16 | L58: Compass India Food Services Private Limited | M58: 2.88 | N58: Corporate | O58: Purnea | P58: Value Added | R58: =IF(Config!$B$4>0,M58/Config!$B$4,0) | S58: =IF(Config!$B$4>0,K58/Config!$B$4,0) | T58: =R58*Config!$B$7 | U58: =S58*Config!$B$7 | V58: 0 | W58: 0 | X58: =IF(T58>0,V58/T58,0) | Y58: =IF(U58>0,W58/U58,0) | Z58: =T58-V58 | AA58: =U58-W58 | AB58: =IF(Config!$B$7>0,(V58/Config!$B$7)*Config!$B$4,0) | AC58: =IF(Config!$B$7>0,(W58/Config!$B$7)*Config!$B$4,0)
A59: May | B59: 2026 | C59: 27-04-2026 | D59: 0.72564815 | E59: Makhana_7-2755 | F59: FG | G59: Roasted & Flavoured Makhana | H59: Roasted & Flavored Makhana - Achaari Farmley Standee Pouch 180 g | I59: Prasadam Roasted Makhana | J59: 0.18 | K59: 16 | L59: Compass India Food Services Private Limited | M59: 2.88 | N59: Corporate | O59: Purnea | P59: Value Added | R59: =IF(Config!$B$4>0,M59/Config!$B$4,0) | S59: =IF(Config!$B$4>0,K59/Config!$B$4,0) | T59: =R59*Config!$B$7 | U59: =S59*Config!$B$7 | V59: 0 | W59: 0 | X59: =IF(T59>0,V59/T59,0) | Y59: =IF(U59>0,W59/U59,0) | Z59: =T59-V59 | AA59: =U59-W59 | AB59: =IF(Config!$B$7>0,(V59/Config!$B$7)*Config!$B$4,0) | AC59: =IF(Config!$B$7>0,(W59/Config!$B$7)*Config!$B$4,0)
A60: May | B60: 2026 | C60: 27-04-2026 | D60: 0.72564815 | E60: Makhana_7-2757 | F60: FG | G60: Roasted & Flavoured Makhana | H60: Roasted & Flavored Makhana - Tangy Tomato Farmley Standee Pouch 180 g | I60: Prasadam Roasted Makhana | J60: 0.18 | K60: 16 | L60: Compass India Food Services Private Limited | M60: 2.88 | N60: Corporate | O60: Purnea | P60: Value Added | R60: =IF(Config!$B$4>0,M60/Config!$B$4,0) | S60: =IF(Config!$B$4>0,K60/Config!$B$4,0) | T60: =R60*Config!$B$7 | U60: =S60*Config!$B$7 | V60: 0 | W60: 0 | X60: =IF(T60>0,V60/T60,0) | Y60: =IF(U60>0,W60/U60,0) | Z60: =T60-V60 | AA60: =U60-W60 | AB60: =IF(Config!$B$7>0,(V60/Config!$B$7)*Config!$B$4,0) | AC60: =IF(Config!$B$7>0,(W60/Config!$B$7)*Config!$B$4,0)
A61: May | B61: 2026 | C61: 27-04-2026 | D61: 0.72565972 | E61: Makhana_7-2754 | F61: FG | G61: Roasted & Flavoured Makhana | H61: Roasted & Flavored Makhana - Cream N Onion Farmley Standee Pouch 180 g | I61: Prasadam Roasted Makhana | J61: 0.18 | K61: 16 | L61: Compass India Food Services Private Limited | M61: 2.88 | N61: Corporate | O61: Purnea | P61: Value Added | R61: =IF(Config!$B$4>0,M61/Config!$B$4,0) | S61: =IF(Config!$B$4>0,K61/Config!$B$4,0) | T61: =R61*Config!$B$7 | U61: =S61*Config!$B$7 | V61: 0 | W61: 0 | X61: =IF(T61>0,V61/T61,0) | Y61: =IF(U61>0,W61/U61,0) | Z61: =T61-V61 | AA61: =U61-W61 | AB61: =IF(Config!$B$7>0,(V61/Config!$B$7)*Config!$B$4,0) | AC61: =IF(Config!$B$7>0,(W61/Config!$B$7)*Config!$B$4,0)
A62: May | B62: 2026 | C62: 27-04-2026 | D62: 0.72565972 | E62: Makhana_7-2753 | F62: FG | G62: Roasted & Flavoured Makhana | H62: Roasted & Flavored Makhana - Peri Peri Farmley Standee Pouch 180 g | I62: Prasadam Roasted Makhana | J62: 0.18 | K62: 16 | L62: Compass India Food Services Private Limited | M62: 2.88 | N62: Corporate | O62: Purnea | P62: Value Added | R62: =IF(Config!$B$4>0,M62/Config!$B$4,0) | S62: =IF(Config!$B$4>0,K62/Config!$B$4,0) | T62: =R62*Config!$B$7 | U62: =S62*Config!$B$7 | V62: 0 | W62: 0 | X62: =IF(T62>0,V62/T62,0) | Y62: =IF(U62>0,W62/U62,0) | Z62: =T62-V62 | AA62: =U62-W62 | AB62: =IF(Config!$B$7>0,(V62/Config!$B$7)*Config!$B$4,0) | AC62: =IF(Config!$B$7>0,(W62/Config!$B$7)*Config!$B$4,0)
A63: May | B63: 2026 | C63: 27-04-2026 | D63: 0.72565972 | E63: Makhana_7-30152 | F63: FG | G63: Roasted & Flavoured Makhana | H63: Roasted & Flavored Makhana - Cream & Onion Farmley Pillow Pouch 20 g | I63: Prasadam Roasted Makhana | J63: 0.02 | K63: 6000 | L63: Compass India Food Services Private Limited | M63: 120 | N63: Corporate | O63: Purnea | P63: Value Added | Q63: Roasted & Flavoured Makhana | R63: =IF(Config!$B$4>0,M63/Config!$B$4,0) | S63: =IF(Config!$B$4>0,K63/Config!$B$4,0) | T63: =R63*Config!$B$7 | U63: =S63*Config!$B$7 | V63: 12 | W63: 600 | X63: =IF(T63>0,V63/T63,0) | Y63: =IF(U63>0,W63/U63,0) | Z63: =T63-V63 | AA63: =U63-W63 | AB63: =IF(Config!$B$7>0,(V63/Config!$B$7)*Config!$B$4,0) | AC63: =IF(Config!$B$7>0,(W63/Config!$B$7)*Config!$B$4,0)
A64: May | B64: 2026 | C64: 27-04-2026 | D64: 0.72565972 | E64: Makhana_7-30154 | F64: FG | G64: Roasted & Flavoured Makhana | H64: Roasted & Flavored Makhana - Achaari Farmley Pillow Pouch 20 g | I64: Prasadam Roasted Makhana | J64: 0.02 | K64: 500 | L64: Compass India Food Services Private Limited | M64: 10 | N64: Corporate | O64: Purnea | P64: Value Added | R64: =IF(Config!$B$4>0,M64/Config!$B$4,0) | S64: =IF(Config!$B$4>0,K64/Config!$B$4,0) | T64: =R64*Config!$B$7 | U64: =S64*Config!$B$7 | V64: 0 | W64: 0 | X64: =IF(T64>0,V64/T64,0) | Y64: =IF(U64>0,W64/U64,0) | Z64: =T64-V64 | AA64: =U64-W64 | AB64: =IF(Config!$B$7>0,(V64/Config!$B$7)*Config!$B$4,0) | AC64: =IF(Config!$B$7>0,(W64/Config!$B$7)*Config!$B$4,0)
A65: May | B65: 2026 | C65: 27-04-2026 | D65: 0.72565972 | E65: Makhana_7-30153 | F65: FG | G65: Roasted & Flavoured Makhana | H65: Roasted & Flavored Makhana - Peri Peri Farmley Pillow Pouch 20 g | I65: Prasadam Roasted Makhana | J65: 0.02 | K65: 1000 | L65: Compass India Food Services Private Limited | M65: 20 | N65: Corporate | O65: Purnea | P65: Value Added | Q65: Roasted & Flavoured Makhana | R65: =IF(Config!$B$4>0,M65/Config!$B$4,0) | S65: =IF(Config!$B$4>0,K65/Config!$B$4,0) | T65: =R65*Config!$B$7 | U65: =S65*Config!$B$7 | V65: 0 | W65: 0 | X65: =IF(T65>0,V65/T65,0) | Y65: =IF(U65>0,W65/U65,0) | Z65: =T65-V65 | AA65: =U65-W65 | AB65: =IF(Config!$B$7>0,(V65/Config!$B$7)*Config!$B$4,0) | AC65: =IF(Config!$B$7>0,(W65/Config!$B$7)*Config!$B$4,0)
A66: May | B66: 2026 | C66: 27-04-2026 | D66: 0.7256713 | E66: Makhana_7-30151 | F66: FG | G66: Roasted & Flavoured Makhana | H66: Roasted & Flavored Makhana - Tangy Tomato Farmley Pillow Pouch 20 g | I66: Prasadam Roasted Makhana | J66: 0.02 | K66: 2000 | L66: Bottle Lab Technologies Private Limited | M66: 40 | N66: Vending | O66: Purnea | P66: Value Added | Q66: Roasted & Flavoured Makhana | R66: =IF(Config!$B$4>0,M66/Config!$B$4,0) | S66: =IF(Config!$B$4>0,K66/Config!$B$4,0) | T66: =R66*Config!$B$7 | U66: =S66*Config!$B$7 | V66: 24 | W66: 1200 | X66: =IF(T66>0,V66/T66,0) | Y66: =IF(U66>0,W66/U66,0) | Z66: =T66-V66 | AA66: =U66-W66 | AB66: =IF(Config!$B$7>0,(V66/Config!$B$7)*Config!$B$4,0) | AC66: =IF(Config!$B$7>0,(W66/Config!$B$7)*Config!$B$4,0)
A67: May | B67: 2026 | C67: 27-04-2026 | D67: 0.7256713 | E67: Makhana_7-30152 | F67: FG | G67: Roasted & Flavoured Makhana | H67: Roasted & Flavored Makhana - Cream & Onion Farmley Pillow Pouch 20 g | I67: Prasadam Roasted Makhana | J67: 0.02 | K67: 3500 | L67: Bottle Lab Technologies Private Limited | M67: 70 | N67: Vending | O67: Purnea | P67: Value Added | Q67: Roasted & Flavoured Makhana | R67: =IF(Config!$B$4>0,M67/Config!$B$4,0) | S67: =IF(Config!$B$4>0,K67/Config!$B$4,0) | T67: =R67*Config!$B$7 | U67: =S67*Config!$B$7 | V67: 24 | W67: 1200 | X67: =IF(T67>0,V67/T67,0) | Y67: =IF(U67>0,W67/U67,0) | Z67: =T67-V67 | AA67: =U67-W67 | AB67: =IF(Config!$B$7>0,(V67/Config!$B$7)*Config!$B$4,0) | AC67: =IF(Config!$B$7>0,(W67/Config!$B$7)*Config!$B$4,0)
A68: May | B68: 2026 | C68: 27-04-2026 | D68: 0.7256713 | E68: Makhana_7-30153 | F68: FG | G68: Roasted & Flavoured Makhana | H68: Roasted & Flavored Makhana - Peri Peri Farmley Pillow Pouch 20 g | I68: Prasadam Roasted Makhana | J68: 0.02 | K68: 2500 | L68: Bottle Lab Technologies Private Limited | M68: 50 | N68: Vending | O68: Purnea | P68: Value Added | Q68: Roasted & Flavoured Makhana | R68: =IF(Config!$B$4>0,M68/Config!$B$4,0) | S68: =IF(Config!$B$4>0,K68/Config!$B$4,0) | T68: =R68*Config!$B$7 | U68: =S68*Config!$B$7 | V68: 24 | W68: 1200 | X68: =IF(T68>0,V68/T68,0) | Y68: =IF(U68>0,W68/U68,0) | Z68: =T68-V68 | AA68: =U68-W68 | AB68: =IF(Config!$B$7>0,(V68/Config!$B$7)*Config!$B$4,0) | AC68: =IF(Config!$B$7>0,(W68/Config!$B$7)*Config!$B$4,0)
A69: May | B69: 2026 | C69: 27-04-2026 | D69: 0.7256713 | E69: Makhana_7-30154 | F69: FG | G69: Roasted & Flavoured Makhana | H69: Roasted & Flavored Makhana - Achaari Farmley Pillow Pouch 20 g | I69: Prasadam Roasted Makhana | J69: 0.02 | K69: 1500 | L69: Bottle Lab Technologies Private Limited | M69: 30 | N69: Vending | O69: Purnea | P69: Value Added | R69: =IF(Config!$B$4>0,M69/Config!$B$4,0) | S69: =IF(Config!$B$4>0,K69/Config!$B$4,0) | T69: =R69*Config!$B$7 | U69: =S69*Config!$B$7 | V69: 0 | W69: 0 | X69: =IF(T69>0,V69/T69,0) | Y69: =IF(U69>0,W69/U69,0) | Z69: =T69-V69 | AA69: =U69-W69 | AB69: =IF(Config!$B$7>0,(V69/Config!$B$7)*Config!$B$4,0) | AC69: =IF(Config!$B$7>0,(W69/Config!$B$7)*Config!$B$4,0)
A70: May | B70: 2026 | C70: 27-04-2026 | D70: 0.7256713 | E70: Makhana_7-3072 | F70: FG | G70: Roasted & Flavoured Makhana | H70: Roasted & Flavoured Makhana - Tangy Tomato Farmley Composite Jar 57 g-Institutional | I70: Prasadam Roasted Makhana | J70: 0.057 | K70: 35 | L70: Mumbai Travel Retail Private Limited | M70: 2 | N70: Other Institutions | O70: Purnea | P70: Value Added | Q70: Roasted & Flavoured Makhana | R70: =IF(Config!$B$4>0,M70/Config!$B$4,0) | S70: =IF(Config!$B$4>0,K70/Config!$B$4,0) | T70: =R70*Config!$B$7 | U70: =S70*Config!$B$7 | V70: 0 | W70: 0 | X70: =IF(T70>0,V70/T70,0) | Y70: =IF(U70>0,W70/U70,0) | Z70: =T70-V70 | AA70: =U70-W70 | AB70: =IF(Config!$B$7>0,(V70/Config!$B$7)*Config!$B$4,0) | AC70: =IF(Config!$B$7>0,(W70/Config!$B$7)*Config!$B$4,0)
A71: May | B71: 2026 | C71: 27-04-2026 | D71: 0.7256713 | E71: Makhana_7-3069 | F71: FG | G71: Roasted & Flavoured Makhana | H71: Roasted & Salted Makhana Farmley Composite Jar 57 g-Institutional | I71: Prasadam Roasted Makhana | J71: 0.057 | K71: 150 | L71: Mumbai Travel Retail Private Limited | M71: 8.55 | N71: Other Institutions | O71: Purnea | P71: Value Added | Q71: Roasted & Flavoured Makhana | R71: =IF(Config!$B$4>0,M71/Config!$B$4,0) | S71: =IF(Config!$B$4>0,K71/Config!$B$4,0) | T71: =R71*Config!$B$7 | U71: =S71*Config!$B$7 | V71: 0 | W71: 0 | X71: =IF(T71>0,V71/T71,0) | Y71: =IF(U71>0,W71/U71,0) | Z71: =T71-V71 | AA71: =U71-W71 | AB71: =IF(Config!$B$7>0,(V71/Config!$B$7)*Config!$B$4,0) | AC71: =IF(Config!$B$7>0,(W71/Config!$B$7)*Config!$B$4,0)
A72: May | B72: 2026 | C72: 27-04-2026 | D72: 0.7256713 | E72: Makhana_7-3071 | F72: FG | G72: Roasted & Flavoured Makhana | H72: Roasted & Flavoured Makhana - Cream & Onion Farmley Composite Jar 57 g-Institutional | I72: Prasadam Roasted Makhana | J72: 0.057 | K72: 150 | L72: Mumbai Travel Retail Private Limited | M72: 8.55 | N72: Other Institutions | O72: Purnea | P72: Value Added | Q72: Roasted & Flavoured Makhana | R72: =IF(Config!$B$4>0,M72/Config!$B$4,0) | S72: =IF(Config!$B$4>0,K72/Config!$B$4,0) | T72: =R72*Config!$B$7 | U72: =S72*Config!$B$7 | V72: 0 | W72: 0 | X72: =IF(T72>0,V72/T72,0) | Y72: =IF(U72>0,W72/U72,0) | Z72: =T72-V72 | AA72: =U72-W72 | AB72: =IF(Config!$B$7>0,(V72/Config!$B$7)*Config!$B$4,0) | AC72: =IF(Config!$B$7>0,(W72/Config!$B$7)*Config!$B$4,0)
A73: May | B73: 2026 | C73: 27-04-2026 | D73: 0.7256713 | E73: Makhana_7-3070 | F73: FG | G73: Roasted & Flavoured Makhana | H73: Roasted & Flavoured Makhana - Peri Peri Farmley Composite Jar 57 g-Institutional | I73: Prasadam Roasted Makhana | J73: 0.057 | K73: 105 | L73: Mumbai Travel Retail Private Limited | M73: 5.99 | N73: Other Institutions | O73: Purnea | P73: Value Added | Q73: Roasted & Flavoured Makhana | R73: =IF(Config!$B$4>0,M73/Config!$B$4,0) | S73: =IF(Config!$B$4>0,K73/Config!$B$4,0) | T73: =R73*Config!$B$7 | U73: =S73*Config!$B$7 | V73: 0 | W73: 0 | X73: =IF(T73>0,V73/T73,0) | Y73: =IF(U73>0,W73/U73,0) | Z73: =T73-V73 | AA73: =U73-W73 | AB73: =IF(Config!$B$7>0,(V73/Config!$B$7)*Config!$B$4,0) | AC73: =IF(Config!$B$7>0,(W73/Config!$B$7)*Config!$B$4,0)
A74: May | B74: 2026 | C74: 27-04-2026 | D74: 0.72568287 | E74: Makhana_7-3072 | F74: FG | G74: Roasted & Flavoured Makhana | H74: Roasted & Flavoured Makhana - Tangy Tomato Farmley Composite Jar 57 g-Institutional | I74: Prasadam Roasted Makhana | J74: 0.057 | K74: 200 | L74: April Moon Retail Limited | M74: 11.4 | N74: Other Institutions | O74: Purnea | P74: Value Added | Q74: Roasted & Flavoured Makhana | R74: =IF(Config!$B$4>0,M74/Config!$B$4,0) | S74: =IF(Config!$B$4>0,K74/Config!$B$4,0) | T74: =R74*Config!$B$7 | U74: =S74*Config!$B$7 | V74: 7.98 | W74: 140 | X74: =IF(T74>0,V74/T74,0) | Y74: =IF(U74>0,W74/U74,0) | Z74: =T74-V74 | AA74: =U74-W74 | AB74: =IF(Config!$B$7>0,(V74/Config!$B$7)*Config!$B$4,0) | AC74: =IF(Config!$B$7>0,(W74/Config!$B$7)*Config!$B$4,0)
A75: May | B75: 2026 | C75: 27-04-2026 | D75: 0.72568287 | E75: Makhana_7-3069 | F75: FG | G75: Roasted & Flavoured Makhana | H75: Roasted & Salted Makhana Farmley Composite Jar 57 g-Institutional | I75: Prasadam Roasted Makhana | J75: 0.057 | K75: 460 | L75: April Moon Retail Limited | M75: 26.22 | N75: Other Institutions | O75: Purnea | P75: Value Added | Q75: Roasted & Flavoured Makhana | R75: =IF(Config!$B$4>0,M75/Config!$B$4,0) | S75: =IF(Config!$B$4>0,K75/Config!$B$4,0) | T75: =R75*Config!$B$7 | U75: =S75*Config!$B$7 | V75: 23.94 | W75: 420 | X75: =IF(T75>0,V75/T75,0) | Y75: =IF(U75>0,W75/U75,0) | Z75: =T75-V75 | AA75: =U75-W75 | AB75: =IF(Config!$B$7>0,(V75/Config!$B$7)*Config!$B$4,0) | AC75: =IF(Config!$B$7>0,(W75/Config!$B$7)*Config!$B$4,0)
A76: May | B76: 2026 | C76: 27-04-2026 | D76: 0.72568287 | E76: Makhana_7-3071 | F76: FG | G76: Roasted & Flavoured Makhana | H76: Roasted & Flavoured Makhana - Cream & Onion Farmley Composite Jar 57 g-Institutional | I76: Prasadam Roasted Makhana | J76: 0.057 | K76: 250 | L76: April Moon Retail Limited | M76: 14.25 | N76: Other Institutions | O76: Purnea | P76: Value Added | Q76: Roasted & Flavoured Makhana | R76: =IF(Config!$B$4>0,M76/Config!$B$4,0) | S76: =IF(Config!$B$4>0,K76/Config!$B$4,0) | T76: =R76*Config!$B$7 | U76: =S76*Config!$B$7 | V76: 13.96 | W76: 245 | X76: =IF(T76>0,V76/T76,0) | Y76: =IF(U76>0,W76/U76,0) | Z76: =T76-V76 | AA76: =U76-W76 | AB76: =IF(Config!$B$7>0,(V76/Config!$B$7)*Config!$B$4,0) | AC76: =IF(Config!$B$7>0,(W76/Config!$B$7)*Config!$B$4,0)
A77: May | B77: 2026 | C77: 27-04-2026 | D77: 0.72568287 | E77: Makhana_7-3070 | F77: FG | G77: Roasted & Flavoured Makhana | H77: Roasted & Flavoured Makhana - Peri Peri Farmley Composite Jar 57 g-Institutional | I77: Prasadam Roasted Makhana | J77: 0.057 | K77: 315 | L77: April Moon Retail Limited | M77: 17.95 | N77: Other Institutions | O77: Purnea | P77: Value Added | Q77: Roasted & Flavoured Makhana | R77: =IF(Config!$B$4>0,M77/Config!$B$4,0) | S77: =IF(Config!$B$4>0,K77/Config!$B$4,0) | T77: =R77*Config!$B$7 | U77: =S77*Config!$B$7 | V77: 11.97 | W77: 210 | X77: =IF(T77>0,V77/T77,0) | Y77: =IF(U77>0,W77/U77,0) | Z77: =T77-V77 | AA77: =U77-W77 | AB77: =IF(Config!$B$7>0,(V77/Config!$B$7)*Config!$B$4,0) | AC77: =IF(Config!$B$7>0,(W77/Config!$B$7)*Config!$B$4,0)
A78: May | B78: 2026 | C78: 29-04-2026 | D78: 0.61246528 | E78: Makhana_7-30175 | F78: FG | G78: Roasted & Flavoured Makhana | H78: Roasted & Flavoured Cheddar Cheese Makhana Farmley Jar 54g Institutional pack | I78: Prasadam Roasted Makhana | J78: 0.054 | K78: 8700 | L78: Air India Express Limited | M78: 469.8 | N78: Airlines | O78: Purnea | P78: Value Added | Q78: Roasted & Flavoured Makhana | R78: =IF(Config!$B$4>0,M78/Config!$B$4,0) | S78: =IF(Config!$B$4>0,K78/Config!$B$4,0) | T78: =R78*Config!$B$7 | U78: =S78*Config!$B$7 | V78: 360.99 | W78: 6685 | X78: =IF(T78>0,V78/T78,0) | Y78: =IF(U78>0,W78/U78,0) | Z78: =T78-V78 | AA78: =U78-W78 | AB78: =IF(Config!$B$7>0,(V78/Config!$B$7)*Config!$B$4,0) | AC78: =IF(Config!$B$7>0,(W78/Config!$B$7)*Config!$B$4,0)
A79: May | B79: 2026 | C79: 27-04-2026 | D79: 0.83001157 | E79: Makhana_7-2992 | F79: FG | G79: Roasted & Flavoured Makhana | H79: Roasted & Flavoured Peri Peri Makhana Farmley Jar 55 g | I79: Prasadam Roasted Makhana | J79: 0.055 | K79: 11558 | L79: GT Retail | M79: 635.69 | N79: Category A | O79: Purnea | P79: Value Added | Q79: Roasted & Flavoured Makhana | R79: =IF(Config!$B$4>0,M79/Config!$B$4,0) | S79: =IF(Config!$B$4>0,K79/Config!$B$4,0) | T79: =R79*Config!$B$7 | U79: =S79*Config!$B$7 | V79: 194.43 | W79: 3535 | X79: =IF(T79>0,V79/T79,0) | Y79: =IF(U79>0,W79/U79,0) | Z79: =T79-V79 | AA79: =U79-W79 | AB79: =IF(Config!$B$7>0,(V79/Config!$B$7)*Config!$B$4,0) | AC79: =IF(Config!$B$7>0,(W79/Config!$B$7)*Config!$B$4,0)
A80: May | B80: 2026 | C80: 27-04-2026 | D80: 0.83001157 | E80: Makhana_7-2995 | F80: FG | G80: Roasted & Flavoured Makhana | H80: Roasted & Flavoured Cream & Onion Makhana Farmley Jar 55 g | I80: Prasadam Roasted Makhana | J80: 0.055 | K80: 11155 | L80: GT Retail | M80: 613.52 | N80: Category A | O80: Purnea | P80: Value Added | Q80: Roasted & Flavoured Makhana | R80: =IF(Config!$B$4>0,M80/Config!$B$4,0) | S80: =IF(Config!$B$4>0,K80/Config!$B$4,0) | T80: =R80*Config!$B$7 | U80: =S80*Config!$B$7 | V80: 165.55 | W80: 3010 | X80: =IF(T80>0,V80/T80,0) | Y80: =IF(U80>0,W80/U80,0) | Z80: =T80-V80 | AA80: =U80-W80 | AB80: =IF(Config!$B$7>0,(V80/Config!$B$7)*Config!$B$4,0) | AC80: =IF(Config!$B$7>0,(W80/Config!$B$7)*Config!$B$4,0)
A81: May | B81: 2026 | C81: 27-04-2026 | D81: 0.83001157 | E81: Makhana_7-2998 | F81: FG | G81: Roasted & Flavoured Makhana | H81: Roasted & Flavoured Cheddar Cheese Makhana Farmley Jar 55 g | I81: Prasadam Roasted Makhana | J81: 0.055 | K81: 11000 | L81: GT Retail | M81: 605 | N81: Category A | O81: Purnea | P81: Value Added | Q81: Roasted & Flavoured Makhana | R81: =IF(Config!$B$4>0,M81/Config!$B$4,0) | S81: =IF(Config!$B$4>0,K81/Config!$B$4,0) | T81: =R81*Config!$B$7 | U81: =S81*Config!$B$7 | V81: 134.75 | W81: 2450 | X81: =IF(T81>0,V81/T81,0) | Y81: =IF(U81>0,W81/U81,0) | Z81: =T81-V81 | AA81: =U81-W81 | AB81: =IF(Config!$B$7>0,(V81/Config!$B$7)*Config!$B$4,0) | AC81: =IF(Config!$B$7>0,(W81/Config!$B$7)*Config!$B$4,0)
... A253: May | B253: 2026 | C253: 25-04-2026 | D253: 0.72671296 | E253: Makhana_7-30096 | F253: FG | G253: Makhana Raw | H253: Prasadam Makhana Center Seal Pouch 100 g- NEW | I253: Prasadam Makhana | J253: 0.1 | K253: 120 | L253: Natures Basket Limited | M253: 12 | N253: Modern Trade | O253: Purnea | P253: KVI | Q253: Makhana Raw | R253: =IF(Config!$B$4>0,M253/Config!$B$4,0) | S253: =IF(Config!$B$4>0,K253/Config!$B$4,0) | T253: =R253*Config!$B$7 | U253: =S253*Config!$B$7 | V253: 0 | W253: 0 | X253: =IF(T253>0,V253/T253,0) | Y253: =IF(U253>0,W253/U253,0) | Z253: =T253-V253 | AA253: =U253-W253 | AB253: =IF(Config!$B$7>0,(V253/Config!$B$7)*Config!$B$4,0) | AC253: =IF(Config!$B$7>0,(W253/Config!$B$7)*Config!$B$4,0)
E254: Makhana_7-2979 | G254: Makhana | H254: Roasted & Flavored Makhana -Cheddar Cheese Farmley Composite Jar 77 g | J254: 0 | K254: 0 | L254: Amazon Retail India Private Limited | M254: 0 | N254: Amazon Retail India | O254: Purnea | Q254: Roasted & Flavoured Makhana | R254: =IF(Config!$B$4>0,M254/Config!$B$4,0) | S254: =IF(Config!$B$4>0,K254/Config!$B$4,0) | T254: =R254*Config!$B$7 | U254: =S254*Config!$B$7 | V254: 40.66 | W254: 528 | X254: =IF(T254>0,V254/T254,0) | Y254: =IF(U254>0,W254/U254,0) | Z254: =T254-V254 | AA254: =U254-W254 | AB254: =IF(Config!$B$7>0,(V254/Config!$B$7)*Config!$B$4,0) | AC254: =IF(Config!$B$7>0,(W254/Config!$B$7)*Config!$B$4,0)
E255: Makhana_7-2980 | G255: Makhana | H255: Roasted & Flavored Makhana - Mint Farmley Composite Jar 77 g | J255: 0 | K255: 0 | L255: Amazon Retail India Private Limited | M255: 0 | N255: Amazon Retail India | O255: Purnea | Q255: Roasted & Flavoured Makhana | R255: =IF(Config!$B$4>0,M255/Config!$B$4,0) | S255: =IF(Config!$B$4>0,K255/Config!$B$4,0) | T255: =R255*Config!$B$7 | U255: =S255*Config!$B$7 | V255: 66.53 | W255: 864 | X255: =IF(T255>0,V255/T255,0) | Y255: =IF(U255>0,W255/U255,0) | Z255: =T255-V255 | AA255: =U255-W255 | AB255: =IF(Config!$B$7>0,(V255/Config!$B$7)*Config!$B$4,0) | AC255: =IF(Config!$B$7>0,(W255/Config!$B$7)*Config!$B$4,0)
E256: Makhana_7-2981 | G256: Makhana | H256: Roasted & Flavored Makhana - Black Pepper Farmley Composite jar 77 g | J256: 0 | K256: 0 | L256: Amazon Retail India Private Limited | M256: 0 | N256: Amazon Retail India | O256: Purnea | Q256: Roasted & Flavoured Makhana | R256: =IF(Config!$B$4>0,M256/Config!$B$4,0) | S256: =IF(Config!$B$4>0,K256/Config!$B$4,0) | T256: =R256*Config!$B$7 | U256: =S256*Config!$B$7 | V256: 5.54 | W256: 72 | X256: =IF(T256>0,V256/T256,0) | Y256: =IF(U256>0,W256/U256,0) | Z256: =T256-V256 | AA256: =U256-W256 | AB256: =IF(Config!$B$7>0,(V256/Config!$B$7)*Config!$B$4,0) | AC256: =IF(Config!$B$7>0,(W256/Config!$B$7)*Config!$B$4,0)
E257: Makhana_7-2983 | G257: Makhana | H257: Roasted & Flavored Makhana - Peri Peri Farmley Composite Jar 77 g | J257: 0 | K257: 0 | L257: Amazon Retail India Private Limited | M257: 0 | N257: Amazon Retail India | O257: Purnea | Q257: Roasted & Flavoured Makhana | R257: =IF(Config!$B$4>0,M257/Config!$B$4,0) | S257: =IF(Config!$B$4>0,K257/Config!$B$4,0) | T257: =R257*Config!$B$7 | U257: =S257*Config!$B$7 | V257: 44.35 | W257: 576 | X257: =IF(T257>0,V257/T257,0) | Y257: =IF(U257>0,W257/U257,0) | Z257: =T257-V257 | AA257: =U257-W257 | AB257: =IF(Config!$B$7>0,(V257/Config!$B$7)*Config!$B$4,0) | AC257: =IF(Config!$B$7>0,(W257/Config!$B$7)*Config!$B$4,0)
E258: Makhana_7-2984 | G258: Makhana | H258: Roasted & Salted Makhana Farmley Composite Jar 77 g | J258: 0 | K258: 0 | L258: Amazon Retail India Private Limited | M258: 0 | N258: Amazon Retail India | O258: Purnea | Q258: Roasted & Flavoured Makhana | R258: =IF(Config!$B$4>0,M258/Config!$B$4,0) | S258: =IF(Config!$B$4>0,K258/Config!$B$4,0) | T258: =R258*Config!$B$7 | U258: =S258*Config!$B$7 | V258: 136.75 | W258: 1776 | X258: =IF(T258>0,V258/T258,0) | Y258: =IF(U258>0,W258/U258,0) | Z258: =T258-V258 | AA258: =U258-W258 | AB258: =IF(Config!$B$7>0,(V258/Config!$B$7)*Config!$B$4,0) | AC258: =IF(Config!$B$7>0,(W258/Config!$B$7)*Config!$B$4,0)
E259: Makhana_7-2985 | G259: Makhana | H259: Roasted & Flavored Makhana - Tangy Tomato Farmley Composite Jar 77 g | J259: 0 | K259: 0 | L259: Amazon Retail India Private Limited | M259: 0 | N259: Amazon Retail India | O259: Purnea | Q259: Roasted & Flavoured Makhana | R259: =IF(Config!$B$4>0,M259/Config!$B$4,0) | S259: =IF(Config!$B$4>0,K259/Config!$B$4,0) | T259: =R259*Config!$B$7 | U259: =S259*Config!$B$7 | V259: 25.87 | W259: 336 | X259: =IF(T259>0,V259/T259,0) | Y259: =IF(U259>0,W259/U259,0) | Z259: =T259-V259 | AA259: =U259-W259 | AB259: =IF(Config!$B$7>0,(V259/Config!$B$7)*Config!$B$4,0) | AC259: =IF(Config!$B$7>0,(W259/Config!$B$7)*Config!$B$4,0)
E260: Makhana_7-2986 | G260: Makhana | H260: Roasted & Flavored Makhana -Cream and Onion Farmley Composite Jar 77 g | J260: 0 | K260: 0 | L260: Amazon Retail India Private Limited | M260: 0 | N260: Amazon Retail India | O260: Purnea | Q260: Roasted & Flavoured Makhana | R260: =IF(Config!$B$4>0,M260/Config!$B$4,0) | S260: =IF(Config!$B$4>0,K260/Config!$B$4,0) | T260: =R260*Config!$B$7 | U260: =S260*Config!$B$7 | V260: 142.3 | W260: 1848 | X260: =IF(T260>0,V260/T260,0) | Y260: =IF(U260>0,W260/U260,0) | Z260: =T260-V260 | AA260: =U260-W260 | AB260: =IF(Config!$B$7>0,(V260/Config!$B$7)*Config!$B$4,0) | AC260: =IF(Config!$B$7>0,(W260/Config!$B$7)*Config!$B$4,0)
E261: Makhana_7-3007 | G261: Makhana | H261: Roasted & Flavored Makhana Combo Farmley Jar 308 g - Pack of 4 (77 g Each) | J261: 0 | K261: 0 | L261: Amazon Retail India Private Limited | M261: 0 | N261: Amazon Retail India | O261: Purnea | Q261: Roasted & Flavoured Makhana | R261: =IF(Config!$B$4>0,M261/Config!$B$4,0) | S261: =IF(Config!$B$4>0,K261/Config!$B$4,0) | T261: =R261*Config!$B$7 | U261: =S261*Config!$B$7 | V261: 12.94 | W261: 42 | X261: =IF(T261>0,V261/T261,0) | Y261: =IF(U261>0,W261/U261,0) | Z261: =T261-V261 | AA261: =U261-W261 | AB261: =IF(Config!$B$7>0,(V261/Config!$B$7)*Config!$B$4,0) | AC261: =IF(Config!$B$7>0,(W261/Config!$B$7)*Config!$B$4,0)
E262: Makhana_7-2993 | G262: Makhana | H262: Roasted & Flavoured Minty Pudina Makhana Farmley Jar 55 g | J262: 0 | K262: 0 | L262: CPC - C P C Master Canteen -Khargone -Madhya Pradesh -451115 | M262: 0 | N262: CPC KPKB | O262: Purnea | Q262: Roasted & Flavoured Makhana | R262: =IF(Config!$B$4>0,M262/Config!$B$4,0) | S262: =IF(Config!$B$4>0,K262/Config!$B$4,0) | T262: =R262*Config!$B$7 | U262: =S262*Config!$B$7 | V262: 3.85 | W262: 70 | X262: =IF(T262>0,V262/T262,0) | Y262: =IF(U262>0,W262/U262,0) | Z262: =T262-V262 | AA262: =U262-W262 | AB262: =IF(Config!$B$7>0,(V262/Config!$B$7)*Config!$B$4,0) | AC262: =IF(Config!$B$7>0,(W262/Config!$B$7)*Config!$B$4,0)
E263: Makhana_7-2992 | G263: Makhana | H263: Roasted & Flavoured Peri Peri Makhana Farmley Jar 55 g | J263: 0 | K263: 0 | L263: CPC - Canteen Officer Master Canteen Frontier HQR SSB Lucknow | M263: 0 | N263: CPC KPKB | O263: Purnea | Q263: Roasted & Flavoured Makhana | R263: =IF(Config!$B$4>0,M263/Config!$B$4,0) | S263: =IF(Config!$B$4>0,K263/Config!$B$4,0) | T263: =R263*Config!$B$7 | U263: =S263*Config!$B$7 | V263: 5.78 | W263: 105 | X263: =IF(T263>0,V263/T263,0) | Y263: =IF(U263>0,W263/U263,0) | Z263: =T263-V263 | AA263: =U263-W263 | AB263: =IF(Config!$B$7>0,(V263/Config!$B$7)*Config!$B$4,0) | AC263: =IF(Config!$B$7>0,(W263/Config!$B$7)*Config!$B$4,0)
E264: Makhana_7-2993 | G264: Makhana | H264: Roasted & Flavoured Minty Pudina Makhana Farmley Jar 55 g | J264: 0 | K264: 0 | L264: CPC - Canteen Officer Master Canteen Frontier HQR SSB Lucknow | M264: 0 | N264: CPC KPKB | O264: Purnea | Q264: Roasted & Flavoured Makhana | R264: =IF(Config!$B$4>0,M264/Config!$B$4,0) | S264: =IF(Config!$B$4>0,K264/Config!$B$4,0) | T264: =R264*Config!$B$7 | U264: =S264*Config!$B$7 | V264: 3.85 | W264: 70 | X264: =IF(T264>0,V264/T264,0) | Y264: =IF(U264>0,W264/U264,0) | Z264: =T264-V264 | AA264: =U264-W264 | AB264: =IF(Config!$B$7>0,(V264/Config!$B$7)*Config!$B$4,0) | AC264: =IF(Config!$B$7>0,(W264/Config!$B$7)*Config!$B$4,0)
E265: Makhana_7-2994 | G265: Makhana | H265: Roasted & Salted Makhana Farmley Jar 55 g | J265: 0 | K265: 0 | L265: CPC - Canteen Officer Master Canteen Frontier HQR SSB Lucknow | M265: 0 | N265: CPC KPKB | O265: Purnea | Q265: Roasted & Flavoured Makhana | R265: =IF(Config!$B$4>0,M265/Config!$B$4,0) | S265: =IF(Config!$B$4>0,K265/Config!$B$4,0) | T265: =R265*Config!$B$7 | U265: =S265*Config!$B$7 | V265: 3.85 | W265: 70 | X265: =IF(T265>0,V265/T265,0) | Y265: =IF(U265>0,W265/U265,0) | Z265: =T265-V265 | AA265: =U265-W265 | AB265: =IF(Config!$B$7>0,(V265/Config!$B$7)*Config!$B$4,0) | AC265: =IF(Config!$B$7>0,(W265/Config!$B$7)*Config!$B$4,0)
... E458: Makhana_7-30074 | G458: Makhana | H458: Roasted & Flavoured Makhana - Cream & Onion Farmley Pillow Pouch 14g-Ladi | J458: 0 | K458: 0 | L458: Vendiman Private Limited | M458: 0 | N458: Vending | O458: Purnea | Q458: Roasted & Flavoured Makhana | R458: =IF(Config!$B$4>0,M458/Config!$B$4,0) | S458: =IF(Config!$B$4>0,K458/Config!$B$4,0) | T458: =R458*Config!$B$7 | U458: =S458*Config!$B$7 | V458: 16.8 | W458: 1200 | X458: =IF(T458>0,V458/T458,0) | Y458: =IF(U458>0,W458/U458,0) | Z458: =T458-V458 | AA458: =U458-W458 | AB458: =IF(Config!$B$7>0,(V458/Config!$B$7)*Config!$B$4,0) | AC458: =IF(Config!$B$7>0,(W458/Config!$B$7)*Config!$B$4,0)
A459: May | B459: 2026 | C459: 29-04-2026 | D459: 0.47065972 | E459: Multiple | F459: FG | G459: Seed Mix | H459: Indore | I459: Seed Mix | J459: 0.16 | K459: 4861459.8 | L459: 116 Customers | M459: 584578.98 | N459: Multiple | O459: Indore | P459: Value Added | Q459: Seed Mix | R459: =IF(Config!$B$4>0,M459/Config!$B$4,0) | S459: =IF(Config!$B$4>0,K459/Config!$B$4,0) | T459: =R459*Config!$B$7 | U459: =S459*Config!$B$7 | V459: 284728.15 | W459: 2391840 | X459: =IF(T459>0,V459/T459,0) | Y459: =IF(U459>0,W459/U459,0) | Z459: =T459-V459 | AA459: =U459-W459 | AB459: =IF(Config!$B$7>0,(V459/Config!$B$7)*Config!$B$4,0) | AC459: =IF(Config!$B$7>0,(W459/Config!$B$7)*Config!$B$4,0)
A460: May | B460: 2026 | C460: 29-04-2026 | D460: 0.47065972 | E460: Dry Fruit Mix_15-2941 | F460: FG | G460: Seed Mix | H460: Seed mix Farmley 160g Standee Pouches | I460: Seed Mix | J460: 0.16 | K460: 1590 | L460: Canteen Store Department (CSD) | M460: 254.4 | N460: CSD | O460: Indore | P460: Value Added | Q460: Seed Mix | R460: =IF(Config!$B$4>0,M460/Config!$B$4,0) | S460: =IF(Config!$B$4>0,K460/Config!$B$4,0) | T460: =R460*Config!$B$7 | U460: =S460*Config!$B$7 | V460: 0 | W460: 0 | X460: =IF(T460>0,V460/T460,0) | Y460: =IF(U460>0,W460/U460,0) | Z460: =T460-V460 | AA460: =U460-W460 | AB460: =IF(Config!$B$7>0,(V460/Config!$B$7)*Config!$B$4,0) | AC460: =IF(Config!$B$7>0,(W460/Config!$B$7)*Config!$B$4,0)
A461: May | B461: 2026 | C461: 29-04-2026 | D461: 0.47065972 | E461: Cashewnut_3-1987 | F461: FG | G461: Cashew | H461: Premium W320 Cashew Farmley Standee Pouch 500 g | I461: Premium W320 Cashew | J461: 0.5 | K461: 8700 | L461: CPC KPKB | M461: 4350 | N461: CPC | O461: Indore | P461: KVI | Q461: Cashew | R461: =IF(Config!$B$4>0,M461/Config!$B$4,0) | S461: =IF(Config!$B$4>0,K461/Config!$B$4,0) | T461: =R461*Config!$B$7 | U461: =S461*Config!$B$7 | V461: 0 | W461: 0 | X461: =IF(T461>0,V461/T461,0) | Y461: =IF(U461>0,W461/U461,0) | Z461: =T461-V461 | AA461: =U461-W461 | AB461: =IF(Config!$B$7>0,(V461/Config!$B$7)*Config!$B$4,0) | AC461: =IF(Config!$B$7>0,(W461/Config!$B$7)*Config!$B$4,0)
A462: May | B462: 2026 | C462: 29-04-2026 | D462: 0.47065972 | E462: Seeds_11-2541 | F462: FG | G462: Chia Seeds | H462: Premium Chia Seeds Farmley Standee Pouch 200 g | I462: Premium Chia Seeds | J462: 0.2 | K462: 1740 | L462: Canteen Store Department (CSD) | M462: 348 | N462: CSD | O462: Indore | P462: KVI | Q462: Chia Seeds | R462: =IF(Config!$B$4>0,M462/Config!$B$4,0) | S462: =IF(Config!$B$4>0,K462/Config!$B$4,0) | T462: =R462*Config!$B$7 | U462: =S462*Config!$B$7 | V462: 0 | W462: 0 | X462: =IF(T462>0,V462/T462,0) | Y462: =IF(U462>0,W462/U462,0) | Z462: =T462-V462 | AA462: =U462-W462 | AB462: =IF(Config!$B$7>0,(V462/Config!$B$7)*Config!$B$4,0) | AC462: =IF(Config!$B$7>0,(W462/Config!$B$7)*Config!$B$4,0)
A463: May | B463: 2026 | C463: 29-04-2026 | D463: 0.47065972 | E463: Almonds_1-1748 | F463: FG | G463: Almonds | H463: Premium California Almonds Farmley Standee Pouch 500 g | I463: Premium California Almonds | J463: 0.5 | K463: 9840 | L463: CPC KPKB | M463: 4920 | N463: CPC | O463: Indore | P463: KVI | Q463: Almonds | R463: =IF(Config!$B$4>0,M463/Config!$B$4,0) | S463: =IF(Config!$B$4>0,K463/Config!$B$4,0) | T463: =R463*Config!$B$7 | U463: =S463*Config!$B$7 | V463: 0 | W463: 0 | X463: =IF(T463>0,V463/T463,0) | Y463: =IF(U463>0,W463/U463,0) | Z463: =T463-V463 | AA463: =U463-W463 | AB463: =IF(Config!$B$7>0,(V463/Config!$B$7)*Config!$B$4,0) | AC463: =IF(Config!$B$7>0,(W463/Config!$B$7)*Config!$B$4,0)
